Workbook

Sheet Cover
A2: SEO KEYWORD RESEARCH & STRATEGY WORKBOOK
A3: Carter Family Dentistry, LLC | Rainsville, Alabama | United States Of America
A5: Prepared by Md. Abdul Alim – Dental SEO & AI Search Optimization Consultant
B8: Headline Numbers
B9: Keywords researched | C9: =COUNTA('Keyword Master Database'!$A$2:$A$137) -> 136
B10: Keyword clusters | C10: =COUNTA('Keyword Clusters'!A2:A20) -> 19
B11: Est. monthly volume – local + regional keywords | C11: =SUMIFS('Keyword Master Database'!$H$2:$H$137,'Keyword Master Database'!$Z$2:$Z$137,"<>National") -> 2570
B12: National benchmark keywords (excluded from volume) | C12: =COUNTIF('Keyword Master Database'!$Z$2:$Z$137,"National") -> 77
B13: Avg. est. KD – local + regional keywords | C13: =ROUND(SUMPRODUCT(('Keyword Master Database'!$Z$2:$Z$137<>"National")*'Keyword Master Database'!$I$2:$I$137)/(COUNTA('Keyword Master Database'!$A$2:$A$137)-COUNTIF('Keyword Master Database'!$Z$2:$Z$137,"National")),0) -> 11
B14: Critical + High priority keywords | C14: =COUNTIF('Keyword Master Database'!$V$2:$V$137,"Critical")+COUNTIF('Keyword Master Database'!$V$2:$V$137,"High") -> 70
B15: Pages mapped (existing + new) | C15: =COUNTA('Keyword Mapping'!A2:A51) -> 50
B16: New pages to create | C16: =COUNTIF('Keyword Mapping'!G2:G51,"New") -> 31
B17: Internal links planned | C17: =COUNTA('Internal Linking Blueprint'!A2:A129) -> 128
B18: Content roadmap items | C18: =COUNTA('Content Roadmap'!A2:A49) -> 48
B20: Search Intent Mix
B21: Informational | C21: =COUNTIF('Keyword Master Database'!$E$2:$E$137,B21) -> 30
B22: Navigational | C22: =COUNTIF('Keyword Master Database'!$E$2:$E$137,B22) -> 9
B23: Commercial | C23: =COUNTIF('Keyword Master Database'!$E$2:$E$137,B23) -> 37
B24: Transactional | C24: =COUNTIF('Keyword Master Database'!$E$2:$E$137,B24) -> 60
B26: Funnel Stage Mix
B27: TOFU | C27: =COUNTIF('Keyword Master Database'!$F$2:$F$137,B27) -> 30
B28: MOFU | C28: =COUNTIF('Keyword Master Database'!$F$2:$F$137,B28) -> 41
B29: BOFU | C29: =COUNTIF('Keyword Master Database'!$F$2:$F$137,B29) -> 65
B31: Priority Level Mix
B32: Critical | C32: =COUNTIF('Keyword Master Database'!$V$2:$V$137,B32) -> 6
B33: High | C33: =COUNTIF('Keyword Master Database'!$V$2:$V$137,B33) -> 64
B34: Medium | C34: =COUNTIF('Keyword Master Database'!$V$2:$V$137,B34) -> 42
B35: Low | C35: =COUNTIF('Keyword Master Database'!$V$2:$V$137,B35) -> 24
B36: Optional | C36: =COUNTIF('Keyword Master Database'!$V$2:$V$137,B36) -> 0
B38: Workbook Contents
B39: Business Analysis | C39: Client profile and live website review
B40: Keyword Master Database | C40: Keywords with intent, funnel, volume, KD, CPC and priority
B41: Keyword Clusters | C41: Keyword groups with questions and entities
B42: Competitor Analysis | C42: Client competitors and SERP competitor types
B43: Keyword Mapping | C43: One primary keyword per URL; cannibalization risk
B44: Topical Authority Map | C44: Topic depth for each service
B45: SEO Silo Architecture | C45: Proposed site structure
B46: Internal Linking Blueprint | C46: Planned links, anchors and purpose
B47: Content Roadmap | C47: Six-month publishing and optimization plan
B48: Quick Wins | C48: First-30-day opportunities
B49: Methodology | C49: Scoring model, assumptions and data notes

Sheet Business Analysis
A1: Business Analysis
A4: Field | B4: Detail
A5: Business Name | B5: Carter Family Dentistry, LLC
A6: Website | B6: https://www.carterdentistry.com/
A7: Industry | B7: Dental Clinic (general, restorative and cosmetic dentistry)
A8: Country | B8: United States
A9: Location | B9: 20 Bartlett Ave, Rainsville, AL 35986 – serves DeKalb County, Jackson County and surrounding areas
A10: Services | B10: Dental Exams; Emergency Exam; Digital Imaging; Fillings; Silver Diamine Fluoride (SDF); Crowns; Veneers; Bridges; Root Canals; Extractions; Implants; Dentures; Partial Dentures
A11: Products | B11: None – service business (no retail products)
A12: Primary Business Goals | B12: Generate more local leads; increase organic traffic; improve service page rankings; build topical authority
A13: Primary SEO Focus | B13: Local SEO
A14: Contact (per website) | B14: (256) 638-2121; info@carterdentistry.com; Mon–Fri 8am–5pm, closed Sat/Sun
A15: Provider | B15: Dr. Emily Carter
A17: Website Analysis – Current SEO Position
A18: Area | B18: Finding | C18: SEO Implication / Opportunity | D18: Type
A19: Title tag | B19: Homepage title: "Carter Family Dentistry, LLC | Dentist in Rainsville, AL | Dentist Near Me | Female Dentist" (91 characters). | C19: Strength: city and 'female dentist' differentiator are present. Gap: too long (truncates in search results) and 'Dentist Near Me' looks stuffed. Shorten to under ~60 characters, e.g. 'Dentist in Rainsville, AL | Carter Family Dentistry'. | D19: Observation
A20: Meta description | B20: Mentions Dr. Emily Carter, comprehensive general, restorative and cosmetic care, Rainsville, and the whole family. No phone number or call-to-action; appears longer than ~160 characters. | C20: Tighten to ~155 characters with a CTA and phone number. | D20: Observation
A21: Homepage H1 / copy | B21: The H1 is the brand name only. Most homepage text is short headings and images with little service or location copy. | C21: Add a keyword-led H1 (e.g. 'Family Dentist in Rainsville, AL') and 300–500 words covering services, towns served and insurance. | D21: Gap
A22: Service pages | B22: 13 dedicated service pages are linked in the navigation (exams, emergency exam, imaging, fillings, SDF, crowns, veneers, bridges, root canals, extractions, implants, dentures, partial dentures). | C22: Strong foundation for service-level targeting. Individual page copy was not audited in this version – review depth, headings and FAQs per page. | D22: Strength
A23: Service area | B23: Homepage says it serves DeKalb County, Jackson County and surrounding areas, but no dedicated service-area or town pages were found in the navigation. | C23: Create a service-area hub plus Fort Payne and Scottsboro pages. | D23: Gap
A24: Insurance | B24: Homepage states all major plans are accepted and the practice is in-network with Blue Cross Blue Shield of Alabama and Southland. No dedicated insurance/payment page in navigation. | C24: A dedicated insurance page targets high-intent 'dentist that accepts [insurance]' searches. | D24: Opportunity
A25: Content / blog | B25: No blog, resources or FAQ section appears in the main navigation. | C25: No TOFU/MOFU content exists to capture informational searches – see Content Roadmap. | D25: Gap
A26: Trust / E-E-A-T | B26: Meet Dr. Emily Carter, Meet the Team, Office Tour and Testimonials pages exist. | C26: Good trust assets; add credentials, reviewed-by bylines and review schema. | D26: Strength
A27: NAP & hours | B27: Name, address, phone, email and weekday hours (8am–5pm) are present on the homepage footer. | C27: Keep identical on GBP and directories; add LocalBusiness/Dentist schema. | D27: Strength
A28: Conversion path | B28: Appointment request page exists; new-patient forms are hosted on an external domain (patientviewer.com). | C28: Track clicks to the external form as a conversion event; add click-to-call tracking. | D28: Opportunity
A29: Freshness | B29: Footer copyright reads 2022, while the privacy notice link is dated 2026. | C29: Update the copyright year and publish new content to show the site is current. | D29: Observation
... A31: Brand collision | B31: A Boise, Idaho practice (carterfamilydds.com) shares the name 'Carter Family Dentistry'; Carter Braces (an orthodontist) is also in Rainsville. | C31: Always pair the brand with 'Rainsville, AL' and Dr. Emily Carter in titles, schema and citations to own the branded SERP. | D31: Risk

Sheet Keyword Master Database
A1: Keyword | B1: Keyword Type | C1: Parent Topic | D1: Cluster | E1: Search Intent | F1: Funnel Stage | G1: Primary / Secondary | H1: Search Volume (monthly) | I1: KD | J1: KD Source | K1: Estimated CPC (USD) | L1: CPC Source | M1: SERP Competition | N1: Ranking Competitors | O1: Business Value (1-5) | P1: Search Demand (1-5) | Q1: Ranking Opportunity (1-5) | R1: Intent Strength (1-5) | S1: Conversion Potential (1-5) | T1: Topical Importance (1-5) | U1: SEO Priority Score (0-100) | V1: Priority Level | W1: Target URL | X1: Recommended Action | Y1: Notes | Z1: Volume Scope
A2: carter family dentistry rainsville al | B2: Brand | C2: Carter Family Dentistry (Brand) | D2: Brand & Navigational | E2: Navigational | F2: BOFU | G2: Primary | H2: 90 | I2: 3 | J2: SERP Competition Analysis | K2: 1.2 | L2: Commercial Intent Analysis | M2: =LOOKUP(I2,Methodology!$B$46:$B$49,Methodology!$C$46:$C$49) -> Easy | N2: Own brand SERP; Facebook; directories; carterfamilydds.com (Boise, ID – name overlap) | O2: 4 | P2: =LOOKUP(H2,Methodology!$B$15:$B$19,Methodology!$C$15:$C$19) -> 3 | Q2: =LOOKUP(I2,Methodology!$B$23:$B$27,Methodology!$C$23:$C$27) -> 5 | R2: {=INDEX(Methodology!$C$31:$C$34,MATCH(E2,Methodology!$B$31:$B$34,0))} -> 3 | S2: 4 | T2: 3 | U2: =ROUND((O2*Methodology!$C$5+P2*Methodology!$C$6+Q2*Methodology!$C$7+R2*Methodology!$C$8+S2*Methodology!$C$9+T2*Methodology!$C$10)*20,0) -> 76 | V2: =LOOKUP(U2,Methodology!$B$38:$B$42,Methodology!$C$38:$C$42) -> High | W2: / | X2: Keep | Y2: Protect branded SERP; pair brand with city + Dr. Emily Carter in title/schema. | Z2: Local
A3: carter family dentistry | B3: Brand | C3: Carter Family Dentistry (Brand) | D3: Brand & Navigational | E3: Navigational | F3: BOFU | G3: Secondary | H3: 480 | I3: 8 | J3: SERP Competition Analysis | K3: 2.1 | L3: Commercial Intent Analysis | M3: =LOOKUP(I3,Methodology!$B$46:$B$49,Methodology!$C$46:$C$49) -> Easy | N3: Own brand SERP; Facebook; directories; carterfamilydds.com (Boise, ID – name overlap) | O3: 4 | P3: =LOOKUP(H3,Methodology!$B$15:$B$19,Methodology!$C$15:$C$19) -> 4 | Q3: =LOOKUP(I3,Methodology!$B$23:$B$27,Methodology!$C$23:$C$27) -> 5 | R3: {=INDEX(Methodology!$C$31:$C$34,MATCH(E3,Methodology!$B$31:$B$34,0))} -> 3 | S3: 4 | T3: 3 | U3: =ROUND((O3*Methodology!$C$5+P3*Methodology!$C$6+Q3*Methodology!$C$7+R3*Methodology!$C$8+S3*Methodology!$C$9+T3*Methodology!$C$10)*20,0) -> 79 | V3: =LOOKUP(U3,Methodology!$B$38:$B$42,Methodology!$C$38:$C$42) -> High | W3: / | X3: Optimize | Y3: Name overlap with a Boise, ID practice (carterfamilydds.com) – always disambiguate with Rainsville, AL. | Z3: National
A4: carterdentistry.com | B4: Brand | C4: Carter Family Dentistry (Brand) | D4: Brand & Navigational | E4: Navigational | F4: BOFU | G4: Secondary | H4: 40 | I4: 1 | J4: SERP Competition Analysis | K4: 0.5 | L4: Commercial Intent Analysis | M4: =LOOKUP(I4,Methodology!$B$46:$B$49,Methodology!$C$46:$C$49) -> Easy | N4: Own brand SERP; Facebook; directories; carterfamilydds.com (Boise, ID – name overlap) | O4: 4 | P4: =LOOKUP(H4,Methodology!$B$15:$B$19,Methodology!$C$15:$C$19) -> 2 | Q4: =LOOKUP(I4,Methodology!$B$23:$B$27,Methodology!$C$23:$C$27) -> 5 | R4: {=INDEX(Methodology!$C$31:$C$34,MATCH(E4,Methodology!$B$31:$B$34,0))} -> 3 | S4: 4 | T4: 3 | U4: =ROUND((O4*Methodology!$C$5+P4*Methodology!$C$6+Q4*Methodology!$C$7+R4*Methodology!$C$8+S4*Methodology!$C$9+T4*Methodology!$C$10)*20,0) -> 73 | V4: =LOOKUP(U4,Methodology!$B$38:$B$42,Methodology!$C$38:$C$42) -> Medium | W4: / | X4: Keep | Z4: Local
A5: carter family dentistry reviews | B5: Brand | C5: Carter Family Dentistry (Brand) | D5: Brand & Navigational | E5: Navigational | F5: MOFU | G5: Secondary | H5: 40 | I5: 6 | J5: SERP Competition Analysis | K5: 1.6 | L5: Commercial Intent Analysis | M5: =LOOKUP(I5,Methodology!$B$46:$B$49,Methodology!$C$46:$C$49) -> Easy | N5: Own brand SERP; Facebook; directories; carterfamilydds.com (Boise, ID – name overlap) | O5: 4 | P5: =LOOKUP(H5,Methodology!$B$15:$B$19,Methodology!$C$15:$C$19) -> 2 | Q5: =LOOKUP(I5,Methodology!$B$23:$B$27,Methodology!$C$23:$C$27) -> 5 | R5: {=INDEX(Methodology!$C$31:$C$34,MATCH(E5,Methodology!$B$31:$B$34,0))} -> 3 | S5: 4 | T5: 3 | U5: =ROUND((O5*Methodology!$C$5+P5*Methodology!$C$6+Q5*Methodology!$C$7+R5*Methodology!$C$8+S5*Methodology!$C$9+T5*Methodology!$C$10)*20,0) -> 73 | V5: =LOOKUP(U5,Methodology!$B$38:$B$42,Methodology!$C$38:$C$42) -> Medium | W5: /testimonials | X5: Optimize | Y5: Add review schema and embed Google reviews. | Z5: Local
A6: carter family dentistry phone number | B6: Brand | C6: Carter Family Dentistry (Brand) | D6: Brand & Navigational | E6: Navigational | F6: BOFU | G6: Secondary | H6: 30 | I6: 2 | J6: SERP Competition Analysis | K6: 1.1 | L6: Commercial Intent Analysis | M6: =LOOKUP(I6,Methodology!$B$46:$B$49,Methodology!$C$46:$C$49) -> Easy | N6: Own brand SERP; Facebook; directories; carterfamilydds.com (Boise, ID – name overlap) | O6: 4 | P6: =LOOKUP(H6,Methodology!$B$15:$B$19,Methodology!$C$15:$C$19) -> 2 | Q6: =LOOKUP(I6,Methodology!$B$23:$B$27,Methodology!$C$23:$C$27) -> 5 | R6: {=INDEX(Methodology!$C$31:$C$34,MATCH(E6,Methodology!$B$31:$B$34,0))} -> 3 | S6: 4 | T6: 3 | U6: =ROUND((O6*Methodology!$C$5+P6*Methodology!$C$6+Q6*Methodology!$C$7+R6*Methodology!$C$8+S6*Methodology!$C$9+T6*Methodology!$C$10)*20,0) -> 73 | V6: =LOOKUP(U6,Methodology!$B$38:$B$42,Methodology!$C$38:$C$42) -> Medium | W6: /contact | X6: Optimize | Y6: Click-to-call + NAP consistency: (256) 638-2121. | Z6: Local
A7: carter family dentistry hours | B7: Brand | C7: Carter Family Dentistry (Brand) | D7: Brand & Navigational | E7: Navigational | F7: BOFU | G7: Secondary | H7: 30 | I7: 2 | J7: SERP Competition Analysis | K7: 0.9 | L7: Commercial Intent Analysis | M7: =LOOKUP(I7,Methodology!$B$46:$B$49,Methodology!$C$46:$C$49) -> Easy | N7: Own brand SERP; Facebook; directories; carterfamilydds.com (Boise, ID – name overlap) | O7: 4 | P7: =LOOKUP(H7,Methodology!$B$15:$B$19,Methodology!$C$15:$C$19) -> 2 | Q7: =LOOKUP(I7,Methodology!$B$23:$B$27,Methodology!$C$23:$C$27) -> 5 | R7: {=INDEX(Methodology!$C$31:$C$34,MATCH(E7,Methodology!$B$31:$B$34,0))} -> 3 | S7: 4 | T7: 3 | U7: =ROUND((O7*Methodology!$C$5+P7*Methodology!$C$6+Q7*Methodology!$C$7+R7*Methodology!$C$8+S7*Methodology!$C$9+T7*Methodology!$C$10)*20,0) -> 73 | V7: =LOOKUP(U7,Methodology!$B$38:$B$42,Methodology!$C$38:$C$42) -> Medium | W7: /contact | X7: Optimize | Y7: Website lists Mon–Fri 8am–5pm; keep identical on GBP. | Z7: Local
A8: carter family dentistry insurance | B8: Brand | C8: Carter Family Dentistry (Brand) | D8: Brand & Navigational | E8: Navigational | F8: MOFU | G8: Secondary | H8: 20 | I8: 4 | J8: SERP Competition Analysis | K8: 1.8 | L8: Commercial Intent Analysis | M8: =LOOKUP(I8,Methodology!$B$46:$B$49,Methodology!$C$46:$C$49) -> Easy | N8: Own brand SERP; Facebook; directories; carterfamilydds.com (Boise, ID – name overlap) | O8: 4 | P8: =LOOKUP(H8,Methodology!$B$15:$B$19,Methodology!$C$15:$C$19) -> 2 | Q8: =LOOKUP(I8,Methodology!$B$23:$B$27,Methodology!$C$23:$C$27) -> 5 | R8: {=INDEX(Methodology!$C$31:$C$34,MATCH(E8,Methodology!$B$31:$B$34,0))} -> 3 | S8: 4 | T8: 3 | U8: =ROUND((O8*Methodology!$C$5+P8*Methodology!$C$6+Q8*Methodology!$C$7+R8*Methodology!$C$8+S8*Methodology!$C$9+T8*Methodology!$C$10)*20,0) -> 73 | V8: =LOOKUP(U8,Methodology!$B$38:$B$42,Methodology!$C$38:$C$42) -> Medium | W8: /dental-insurance-payment | X8: Create | Z8: Local
A9: dentist in rainsville al | B9: Local Service | C9: Dentist in Rainsville, AL | D9: Local Dentist – Rainsville & DeKalb | E9: Transactional | F9: BOFU | G9: Primary | H9: 110 | I9: 14 | J9: SERP Competition Analysis | K9: 6.4 | L9: Commercial Intent Analysis | M9: =LOOKUP(I9,Methodology!$B$46:$B$49,Methodology!$C$46:$C$49) -> Easy | N9: Local GBP pack; nearby dental practices (Fort Payne / Scottsboro area); Yelp; Healthgrades | O9: 5 | P9: =LOOKUP(H9,Methodology!$B$15:$B$19,Methodology!$C$15:$C$19) -> 3 | Q9: =LOOKUP(I9,Methodology!$B$23:$B$27,Methodology!$C$23:$C$27) -> 5 | R9: {=INDEX(Methodology!$C$31:$C$34,MATCH(E9,Methodology!$B$31:$B$34,0))} -> 5 | S9: 5 | T9: 5 | U9: =ROUND((O9*Methodology!$C$5+P9*Methodology!$C$6+Q9*Methodology!$C$7+R9*Methodology!$C$8+S9*Methodology!$C$9+T9*Methodology!$C$10)*20,0) -> 94 | V9: =LOOKUP(U9,Methodology!$B$38:$B$42,Methodology!$C$38:$C$42) -> Critical | W9: / | X9: Optimize | Y9: Core money keyword – homepage H1/title/body. | Z9: Local
A10: dentist rainsville alabama | B10: Location | C10: Dentist in Rainsville, AL | D10: Local Dentist – Rainsville & DeKalb | E10: Transactional | F10: BOFU | G10: Secondary | H10: 40 | I10: 12 | J10: SERP Competition Analysis | K10: 6.1 | L10: Commercial Intent Analysis | M10: =LOOKUP(I10,Methodology!$B$46:$B$49,Methodology!$C$46:$C$49) -> Easy | N10: Local GBP pack; nearby dental practices (Fort Payne / Scottsboro area); Yelp; Healthgrades | O10: 5 | P10: =LOOKUP(H10,Methodology!$B$15:$B$19,Methodology!$C$15:$C$19) -> 2 | Q10: =LOOKUP(I10,Methodology!$B$23:$B$27,Methodology!$C$23:$C$27) -> 5 | R10: {=INDEX(Methodology!$C$31:$C$34,MATCH(E10,Methodology!$B$31:$B$34,0))} -> 5 | S10: 5 | T10: 5 | U10: =ROUND((O10*Methodology!$C$5+P10*Methodology!$C$6+Q10*Methodology!$C$7+R10*Methodology!$C$8+S10*Methodology!$C$9+T10*Methodology!$C$10)*20,0) -> 91 | V10: =LOOKUP(U10,Methodology!$B$38:$B$42,Methodology!$C$38:$C$42) -> Critical | W10: / | X10: Optimize | Z10: Local
A11: dental office rainsville al | B11: Location | C11: Dentist in Rainsville, AL | D11: Local Dentist – Rainsville & DeKalb | E11: Transactional | F11: BOFU | G11: Secondary | H11: 30 | I11: 10 | J11: SERP Competition Analysis | K11: 5.4 | L11: Commercial Intent Analysis | M11: =LOOKUP(I11,Methodology!$B$46:$B$49,Methodology!$C$46:$C$49) -> Easy | N11: Local GBP pack; nearby dental practices (Fort Payne / Scottsboro area); Yelp; Healthgrades | O11: 5 | P11: =LOOKUP(H11,Methodology!$B$15:$B$19,Methodology!$C$15:$C$19) -> 2 | Q11: =LOOKUP(I11,Methodology!$B$23:$B$27,Methodology!$C$23:$C$27) -> 5 | R11: {=INDEX(Methodology!$C$31:$C$34,MATCH(E11,Methodology!$B$31:$B$34,0))} -> 5 | S11: 5 | T11: 5 | U11: =ROUND((O11*Methodology!$C$5+P11*Methodology!$C$6+Q11*Methodology!$C$7+R11*Methodology!$C$8+S11*Methodology!$C$9+T11*Methodology!$C$10)*20,0) -> 91 | V11: =LOOKUP(U11,Methodology!$B$38:$B$42,Methodology!$C$38:$C$42) -> Critical | W11: / | X11: Optimize | Z11: Local
A12: general dentist rainsville al | B12: Core Service | C12: Dentist in Rainsville, AL | D12: Local Dentist – Rainsville & DeKalb | E12: Transactional | F12: BOFU | G12: Secondary | H12: 30 | I12: 11 | J12: SERP Competition Analysis | K12: 6 | L12: Commercial Intent Analysis | M12: =LOOKUP(I12,Methodology!$B$46:$B$49,Methodology!$C$46:$C$49) -> Easy | N12: Local GBP pack; nearby dental practices (Fort Payne / Scottsboro area); Yelp; Healthgrades | O12: 5 | P12: =LOOKUP(H12,Methodology!$B$15:$B$19,Methodology!$C$15:$C$19) -> 2 | Q12: =LOOKUP(I12,Methodology!$B$23:$B$27,Methodology!$C$23:$C$27) -> 5 | R12: {=INDEX(Methodology!$C$31:$C$34,MATCH(E12,Methodology!$B$31:$B$34,0))} -> 5 | S12: 5 | T12: 5 | U12: =ROUND((O12*Methodology!$C$5+P12*Methodology!$C$6+Q12*Methodology!$C$7+R12*Methodology!$C$8+S12*Methodology!$C$9+T12*Methodology!$C$10)*20,0) -> 91 | V12: =LOOKUP(U12,Methodology!$B$38:$B$42,Methodology!$C$38:$C$42) -> Critical | W12: /services | X12: Optimize | Y12: Services hub page. | Z12: Local
A13: best dentist in rainsville al | B13: Commercial | C13: Dentist in Rainsville, AL | D13: Local Dentist – Rainsville & DeKalb | E13: Commercial | F13: MOFU | G13: Secondary | H13: 20 | I13: 13 | J13: SERP Competition Analysis | K13: 5.8 | L13: Commercial Intent Analysis | M13: =LOOKUP(I13,Methodology!$B$46:$B$49,Methodology!$C$46:$C$49) -> Easy | N13: Local GBP pack; nearby dental practices (Fort Payne / Scottsboro area); Yelp; Healthgrades | O13: 5 | P13: =LOOKUP(H13,Methodology!$B$15:$B$19,Methodology!$C$15:$C$19) -> 2 | Q13: =LOOKUP(I13,Methodology!$B$23:$B$27,Methodology!$C$23:$C$27) -> 5 | R13: {=INDEX(Methodology!$C$31:$C$34,MATCH(E13,Methodology!$B$31:$B$34,0))} -> 4 | S13: 3 | T13: 5 | U13: =ROUND((O13*Methodology!$C$5+P13*Methodology!$C$6+Q13*Methodology!$C$7+R13*Methodology!$C$8+S13*Methodology!$C$9+T13*Methodology!$C$10)*20,0) -> 82 | V13: =LOOKUP(U13,Methodology!$B$38:$B$42,Methodology!$C$38:$C$42) -> High | W13: / | X13: Optimize | Y13: Support with reviews / testimonials block. | Z13: Local
A14: affordable dentist rainsville al | B14: Commercial | C14: Dentist in Rainsville, AL | D14: Local Dentist – Rainsville & DeKalb | E14: Commercial | F14: MOFU | G14: Secondary | H14: 20 | I14: 10 | J14: SERP Competition Analysis | K14: 5.1 | L14: Commercial Intent Analysis | M14: =LOOKUP(I14,Methodology!$B$46:$B$49,Methodology!$C$46:$C$49) -> Easy | N14: Cost guides (Delta Dental, Colgate, Healthline); regional practices; directories | O14: 5 | P14: =LOOKUP(H14,Methodology!$B$15:$B$19,Methodology!$C$15:$C$19) -> 2 | Q14: =LOOKUP(I14,Methodology!$B$23:$B$27,Methodology!$C$23:$C$27) -> 5 | R14: {=INDEX(Methodology!$C$31:$C$34,MATCH(E14,Methodology!$B$31:$B$34,0))} -> 4 | S14: 3 | T14: 5 | U14: =ROUND((O14*Methodology!$C$5+P14*Methodology!$C$6+Q14*Methodology!$C$7+R14*Methodology!$C$8+S14*Methodology!$C$9+T14*Methodology!$C$10)*20,0) -> 82 | V14: =LOOKUP(U14,Methodology!$B$38:$B$42,Methodology!$C$38:$C$42) -> High | W14: /dental-insurance-payment | X14: Create | Y14: Website promises affordable pricing – back it with an insurance/payment page. | Z14: Local
A15: new patient dentist rainsville al | B15: Transactional | C15: Dentist in Rainsville, AL | D15: Local Dentist – Rainsville & DeKalb | E15: Transactional | F15: BOFU | G15: Secondary | H15: 20 | I15: 9 | J15: SERP Competition Analysis | K15: 6.5 | L15: Commercial Intent Analysis | M15: =LOOKUP(I15,Methodology!$B$46:$B$49,Methodology!$C$46:$C$49) -> Easy | N15: Local GBP pack; nearby dental practices (Fort Payne / Scottsboro area); Yelp; Healthgrades | O15: 5 | P15: =LOOKUP(H15,Methodology!$B$15:$B$19,Methodology!$C$15:$C$19) -> 2 | Q15: =LOOKUP(I15,Methodology!$B$23:$B$27,Methodology!$C$23:$C$27) -> 5 | R15: {=INDEX(Methodology!$C$31:$C$34,MATCH(E15,Methodology!$B$31:$B$34,0))} -> 5 | S15: 5 | T15: 5 | U15: =ROUND((O15*Methodology!$C$5+P15*Methodology!$C$6+Q15*Methodology!$C$7+R15*Methodology!$C$8+S15*Methodology!$C$9+T15*Methodology!$C$10)*20,0) -> 91 | V15: =LOOKUP(U15,Methodology!$B$38:$B$42,Methodology!$C$38:$C$42) -> Critical | W15: /appointment | X15: Optimize | Z15: Local
A16: dentist accepting new patients rainsville al | B16: Transactional | C16: Dentist in Rainsville, AL | D16: Local Dentist – Rainsville & DeKalb | E16: Transactional | F16: BOFU | G16: Secondary | H16: 20 | I16: 9 | J16: SERP Competition Analysis | K16: 6.5 | L16: Commercial Intent Analysis | M16: =LOOKUP(I16,Methodology!$B$46:$B$49,Methodology!$C$46:$C$49) -> Easy | N16: Local GBP pack; nearby dental practices (Fort Payne / Scottsboro area); Yelp; Healthgrades | O16: 5 | P16: =LOOKUP(H16,Methodology!$B$15:$B$19,Methodology!$C$15:$C$19) -> 2 | Q16: =LOOKUP(I16,Methodology!$B$23:$B$27,Methodology!$C$23:$C$27) -> 5 | R16: {=INDEX(Methodology!$C$31:$C$34,MATCH(E16,Methodology!$B$31:$B$34,0))} -> 5 | S16: 5 | T16: 5 | U16: =ROUND((O16*Methodology!$C$5+P16*Methodology!$C$6+Q16*Methodology!$C$7+R16*Methodology!$C$8+S16*Methodology!$C$9+T16*Methodology!$C$10)*20,0) -> 91 | V16: =LOOKUP(U16,Methodology!$B$38:$B$42,Methodology!$C$38:$C$42) -> Critical | W16: /appointment | X16: Optimize | Z16: Local
A17: dentist near me | B17: Transactional | C17: Dentist in Rainsville, AL | D17: Local Dentist – Rainsville & DeKalb | E17: Transactional | F17: BOFU | G17: Secondary | H17: 1220000 | I17: 78 | J17: SERP Competition Analysis | K17: 5.8 | L17: Commercial Intent Analysis | M17: =LOOKUP(I17,Methodology!$B$46:$B$49,Methodology!$C$46:$C$49) -> Very Competitive | N17: Local GBP pack; nearby dental practices (Fort Payne / Scottsboro area); Yelp; Healthgrades | O17: 5 | P17: =LOOKUP(H17,Methodology!$B$15:$B$19,Methodology!$C$15:$C$19) -> 5 | Q17: =LOOKUP(I17,Methodology!$B$23:$B$27,Methodology!$C$23:$C$27) -> 1 | R17: {=INDEX(Methodology!$C$31:$C$34,MATCH(E17,Methodology!$B$31:$B$34,0))} -> 5 | S17: 5 | T17: 5 | U17: =ROUND((O17*Methodology!$C$5+P17*Methodology!$C$6+Q17*Methodology!$C$7+R17*Methodology!$C$8+S17*Methodology!$C$9+T17*Methodology!$C$10)*20,0) -> 84 | V17: =LOOKUP(U17,Methodology!$B$38:$B$42,Methodology!$C$38:$C$42) -> High | W17: / | X17: Keep | Y17: Benchmark head term only – win via GBP proximity, reviews and NAP, not on-page targeting. | Z17: National
A18: dental exam rainsville al | B18: Core Service | C18: Dental Exams & Cleanings | D18: Exams & Preventive Care | E18: Transactional | F18: BOFU | G18: Primary | H18: 20 | I18: 9 | J18: SERP Competition Analysis | K18: 6.2 | L18: Commercial Intent Analysis | M18: =LOOKUP(I18,Methodology!$B$46:$B$49,Methodology!$C$46:$C$49) -> Easy | N18: Local GBP pack; nearby dental practices (Fort Payne / Scottsboro area); Yelp; Healthgrades | O18: 4 | P18: =LOOKUP(H18,Methodology!$B$15:$B$19,Methodology!$C$15:$C$19) -> 2 | Q18: =LOOKUP(I18,Methodology!$B$23:$B$27,Methodology!$C$23:$C$27) -> 5 | R18: {=INDEX(Methodology!$C$31:$C$34,MATCH(E18,Methodology!$B$31:$B$34,0))} -> 5 | S18: 5 | T18: 4 | U18: =ROUND((O18*Methodology!$C$5+P18*Methodology!$C$6+Q18*Methodology!$C$7+R18*Methodology!$C$8+S18*Methodology!$C$9+T18*Methodology!$C$10)*20,0) -> 84 | V18: =LOOKUP(U18,Methodology!$B$38:$B$42,Methodology!$C$38:$C$42) -> High | W18: /dental-exams | X18: Optimize | Z18: Local
A19: dental cleaning rainsville al | B19: Core Service | C19: Dental Exams & Cleanings | D19: Exams & Preventive Care | E19: Transactional | F19: BOFU | G19: Secondary | H19: 30 | I19: 10 | J19: SERP Competition Analysis | K19: 5.9 | L19: Commercial Intent Analysis | M19: =LOOKUP(I19,Methodology!$B$46:$B$49,Methodology!$C$46:$C$49) -> Easy | N19: Local GBP pack; nearby dental practices (Fort Payne / Scottsboro area); Yelp; Healthgrades | O19: 4 | P19: =LOOKUP(H19,Methodology!$B$15:$B$19,Methodology!$C$15:$C$19) -> 2 | Q19: =LOOKUP(I19,Methodology!$B$23:$B$27,Methodology!$C$23:$C$27) -> 5 | R19: {=INDEX(Methodology!$C$31:$C$34,MATCH(E19,Methodology!$B$31:$B$34,0))} -> 5 | S19: 5 | T19: 4 | U19: =ROUND((O19*Methodology!$C$5+P19*Methodology!$C$6+Q19*Methodology!$C$7+R19*Methodology!$C$8+S19*Methodology!$C$9+T19*Methodology!$C$10)*20,0) -> 84 | V19: =LOOKUP(U19,Methodology!$B$38:$B$42,Methodology!$C$38:$C$42) -> High | W19: /dental-exams | X19: Optimize | Z19: Local
A20: new patient dental exam | B20: Commercial | C20: Dental Exams & Cleanings | D20: Exams & Preventive Care | E20: Commercial | F20: MOFU | G20: Secondary | H20: 880 | I20: 38 | J20: SERP Competition Analysis | K20: 7.4 | L20: Commercial Intent Analysis | M20: =LOOKUP(I20,Methodology!$B$46:$B$49,Methodology!$C$46:$C$49) -> Moderate | N20: WebMD; Colgate; Healthline; Mayo Clinic; ADA MouthHealthy | O20: 4 | P20: =LOOKUP(H20,Methodology!$B$15:$B$19,Methodology!$C$15:$C$19) -> 4 | Q20: =LOOKUP(I20,Methodology!$B$23:$B$27,Methodology!$C$23:$C$27) -> 3 | R20: {=INDEX(Methodology!$C$31:$C$34,MATCH(E20,Methodology!$B$31:$B$34,0))} -> 4 | S20: 3 | T20: 4 | U20: =ROUND((O20*Methodology!$C$5+P20*Methodology!$C$6+Q20*Methodology!$C$7+R20*Methodology!$C$8+S20*Methodology!$C$9+T20*Methodology!$C$10)*20,0) -> 73 | V20: =LOOKUP(U20,Methodology!$B$38:$B$42,Methodology!$C$38:$C$42) -> Medium | W20: /dental-exams | X20: Optimize | Z20: National
A21: dental checkup near me | B21: Transactional | C21: Dental Exams & Cleanings | D21: Exams & Preventive Care | E21: Transactional | F21: BOFU | G21: Secondary | H21: 9900 | I21: 62 | J21: SERP Competition Analysis | K21: 6.8 | L21: Commercial Intent Analysis | M21: =LOOKUP(I21,Methodology!$B$46:$B$49,Methodology!$C$46:$C$49) -> Competitive | N21: Local GBP pack; nearby dental practices (Fort Payne / Scottsboro area); Yelp; Healthgrades | O21: 4 | P21: =LOOKUP(H21,Methodology!$B$15:$B$19,Methodology!$C$15:$C$19) -> 5 | Q21: =LOOKUP(I21,Methodology!$B$23:$B$27,Methodology!$C$23:$C$27) -> 1 | R21: {=INDEX(Methodology!$C$31:$C$34,MATCH(E21,Methodology!$B$31:$B$34,0))} -> 5 | S21: 5 | T21: 4 | U21: =ROUND((O21*Methodology!$C$5+P21*Methodology!$C$6+Q21*Methodology!$C$7+R21*Methodology!$C$8+S21*Methodology!$C$9+T21*Methodology!$C$10)*20,0) -> 77 | V21: =LOOKUP(U21,Methodology!$B$38:$B$42,Methodology!$C$38:$C$42) -> High | W21: /dental-exams | X21: Optimize | Z21: National
A22: teeth cleaning near me | B22: Transactional | C22: Dental Exams & Cleanings | D22: Exams & Preventive Care | E22: Transactional | F22: BOFU | G22: Secondary | H22: 33100 | I22: 66 | J22: SERP Competition Analysis | K22: 6.2 | L22: Commercial Intent Analysis | M22: =LOOKUP(I22,Methodology!$B$46:$B$49,Methodology!$C$46:$C$49) -> Competitive | N22: Local GBP pack; nearby dental practices (Fort Payne / Scottsboro area); Yelp; Healthgrades | O22: 4 | P22: =LOOKUP(H22,Methodology!$B$15:$B$19,Methodology!$C$15:$C$19) -> 5 | Q22: =LOOKUP(I22,Methodology!$B$23:$B$27,Methodology!$C$23:$C$27) -> 1 | R22: {=INDEX(Methodology!$C$31:$C$34,MATCH(E22,Methodology!$B$31:$B$34,0))} -> 5 | S22: 5 | T22: 4 | U22: =ROUND((O22*Methodology!$C$5+P22*Methodology!$C$6+Q22*Methodology!$C$7+R22*Methodology!$C$8+S22*Methodology!$C$9+T22*Methodology!$C$10)*20,0) -> 77 | V22: =LOOKUP(U22,Methodology!$B$38:$B$42,Methodology!$C$38:$C$42) -> High | W22: /dental-exams | X22: Optimize | Z22: National
A23: what happens at a dental exam | B23: Informational | C23: Dental Exams & Cleanings | D23: Exams & Preventive Care | E23: Informational | F23: TOFU | G23: Secondary | H23: 1600 | I23: 30 | J23: SERP Competition Analysis | K23: 2.1 | L23: Commercial Intent Analysis | M23: =LOOKUP(I23,Methodology!$B$46:$B$49,Methodology!$C$46:$C$49) -> Moderate | N23: WebMD; Colgate; Healthline; Mayo Clinic; ADA MouthHealthy | O23: 3 | P23: =LOOKUP(H23,Methodology!$B$15:$B$19,Methodology!$C$15:$C$19) -> 5 | Q23: =LOOKUP(I23,Methodology!$B$23:$B$27,Methodology!$C$23:$C$27) -> 3 | R23: {=INDEX(Methodology!$C$31:$C$34,MATCH(E23,Methodology!$B$31:$B$34,0))} -> 2 | S23: 1 | T23: 3 | U23: =ROUND((O23*Methodology!$C$5+P23*Methodology!$C$6+Q23*Methodology!$C$7+R23*Methodology!$C$8+S23*Methodology!$C$9+T23*Methodology!$C$10)*20,0) -> 57 | V23: =LOOKUP(U23,Methodology!$B$38:$B$42,Methodology!$C$38:$C$42) -> Low | W23: /blog/what-happens-at-a-dental-exam | X23: Create | Z23: National
A24: family dentist rainsville al | B24: Local Service | C24: Dental Exams & Cleanings | D24: Exams & Preventive Care | E24: Transactional | F24: BOFU | G24: Secondary | H24: 50 | I24: 12 | J24: SERP Competition Analysis | K24: 6 | L24: Commercial Intent Analysis | M24: =LOOKUP(I24,Methodology!$B$46:$B$49,Methodology!$C$46:$C$49) -> Easy | N24: Local GBP pack; nearby dental practices (Fort Payne / Scottsboro area); Yelp; Healthgrades | O24: 4 | P24: =LOOKUP(H24,Methodology!$B$15:$B$19,Methodology!$C$15:$C$19) -> 3 | Q24: =LOOKUP(I24,Methodology!$B$23:$B$27,Methodology!$C$23:$C$27) -> 5 | R24: {=INDEX(Methodology!$C$31:$C$34,MATCH(E24,Methodology!$B$31:$B$34,0))} -> 5 | S24: 5 | T24: 4 | U24: =ROUND((O24*Methodology!$C$5+P24*Methodology!$C$6+Q24*Methodology!$C$7+R24*Methodology!$C$8+S24*Methodology!$C$9+T24*Methodology!$C$10)*20,0) -> 87 | V24: =LOOKUP(U24,Methodology!$B$38:$B$42,Methodology!$C$38:$C$42) -> High | W24: /family-dentistry | X24: Create | Y24: Family-care page – keep distinct from homepage. | Z24: Local
A25: kids dentist rainsville al | B25: Local Service | C25: Dental Exams & Cleanings | D25: Exams & Preventive Care | E25: Transactional | F25: BOFU | G25: Secondary | H25: 20 | I25: 10 | J25: SERP Competition Analysis | K25: 5.8 | L25: Commercial Intent Analysis | M25: =LOOKUP(I25,Methodology!$B$46:$B$49,Methodology!$C$46:$C$49) -> Easy | N25: Local GBP pack; nearby dental practices (Fort Payne / Scottsboro area); Yelp; Healthgrades | O25: 4 | P25: =LOOKUP(H25,Methodology!$B$15:$B$19,Methodology!$C$15:$C$19) -> 2 | Q25: =LOOKUP(I25,Methodology!$B$23:$B$27,Methodology!$C$23:$C$27) -> 5 | R25: {=INDEX(Methodology!$C$31:$C$34,MATCH(E25,Methodology!$B$31:$B$34,0))} -> 5 | S25: 5 | T25: 4 | U25: =ROUND((O25*Methodology!$C$5+P25*Methodology!$C$6+Q25*Methodology!$C$7+R25*Methodology!$C$8+S25*Methodology!$C$9+T25*Methodology!$C$10)*20,0) -> 84 | V25: =LOOKUP(U25,Methodology!$B$38:$B$42,Methodology!$C$38:$C$42) -> High | W25: /family-dentistry | X25: Create | Y25: Confirm pediatric age range before publishing. | Z25: Local
A26: emergency dentist rainsville al | B26: Local Service | C26: Emergency Dentist | D26: Emergency Dental Care | E26: Transactional | F26: BOFU | G26: Primary | H26: 40 | I26: 14 | J26: SERP Competition Analysis | K26: 9.8 | L26: Commercial Intent Analysis | M26: =LOOKUP(I26,Methodology!$B$46:$B$49,Methodology!$C$46:$C$49) -> Easy | N26: Local GBP pack; nearby dental practices (Fort Payne / Scottsboro area); Yelp; Healthgrades | O26: 5 | P26: =LOOKUP(H26,Methodology!$B$15:$B$19,Methodology!$C$15:$C$19) -> 2 | Q26: =LOOKUP(I26,Methodology!$B$23:$B$27,Methodology!$C$23:$C$27) -> 5 | R26: {=INDEX(Methodology!$C$31:$C$34,MATCH(E26,Methodology!$B$31:$B$34,0))} -> 5 | S26: 5 | T26: 4 | U26: =ROUND((O26*Methodology!$C$5+P26*Methodology!$C$6+Q26*Methodology!$C$7+R26*Methodology!$C$8+S26*Methodology!$C$9+T26*Methodology!$C$10)*20,0) -> 89 | V26: =LOOKUP(U26,Methodology!$B$38:$B$42,Methodology!$C$38:$C$42) -> High | W26: /emergency-exam | X26: Optimize | Y26: Highest-urgency local lead keyword. | Z26: Local
A27: emergency dentist dekalb county al | B27: Location | C27: Emergency Dentist | D27: Emergency Dental Care | E27: Transactional | F27: BOFU | G27: Secondary | H27: 20 | I27: 15 | J27: SERP Competition Analysis | K27: 9.2 | L27: Commercial Intent Analysis | M27: =LOOKUP(I27,Methodology!$B$46:$B$49,Methodology!$C$46:$C$49) -> Easy | N27: Local GBP pack; nearby town practices; directories (Yelp / Healthgrades / Vitals) | O27: 5 | P27: =LOOKUP(H27,Methodology!$B$15:$B$19,Methodology!$C$15:$C$19) -> 2 | Q27: =LOOKUP(I27,Methodology!$B$23:$B$27,Methodology!$C$23:$C$27) -> 5 | R27: {=INDEX(Methodology!$C$31:$C$34,MATCH(E27,Methodology!$B$31:$B$34,0))} -> 5 | S27: 5 | T27: 4 | U27: =ROUND((O27*Methodology!$C$5+P27*Methodology!$C$6+Q27*Methodology!$C$7+R27*Methodology!$C$8+S27*Methodology!$C$9+T27*Methodology!$C$10)*20,0) -> 89 | V27: =LOOKUP(U27,Methodology!$B$38:$B$42,Methodology!$C$38:$C$42) -> High | W27: /emergency-exam | X27: Optimize | Z27: Regional
A28: dentist for tooth pain rainsville al | B28: Problem-Based | C28: Emergency Dentist | D28: Emergency Dental Care | E28: Transactional | F28: BOFU | G28: Secondary | H28: 10 | I28: 10 | J28: SERP Competition Analysis | K28: 8.4 | L28: Commercial Intent Analysis | M28: =LOOKUP(I28,Methodology!$B$46:$B$49,Methodology!$C$46:$C$49) -> Easy | N28: Local GBP pack; nearby dental practices (Fort Payne / Scottsboro area); Yelp; Healthgrades | O28: 5 | P28: =LOOKUP(H28,Methodology!$B$15:$B$19,Methodology!$C$15:$C$19) -> 1 | Q28: =LOOKUP(I28,Methodology!$B$23:$B$27,Methodology!$C$23:$C$27) -> 5 | R28: {=INDEX(Methodology!$C$31:$C$34,MATCH(E28,Methodology!$B$31:$B$34,0))} -> 5 | S28: 5 | T28: 4 | U28: =ROUND((O28*Methodology!$C$5+P28*Methodology!$C$6+Q28*Methodology!$C$7+R28*Methodology!$C$8+S28*Methodology!$C$9+T28*Methodology!$C$10)*20,0) -> 86 | V28: =LOOKUP(U28,Methodology!$B$38:$B$42,Methodology!$C$38:$C$42) -> High | W28: /emergency-exam | X28: Optimize | Z28: Local
A29: emergency dentist near me | B29: Transactional | C29: Emergency Dentist | D29: Emergency Dental Care | E29: Transactional | F29: BOFU | G29: Secondary | H29: 74000 | I29: 70 | J29: SERP Competition Analysis | K29: 11.4 | L29: Commercial Intent Analysis | M29: =LOOKUP(I29,Methodology!$B$46:$B$49,Methodology!$C$46:$C$49) -> Competitive | N29: Local GBP pack; nearby dental practices (Fort Payne / Scottsboro area); Yelp; Healthgrades | O29: 5 | P29: =LOOKUP(H29,Methodology!$B$15:$B$19,Methodology!$C$15:$C$19) -> 5 | Q29: =LOOKUP(I29,Methodology!$B$23:$B$27,Methodology!$C$23:$C$27) -> 1 | R29: {=INDEX(Methodology!$C$31:$C$34,MATCH(E29,Methodology!$B$31:$B$34,0))} -> 5 | S29: 5 | T29: 4 | U29: =ROUND((O29*Methodology!$C$5+P29*Methodology!$C$6+Q29*Methodology!$C$7+R29*Methodology!$C$8+S29*Methodology!$C$9+T29*Methodology!$C$10)*20,0) -> 82 | V29: =LOOKUP(U29,Methodology!$B$38:$B$42,Methodology!$C$38:$C$42) -> High | W29: /emergency-exam | X29: Optimize | Y29: Benchmark head term. | Z29: National
A30: same day dentist appointment near me | B30: Transactional | C30: Emergency Dentist | D30: Emergency Dental Care | E30: Transactional | F30: BOFU | G30: Secondary | H30: 5400 | I30: 48 | J30: SERP Competition Analysis | K30: 9.2 | L30: Commercial Intent Analysis | M30: =LOOKUP(I30,Methodology!$B$46:$B$49,Methodology!$C$46:$C$49) -> Competitive | N30: Local GBP pack; nearby dental practices (Fort Payne / Scottsboro area); Yelp; Healthgrades | O30: 5 | P30: =LOOKUP(H30,Methodology!$B$15:$B$19,Methodology!$C$15:$C$19) -> 5 | Q30: =LOOKUP(I30,Methodology!$B$23:$B$27,Methodology!$C$23:$C$27) -> 2 | R30: {=INDEX(Methodology!$C$31:$C$34,MATCH(E30,Methodology!$B$31:$B$34,0))} -> 5 | S30: 5 | T30: 4 | U30: =ROUND((O30*Methodology!$C$5+P30*Methodology!$C$6+Q30*Methodology!$C$7+R30*Methodology!$C$8+S30*Methodology!$C$9+T30*Methodology!$C$10)*20,0) -> 86 | V30: =LOOKUP(U30,Methodology!$B$38:$B$42,Methodology!$C$38:$C$42) -> High | W30: /emergency-exam | X30: Optimize | Z30: National
A31: what to do for a toothache at night | B31: Problem-Based | C31: Emergency Dentist | D31: Emergency Dental Care | E31: Informational | F31: TOFU | G31: Secondary | H31: 1900 | I31: 28 | J31: SERP Competition Analysis | K31: 1.4 | L31: Commercial Intent Analysis | M31: =LOOKUP(I31,Methodology!$B$46:$B$49,Methodology!$C$46:$C$49) -> Moderate | N31: WebMD; Colgate; Healthline; Mayo Clinic; ADA MouthHealthy | O31: 4 | P31: =LOOKUP(H31,Methodology!$B$15:$B$19,Methodology!$C$15:$C$19) -> 5 | Q31: =LOOKUP(I31,Methodology!$B$23:$B$27,Methodology!$C$23:$C$27) -> 3 | R31: {=INDEX(Methodology!$C$31:$C$34,MATCH(E31,Methodology!$B$31:$B$34,0))} -> 2 | S31: 1 | T31: 3 | U31: =ROUND((O31*Methodology!$C$5+P31*Methodology!$C$6+Q31*Methodology!$C$7+R31*Methodology!$C$8+S31*Methodology!$C$9+T31*Methodology!$C$10)*20,0) -> 62 | V31: =LOOKUP(U31,Methodology!$B$38:$B$42,Methodology!$C$38:$C$42) -> Medium | W31: /blog/toothache-at-night-what-to-do | X31: Create | Z31: National
A32: chipped tooth what to do | B32: Problem-Based | C32: Emergency Dentist | D32: Emergency Dental Care | E32: Informational | F32: TOFU | G32: Secondary | H32: 6600 | I32: 40 | J32: SERP Competition Analysis | K32: 3.1 | L32: Commercial Intent Analysis | M32: =LOOKUP(I32,Methodology!$B$46:$B$49,Methodology!$C$46:$C$49) -> Moderate | N32: WebMD; Colgate; Healthline; Mayo Clinic; ADA MouthHealthy | O32: 4 | P32: =LOOKUP(H32,Methodology!$B$15:$B$19,Methodology!$C$15:$C$19) -> 5 | Q32: =LOOKUP(I32,Methodology!$B$23:$B$27,Methodology!$C$23:$C$27) -> 3 | R32: {=INDEX(Methodology!$C$31:$C$34,MATCH(E32,Methodology!$B$31:$B$34,0))} -> 2 | S32: 1 | T32: 3 | U32: =ROUND((O32*Methodology!$C$5+P32*Methodology!$C$6+Q32*Methodology!$C$7+R32*Methodology!$C$8+S32*Methodology!$C$9+T32*Methodology!$C$10)*20,0) -> 62 | V32: =LOOKUP(U32,Methodology!$B$38:$B$42,Methodology!$C$38:$C$42) -> Medium | W32: /blog/dental-emergencies-chipped-or-knocked-out-tooth | X32: Create | Z32: National
A33: knocked out tooth what to do | B33: Problem-Based | C33: Emergency Dentist | D33: Emergency Dental Care | E33: Informational | F33: TOFU | G33: Secondary | H33: 2900 | I33: 36 | J33: SERP Competition Analysis | K33: 3.4 | L33: Commercial Intent Analysis | M33: =LOOKUP(I33,Methodology!$B$46:$B$49,Methodology!$C$46:$C$49) -> Moderate | N33: WebMD; Colgate; Healthline; Mayo Clinic; ADA MouthHealthy | O33: 4 | P33: =LOOKUP(H33,Methodology!$B$15:$B$19,Methodology!$C$15:$C$19) -> 5 | Q33: =LOOKUP(I33,Methodology!$B$23:$B$27,Methodology!$C$23:$C$27) -> 3 | R33: {=INDEX(Methodology!$C$31:$C$34,MATCH(E33,Methodology!$B$31:$B$34,0))} -> 2 | S33: 1 | T33: 3 | U33: =ROUND((O33*Methodology!$C$5+P33*Methodology!$C$6+Q33*Methodology!$C$7+R33*Methodology!$C$8+S33*Methodology!$C$9+T33*Methodology!$C$10)*20,0) -> 62 | V33: =LOOKUP(U33,Methodology!$B$38:$B$42,Methodology!$C$38:$C$42) -> Medium | W33: /blog/dental-emergencies-chipped-or-knocked-out-tooth | X33: Create | Z33: National
A34: dental abscess symptoms | B34: Problem-Based | C34: Emergency Dentist | D34: Emergency Dental Care | E34: Informational | F34: TOFU | G34: Secondary | H34: 8100 | I34: 48 | J34: SERP Competition Analysis | K34: 2.2 | L34: Commercial Intent Analysis | M34: =LOOKUP(I34,Methodology!$B$46:$B$49,Methodology!$C$46:$C$49) -> Competitive | N34: WebMD; Colgate; Healthline; Mayo Clinic; ADA MouthHealthy | O34: 4 | P34: =LOOKUP(H34,Methodology!$B$15:$B$19,Methodology!$C$15:$C$19) -> 5 | Q34: =LOOKUP(I34,Methodology!$B$23:$B$27,Methodology!$C$23:$C$27) -> 2 | R34: {=INDEX(Methodology!$C$31:$C$34,MATCH(E34,Methodology!$B$31:$B$34,0))} -> 2 | S34: 1 | T34: 3 | U34: =ROUND((O34*Methodology!$C$5+P34*Methodology!$C$6+Q34*Methodology!$C$7+R34*Methodology!$C$8+S34*Methodology!$C$9+T34*Methodology!$C$10)*20,0) -> 58 | V34: =LOOKUP(U34,Methodology!$B$38:$B$42,Methodology!$C$38:$C$42) -> Low | W34: /blog/dental-abscess-symptoms-when-to-seek-care | X34: Create | Z34: National
A35: dental fillings rainsville al | B35: Core Service | C35: Dental Fillings | D35: Fillings & Cavity Care | E35: Transactional | F35: BOFU | G35: Primary | H35: 20 | I35: 10 | J35: SERP Competition Analysis | K35: 5.7 | L35: Commercial Intent Analysis | M35: =LOOKUP(I35,Methodology!$B$46:$B$49,Methodology!$C$46:$C$49) -> Easy | N35: Local GBP pack; nearby dental practices (Fort Payne / Scottsboro area); Yelp; Healthgrades | O35: 3 | P35: =LOOKUP(H35,Methodology!$B$15:$B$19,Methodology!$C$15:$C$19) -> 2 | Q35: =LOOKUP(I35,Methodology!$B$23:$B$27,Methodology!$C$23:$C$27) -> 5 | R35: {=INDEX(Methodology!$C$31:$C$34,MATCH(E35,Methodology!$B$31:$B$34,0))} -> 5 | S35: 5 | T35: 4 | U35: =ROUND((O35*Methodology!$C$5+P35*Methodology!$C$6+Q35*Methodology!$C$7+R35*Methodology!$C$8+S35*Methodology!$C$9+T35*Methodology!$C$10)*20,0) -> 79 | V35: =LOOKUP(U35,Methodology!$B$38:$B$42,Methodology!$C$38:$C$42) -> High | W35: /fillings | X35: Optimize | Z35: Local
A36: tooth filling near me | B36: Transactional | C36: Dental Fillings | D36: Fillings & Cavity Care | E36: Transactional | F36: BOFU | G36: Secondary | H36: 8100 | I36: 55 | J36: SERP Competition Analysis | K36: 6.5 | L36: Commercial Intent Analysis | M36: =LOOKUP(I36,Methodology!$B$46:$B$49,Methodology!$C$46:$C$49) -> Competitive | N36: Local GBP pack; nearby dental practices (Fort Payne / Scottsboro area); Yelp; Healthgrades | O36: 3 | P36: =LOOKUP(H36,Methodology!$B$15:$B$19,Methodology!$C$15:$C$19) -> 5 | Q36: =LOOKUP(I36,Methodology!$B$23:$B$27,Methodology!$C$23:$C$27) -> 2 | R36: {=INDEX(Methodology!$C$31:$C$34,MATCH(E36,Methodology!$B$31:$B$34,0))} -> 5 | S36: 5 | T36: 4 | U36: =ROUND((O36*Methodology!$C$5+P36*Methodology!$C$6+Q36*Methodology!$C$7+R36*Methodology!$C$8+S36*Methodology!$C$9+T36*Methodology!$C$10)*20,0) -> 76 | V36: =LOOKUP(U36,Methodology!$B$38:$B$42,Methodology!$C$38:$C$42) -> High | W36: /fillings | X36: Optimize | Z36: National
A37: cavity filling cost | B37: Commercial | C37: Dental Fillings | D37: Fillings & Cavity Care | E37: Commercial | F37: MOFU | G37: Secondary | H37: 4400 | I37: 45 | J37: SERP Competition Analysis | K37: 5.6 | L37: Commercial Intent Analysis | M37: =LOOKUP(I37,Methodology!$B$46:$B$49,Methodology!$C$46:$C$49) -> Competitive | N37: Cost guides (Delta Dental, Colgate, Healthline); regional practices; directories | O37: 3 | P37: =LOOKUP(H37,Methodology!$B$15:$B$19,Methodology!$C$15:$C$19) -> 5 | Q37: =LOOKUP(I37,Methodology!$B$23:$B$27,Methodology!$C$23:$C$27) -> 2 | R37: {=INDEX(Methodology!$C$31:$C$34,MATCH(E37,Methodology!$B$31:$B$34,0))} -> 4 | S37: 3 | T37: 4 | U37: =ROUND((O37*Methodology!$C$5+P37*Methodology!$C$6+Q37*Methodology!$C$7+R37*Methodology!$C$8+S37*Methodology!$C$9+T37*Methodology!$C$10)*20,0) -> 67 | V37: =LOOKUP(U37,Methodology!$B$38:$B$42,Methodology!$C$38:$C$42) -> Medium | W37: /fillings | X37: Optimize | Z37: National
A38: white fillings | B38: Commercial | C38: Dental Fillings | D38: Fillings & Cavity Care | E38: Commercial | F38: MOFU | G38: Secondary | H38: 3600 | I38: 40 | J38: SERP Competition Analysis | K38: 3.9 | L38: Commercial Intent Analysis | M38: =LOOKUP(I38,Methodology!$B$46:$B$49,Methodology!$C$46:$C$49) -> Moderate | N38: WebMD; Colgate; Healthline; Mayo Clinic; ADA MouthHealthy | O38: 3 | P38: =LOOKUP(H38,Methodology!$B$15:$B$19,Methodology!$C$15:$C$19) -> 5 | Q38: =LOOKUP(I38,Methodology!$B$23:$B$27,Methodology!$C$23:$C$27) -> 3 | R38: {=INDEX(Methodology!$C$31:$C$34,MATCH(E38,Methodology!$B$31:$B$34,0))} -> 4 | S38: 3 | T38: 4 | U38: =ROUND((O38*Methodology!$C$5+P38*Methodology!$C$6+Q38*Methodology!$C$7+R38*Methodology!$C$8+S38*Methodology!$C$9+T38*Methodology!$C$10)*20,0) -> 71 | V38: =LOOKUP(U38,Methodology!$B$38:$B$42,Methodology!$C$38:$C$42) -> Medium | W38: /fillings | X38: Optimize | Z38: National
A39: composite vs amalgam fillings | B39: Comparison | C39: Dental Fillings | D39: Fillings & Cavity Care | E39: Commercial | F39: MOFU | G39: Secondary | H39: 1900 | I39: 38 | J39: SERP Competition Analysis | K39: 2.4 | L39: Commercial Intent Analysis | M39: =LOOKUP(I39,Methodology!$B$46:$B$49,Methodology!$C$46:$C$49) -> Moderate | N39: WebMD; Colgate; Healthline; Mayo Clinic; ADA MouthHealthy | O39: 3 | P39: =LOOKUP(H39,Methodology!$B$15:$B$19,Methodology!$C$15:$C$19) -> 5 | Q39: =LOOKUP(I39,Methodology!$B$23:$B$27,Methodology!$C$23:$C$27) -> 3 | R39: {=INDEX(Methodology!$C$31:$C$34,MATCH(E39,Methodology!$B$31:$B$34,0))} -> 4 | S39: 3 | T39: 4 | U39: =ROUND((O39*Methodology!$C$5+P39*Methodology!$C$6+Q39*Methodology!$C$7+R39*Methodology!$C$8+S39*Methodology!$C$9+T39*Methodology!$C$10)*20,0) -> 71 | V39: =LOOKUP(U39,Methodology!$B$38:$B$42,Methodology!$C$38:$C$42) -> Medium | W39: /blog/composite-vs-amalgam-fillings | X39: Create | Z39: National
A40: signs of a cavity | B40: Problem-Based | C40: Dental Fillings | D40: Fillings & Cavity Care | E40: Informational | F40: TOFU | G40: Secondary | H40: 6600 | I40: 42 | J40: SERP Competition Analysis | K40: 1.9 | L40: Commercial Intent Analysis | M40: =LOOKUP(I40,Methodology!$B$46:$B$49,Methodology!$C$46:$C$49) -> Competitive | N40: WebMD; Colgate; Healthline; Mayo Clinic; ADA MouthHealthy | O40: 2 | P40: =LOOKUP(H40,Methodology!$B$15:$B$19,Methodology!$C$15:$C$19) -> 5 | Q40: =LOOKUP(I40,Methodology!$B$23:$B$27,Methodology!$C$23:$C$27) -> 2 | R40: {=INDEX(Methodology!$C$31:$C$34,MATCH(E40,Methodology!$B$31:$B$34,0))} -> 2 | S40: 1 | T40: 3 | U40: =ROUND((O40*Methodology!$C$5+P40*Methodology!$C$6+Q40*Methodology!$C$7+R40*Methodology!$C$8+S40*Methodology!$C$9+T40*Methodology!$C$10)*20,0) -> 48 | V40: =LOOKUP(U40,Methodology!$B$38:$B$42,Methodology!$C$38:$C$42) -> Low | W40: /blog/signs-of-a-cavity | X40: Create | Z40: National
A41: how to prevent cavities | B41: Informational | C41: Dental Fillings | D41: Fillings & Cavity Care | E41: Informational | F41: TOFU | G41: Secondary | H41: 4400 | I41: 40 | J41: SERP Competition Analysis | K41: 1.6 | L41: Commercial Intent Analysis | M41: =LOOKUP(I41,Methodology!$B$46:$B$49,Methodology!$C$46:$C$49) -> Moderate | N41: WebMD; Colgate; Healthline; Mayo Clinic; ADA MouthHealthy | O41: 2 | P41: =LOOKUP(H41,Methodology!$B$15:$B$19,Methodology!$C$15:$C$19) -> 5 | Q41: =LOOKUP(I41,Methodology!$B$23:$B$27,Methodology!$C$23:$C$27) -> 3 | R41: {=INDEX(Methodology!$C$31:$C$34,MATCH(E41,Methodology!$B$31:$B$34,0))} -> 2 | S41: 1 | T41: 3 | U41: =ROUND((O41*Methodology!$C$5+P41*Methodology!$C$6+Q41*Methodology!$C$7+R41*Methodology!$C$8+S41*Methodology!$C$9+T41*Methodology!$C$10)*20,0) -> 52 | V41: =LOOKUP(U41,Methodology!$B$38:$B$42,Methodology!$C$38:$C$42) -> Low | W41: /blog/how-to-prevent-cavities | X41: Create | Z41: National
A42: silver diamine fluoride rainsville al | B42: Local Service | C42: Silver Diamine Fluoride | D42: Silver Diamine Fluoride (SDF) | E42: Transactional | F42: BOFU | G42: Primary | H42: 10 | I42: 6 | J42: SERP Competition Analysis | K42: 4.5 | L42: Commercial Intent Analysis | M42: =LOOKUP(I42,Methodology!$B$46:$B$49,Methodology!$C$46:$C$49) -> Easy | N42: Local GBP pack; nearby dental practices (Fort Payne / Scottsboro area); Yelp; Healthgrades | O42: 3 | P42: =LOOKUP(H42,Methodology!$B$15:$B$19,Methodology!$C$15:$C$19) -> 1 | Q42: =LOOKUP(I42,Methodology!$B$23:$B$27,Methodology!$C$23:$C$27) -> 5 | R42: {=INDEX(Methodology!$C$31:$C$34,MATCH(E42,Methodology!$B$31:$B$34,0))} -> 5 | S42: 5 | T42: 3 | U42: =ROUND((O42*Methodology!$C$5+P42*Methodology!$C$6+Q42*Methodology!$C$7+R42*Methodology!$C$8+S42*Methodology!$C$9+T42*Methodology!$C$10)*20,0) -> 74 | V42: =LOOKUP(U42,Methodology!$B$38:$B$42,Methodology!$C$38:$C$42) -> Medium | W42: /silver-diamine-fluoride | X42: Optimize | Y42: Low-competition differentiator service. | Z42: Local
A43: silver diamine fluoride | B43: Core Service | C43: Silver Diamine Fluoride | D43: Silver Diamine Fluoride (SDF) | E43: Informational | F43: TOFU | G43: Secondary | H43: 12100 | I43: 36 | J43: SERP Competition Analysis | K43: 2.9 | L43: Commercial Intent Analysis | M43: =LOOKUP(I43,Methodology!$B$46:$B$49,Methodology!$C$46:$C$49) -> Moderate | N43: WebMD; Colgate; Healthline; Mayo Clinic; ADA MouthHealthy | O43: 2 | P43: =LOOKUP(H43,Methodology!$B$15:$B$19,Methodology!$C$15:$C$19) -> 5 | Q43: =LOOKUP(I43,Methodology!$B$23:$B$27,Methodology!$C$23:$C$27) -> 3 | R43: {=INDEX(Methodology!$C$31:$C$34,MATCH(E43,Methodology!$B$31:$B$34,0))} -> 2 | S43: 1 | T43: 2 | U43: =ROUND((O43*Methodology!$C$5+P43*Methodology!$C$6+Q43*Methodology!$C$7+R43*Methodology!$C$8+S43*Methodology!$C$9+T43*Methodology!$C$10)*20,0) -> 50 | V43: =LOOKUP(U43,Methodology!$B$38:$B$42,Methodology!$C$38:$C$42) -> Low | W43: /silver-diamine-fluoride | X43: Optimize | Z43: National
A44: silver diamine fluoride for adults | B44: Informational | C44: Silver Diamine Fluoride | D44: Silver Diamine Fluoride (SDF) | E44: Informational | F44: TOFU | G44: Secondary | H44: 1000 | I44: 28 | J44: SERP Competition Analysis | K44: 2.6 | L44: Commercial Intent Analysis | M44: =LOOKUP(I44,Methodology!$B$46:$B$49,Methodology!$C$46:$C$49) -> Moderate | N44: WebMD; Colgate; Healthline; Mayo Clinic; ADA MouthHealthy | O44: 2 | P44: =LOOKUP(H44,Methodology!$B$15:$B$19,Methodology!$C$15:$C$19) -> 5 | Q44: =LOOKUP(I44,Methodology!$B$23:$B$27,Methodology!$C$23:$C$27) -> 3 | R44: {=INDEX(Methodology!$C$31:$C$34,MATCH(E44,Methodology!$B$31:$B$34,0))} -> 2 | S44: 1 | T44: 2 | U44: =ROUND((O44*Methodology!$C$5+P44*Methodology!$C$6+Q44*Methodology!$C$7+R44*Methodology!$C$8+S44*Methodology!$C$9+T44*Methodology!$C$10)*20,0) -> 50 | V44: =LOOKUP(U44,Methodology!$B$38:$B$42,Methodology!$C$38:$C$42) -> Low | W44: /silver-diamine-fluoride | X44: Optimize | Z44: National
A45: silver diamine fluoride cost | B45: Commercial | C45: Silver Diamine Fluoride | D45: Silver Diamine Fluoride (SDF) | E45: Commercial | F45: MOFU | G45: Secondary | H45: 480 | I45: 26 | J45: SERP Competition Analysis | K45: 3.8 | L45: Commercial Intent Analysis | M45: =LOOKUP(I45,Methodology!$B$46:$B$49,Methodology!$C$46:$C$49) -> Moderate | N45: Cost guides (Delta Dental, Colgate, Healthline); regional practices; directories | O45: 3 | P45: =LOOKUP(H45,Methodology!$B$15:$B$19,Methodology!$C$15:$C$19) -> 4 | Q45: =LOOKUP(I45,Methodology!$B$23:$B$27,Methodology!$C$23:$C$27) -> 3 | R45: {=INDEX(Methodology!$C$31:$C$34,MATCH(E45,Methodology!$B$31:$B$34,0))} -> 4 | S45: 3 | T45: 3 | U45: =ROUND((O45*Methodology!$C$5+P45*Methodology!$C$6+Q45*Methodology!$C$7+R45*Methodology!$C$8+S45*Methodology!$C$9+T45*Methodology!$C$10)*20,0) -> 66 | V45: =LOOKUP(U45,Methodology!$B$38:$B$42,Methodology!$C$38:$C$42) -> Medium | W45: /silver-diamine-fluoride | X45: Optimize | Z45: National
A46: silver diamine fluoride side effects | B46: Informational | C46: Silver Diamine Fluoride | D46: Silver Diamine Fluoride (SDF) | E46: Informational | F46: TOFU | G46: Secondary | H46: 1600 | I46: 30 | J46: SERP Competition Analysis | K46: 1.7 | L46: Commercial Intent Analysis | M46: =LOOKUP(I46,Methodology!$B$46:$B$49,Methodology!$C$46:$C$49) -> Moderate | N46: WebMD; Colgate; Healthline; Mayo Clinic; ADA MouthHealthy | O46: 2 | P46: =LOOKUP(H46,Methodology!$B$15:$B$19,Methodology!$C$15:$C$19) -> 5 | Q46: =LOOKUP(I46,Methodology!$B$23:$B$27,Methodology!$C$23:$C$27) -> 3 | R46: {=INDEX(Methodology!$C$31:$C$34,MATCH(E46,Methodology!$B$31:$B$34,0))} -> 2 | S46: 1 | T46: 2 | U46: =ROUND((O46*Methodology!$C$5+P46*Methodology!$C$6+Q46*Methodology!$C$7+R46*Methodology!$C$8+S46*Methodology!$C$9+T46*Methodology!$C$10)*20,0) -> 50 | V46: =LOOKUP(U46,Methodology!$B$38:$B$42,Methodology!$C$38:$C$42) -> Low | W46: /blog/silver-diamine-fluoride-side-effects | X46: Create | Z46: National
A47: dental crowns rainsville al | B47: Core Service | C47: Dental Crowns | D47: Dental Crowns | E47: Transactional | F47: BOFU | G47: Primary | H47: 20 | I47: 10 | J47: SERP Competition Analysis | K47: 8.8 | L47: Commercial Intent Analysis | M47: =LOOKUP(I47,Methodology!$B$46:$B$49,Methodology!$C$46:$C$49) -> Easy | N47: Local GBP pack; nearby dental practices (Fort Payne / Scottsboro area); Yelp; Healthgrades | O47: 4 | P47: =LOOKUP(H47,Methodology!$B$15:$B$19,Methodology!$C$15:$C$19) -> 2 | Q47: =LOOKUP(I47,Methodology!$B$23:$B$27,Methodology!$C$23:$C$27) -> 5 | R47: {=INDEX(Methodology!$C$31:$C$34,MATCH(E47,Methodology!$B$31:$B$34,0))} -> 5 | S47: 5 | T47: 4 | U47: =ROUND((O47*Methodology!$C$5+P47*Methodology!$C$6+Q47*Methodology!$C$7+R47*Methodology!$C$8+S47*Methodology!$C$9+T47*Methodology!$C$10)*20,0) -> 84 | V47: =LOOKUP(U47,Methodology!$B$38:$B$42,Methodology!$C$38:$C$42) -> High | W47: /crowns | X47: Optimize | Z47: Local
A48: dental crown cost | B48: Commercial | C48: Dental Crowns | D48: Dental Crowns | E48: Commercial | F48: MOFU | G48: Secondary | H48: 22200 | I48: 55 | J48: SERP Competition Analysis | K48: 7.9 | L48: Commercial Intent Analysis | M48: =LOOKUP(I48,Methodology!$B$46:$B$49,Methodology!$C$46:$C$49) -> Competitive | N48: Cost guides (Delta Dental, Colgate, Healthline); regional practices; directories | O48: 4 | P48: =LOOKUP(H48,Methodology!$B$15:$B$19,Methodology!$C$15:$C$19) -> 5 | Q48: =LOOKUP(I48,Methodology!$B$23:$B$27,Methodology!$C$23:$C$27) -> 2 | R48: {=INDEX(Methodology!$C$31:$C$34,MATCH(E48,Methodology!$B$31:$B$34,0))} -> 4 | S48: 3 | T48: 4 | U48: =ROUND((O48*Methodology!$C$5+P48*Methodology!$C$6+Q48*Methodology!$C$7+R48*Methodology!$C$8+S48*Methodology!$C$9+T48*Methodology!$C$10)*20,0) -> 72 | V48: =LOOKUP(U48,Methodology!$B$38:$B$42,Methodology!$C$38:$C$42) -> Medium | W48: /crowns | X48: Optimize | Z48: National
A49: crown vs filling | B49: Comparison | C49: Dental Crowns | D49: Dental Crowns | E49: Commercial | F49: MOFU | G49: Secondary | H49: 1300 | I49: 35 | J49: SERP Competition Analysis | K49: 3.3 | L49: Commercial Intent Analysis | M49: =LOOKUP(I49,Methodology!$B$46:$B$49,Methodology!$C$46:$C$49) -> Moderate | N49: WebMD; Colgate; Healthline; Mayo Clinic; ADA MouthHealthy | O49: 4 | P49: =LOOKUP(H49,Methodology!$B$15:$B$19,Methodology!$C$15:$C$19) -> 5 | Q49: =LOOKUP(I49,Methodology!$B$23:$B$27,Methodology!$C$23:$C$27) -> 3 | R49: {=INDEX(Methodology!$C$31:$C$34,MATCH(E49,Methodology!$B$31:$B$34,0))} -> 4 | S49: 3 | T49: 4 | U49: =ROUND((O49*Methodology!$C$5+P49*Methodology!$C$6+Q49*Methodology!$C$7+R49*Methodology!$C$8+S49*Methodology!$C$9+T49*Methodology!$C$10)*20,0) -> 76 | V49: =LOOKUP(U49,Methodology!$B$38:$B$42,Methodology!$C$38:$C$42) -> High | W49: /crowns | X49: Optimize | Z49: National
A50: tooth crown procedure | B50: Informational | C50: Dental Crowns | D50: Dental Crowns | E50: Informational | F50: TOFU | G50: Secondary | H50: 2900 | I50: 38 | J50: SERP Competition Analysis | K50: 2.2 | L50: Commercial Intent Analysis | M50: =LOOKUP(I50,Methodology!$B$46:$B$49,Methodology!$C$46:$C$49) -> Moderate | N50: WebMD; Colgate; Healthline; Mayo Clinic; ADA MouthHealthy | O50: 3 | P50: =LOOKUP(H50,Methodology!$B$15:$B$19,Methodology!$C$15:$C$19) -> 5 | Q50: =LOOKUP(I50,Methodology!$B$23:$B$27,Methodology!$C$23:$C$27) -> 3 | R50: {=INDEX(Methodology!$C$31:$C$34,MATCH(E50,Methodology!$B$31:$B$34,0))} -> 2 | S50: 1 | T50: 3 | U50: =ROUND((O50*Methodology!$C$5+P50*Methodology!$C$6+Q50*Methodology!$C$7+R50*Methodology!$C$8+S50*Methodology!$C$9+T50*Methodology!$C$10)*20,0) -> 57 | V50: =LOOKUP(U50,Methodology!$B$38:$B$42,Methodology!$C$38:$C$42) -> Low | W50: /crowns | X50: Optimize | Z50: National
A51: how long do dental crowns last | B51: Informational | C51: Dental Crowns | D51: Dental Crowns | E51: Informational | F51: TOFU | G51: Secondary | H51: 4400 | I51: 40 | J51: SERP Competition Analysis | K51: 2.6 | L51: Commercial Intent Analysis | M51: =LOOKUP(I51,Methodology!$B$46:$B$49,Methodology!$C$46:$C$49) -> Moderate | N51: WebMD; Colgate; Healthline; Mayo Clinic; ADA MouthHealthy | O51: 3 | P51: =LOOKUP(H51,Methodology!$B$15:$B$19,Methodology!$C$15:$C$19) -> 5 | Q51: =LOOKUP(I51,Methodology!$B$23:$B$27,Methodology!$C$23:$C$27) -> 3 | R51: {=INDEX(Methodology!$C$31:$C$34,MATCH(E51,Methodology!$B$31:$B$34,0))} -> 2 | S51: 1 | T51: 3 | U51: =ROUND((O51*Methodology!$C$5+P51*Methodology!$C$6+Q51*Methodology!$C$7+R51*Methodology!$C$8+S51*Methodology!$C$9+T51*Methodology!$C$10)*20,0) -> 57 | V51: =LOOKUP(U51,Methodology!$B$38:$B$42,Methodology!$C$38:$C$42) -> Low | W51: /blog/how-long-do-dental-crowns-last | X51: Create | Z51: National
A52: same day crowns near me | B52: Transactional | C52: Dental Crowns | D52: Dental Crowns | E52: Transactional | F52: BOFU | G52: Secondary | H52: 3600 | I52: 50 | J52: SERP Competition Analysis | K52: 8.5 | L52: Commercial Intent Analysis | M52: =LOOKUP(I52,Methodology!$B$46:$B$49,Methodology!$C$46:$C$49) -> Competitive | N52: Local GBP pack; nearby dental practices (Fort Payne / Scottsboro area); Yelp; Healthgrades | O52: 4 | P52: =LOOKUP(H52,Methodology!$B$15:$B$19,Methodology!$C$15:$C$19) -> 5 | Q52: =LOOKUP(I52,Methodology!$B$23:$B$27,Methodology!$C$23:$C$27) -> 2 | R52: {=INDEX(Methodology!$C$31:$C$34,MATCH(E52,Methodology!$B$31:$B$34,0))} -> 5 | S52: 5 | T52: 4 | U52: =ROUND((O52*Methodology!$C$5+P52*Methodology!$C$6+Q52*Methodology!$C$7+R52*Methodology!$C$8+S52*Methodology!$C$9+T52*Methodology!$C$10)*20,0) -> 81 | V52: =LOOKUP(U52,Methodology!$B$38:$B$42,Methodology!$C$38:$C$42) -> High | W52: /crowns | X52: Optimize | Y52: Verify same-day crown availability before targeting. | Z52: National
A53: dental bridges rainsville al | B53: Core Service | C53: Dental Bridges | D53: Dental Bridges | E53: Transactional | F53: BOFU | G53: Primary | H53: 10 | I53: 9 | J53: SERP Competition Analysis | K53: 7.2 | L53: Commercial Intent Analysis | M53: =LOOKUP(I53,Methodology!$B$46:$B$49,Methodology!$C$46:$C$49) -> Easy | N53: Local GBP pack; nearby dental practices (Fort Payne / Scottsboro area); Yelp; Healthgrades | O53: 3 | P53: =LOOKUP(H53,Methodology!$B$15:$B$19,Methodology!$C$15:$C$19) -> 1 | Q53: =LOOKUP(I53,Methodology!$B$23:$B$27,Methodology!$C$23:$C$27) -> 5 | R53: {=INDEX(Methodology!$C$31:$C$34,MATCH(E53,Methodology!$B$31:$B$34,0))} -> 5 | S53: 5 | T53: 4 | U53: =ROUND((O53*Methodology!$C$5+P53*Methodology!$C$6+Q53*Methodology!$C$7+R53*Methodology!$C$8+S53*Methodology!$C$9+T53*Methodology!$C$10)*20,0) -> 76 | V53: =LOOKUP(U53,Methodology!$B$38:$B$42,Methodology!$C$38:$C$42) -> High | W53: /bridges | X53: Optimize | Z53: Local
A54: dental bridge cost | B54: Commercial | C54: Dental Bridges | D54: Dental Bridges | E54: Commercial | F54: MOFU | G54: Secondary | H54: 9900 | I54: 52 | J54: SERP Competition Analysis | K54: 7.4 | L54: Commercial Intent Analysis | M54: =LOOKUP(I54,Methodology!$B$46:$B$49,Methodology!$C$46:$C$49) -> Competitive | N54: Cost guides (Delta Dental, Colgate, Healthline); regional practices; directories | O54: 3 | P54: =LOOKUP(H54,Methodology!$B$15:$B$19,Methodology!$C$15:$C$19) -> 5 | Q54: =LOOKUP(I54,Methodology!$B$23:$B$27,Methodology!$C$23:$C$27) -> 2 | R54: {=INDEX(Methodology!$C$31:$C$34,MATCH(E54,Methodology!$B$31:$B$34,0))} -> 4 | S54: 3 | T54: 4 | U54: =ROUND((O54*Methodology!$C$5+P54*Methodology!$C$6+Q54*Methodology!$C$7+R54*Methodology!$C$8+S54*Methodology!$C$9+T54*Methodology!$C$10)*20,0) -> 67 | V54: =LOOKUP(U54,Methodology!$B$38:$B$42,Methodology!$C$38:$C$42) -> Medium | W54: /bridges | X54: Optimize | Z54: National
A55: how long does a dental bridge last | B55: Informational | C55: Dental Bridges | D55: Dental Bridges | E55: Informational | F55: TOFU | G55: Secondary | H55: 3600 | I55: 38 | J55: SERP Competition Analysis | K55: 2.8 | L55: Commercial Intent Analysis | M55: =LOOKUP(I55,Methodology!$B$46:$B$49,Methodology!$C$46:$C$49) -> Moderate | N55: WebMD; Colgate; Healthline; Mayo Clinic; ADA MouthHealthy | O55: 2 | P55: =LOOKUP(H55,Methodology!$B$15:$B$19,Methodology!$C$15:$C$19) -> 5 | Q55: =LOOKUP(I55,Methodology!$B$23:$B$27,Methodology!$C$23:$C$27) -> 3 | R55: {=INDEX(Methodology!$C$31:$C$34,MATCH(E55,Methodology!$B$31:$B$34,0))} -> 2 | S55: 1 | T55: 3 | U55: =ROUND((O55*Methodology!$C$5+P55*Methodology!$C$6+Q55*Methodology!$C$7+R55*Methodology!$C$8+S55*Methodology!$C$9+T55*Methodology!$C$10)*20,0) -> 52 | V55: =LOOKUP(U55,Methodology!$B$38:$B$42,Methodology!$C$38:$C$42) -> Low | W55: /bridges | X55: Optimize | Z55: National
A56: dental bridge vs implant | B56: Comparison | C56: Dental Bridges | D56: Dental Bridges | E56: Commercial | F56: MOFU | G56: Secondary | H56: 6600 | I56: 48 | J56: SERP Competition Analysis | K56: 6.8 | L56: Commercial Intent Analysis | M56: =LOOKUP(I56,Methodology!$B$46:$B$49,Methodology!$C$46:$C$49) -> Competitive | N56: WebMD; Colgate; Healthline; Mayo Clinic; ADA MouthHealthy | O56: 3 | P56: =LOOKUP(H56,Methodology!$B$15:$B$19,Methodology!$C$15:$C$19) -> 5 | Q56: =LOOKUP(I56,Methodology!$B$23:$B$27,Methodology!$C$23:$C$27) -> 2 | R56: {=INDEX(Methodology!$C$31:$C$34,MATCH(E56,Methodology!$B$31:$B$34,0))} -> 4 | S56: 3 | T56: 4 | U56: =ROUND((O56*Methodology!$C$5+P56*Methodology!$C$6+Q56*Methodology!$C$7+R56*Methodology!$C$8+S56*Methodology!$C$9+T56*Methodology!$C$10)*20,0) -> 67 | V56: =LOOKUP(U56,Methodology!$B$38:$B$42,Methodology!$C$38:$C$42) -> Medium | W56: /blog/dental-bridge-vs-implant | X56: Create | Z56: National
A57: root canal rainsville al | B57: Core Service | C57: Root Canal Treatment | D57: Root Canals | E57: Transactional | F57: BOFU | G57: Primary | H57: 30 | I57: 12 | J57: SERP Competition Analysis | K57: 12.5 | L57: Commercial Intent Analysis | M57: =LOOKUP(I57,Methodology!$B$46:$B$49,Methodology!$C$46:$C$49) -> Easy | N57: Local GBP pack; nearby dental practices (Fort Payne / Scottsboro area); Yelp; Healthgrades | O57: 5 | P57: =LOOKUP(H57,Methodology!$B$15:$B$19,Methodology!$C$15:$C$19) -> 2 | Q57: =LOOKUP(I57,Methodology!$B$23:$B$27,Methodology!$C$23:$C$27) -> 5 | R57: {=INDEX(Methodology!$C$31:$C$34,MATCH(E57,Methodology!$B$31:$B$34,0))} -> 5 | S57: 5 | T57: 4 | U57: =ROUND((O57*Methodology!$C$5+P57*Methodology!$C$6+Q57*Methodology!$C$7+R57*Methodology!$C$8+S57*Methodology!$C$9+T57*Methodology!$C$10)*20,0) -> 89 | V57: =LOOKUP(U57,Methodology!$B$38:$B$42,Methodology!$C$38:$C$42) -> High | W57: /root-canals | X57: Optimize | Y57: Highest CPC local service – strong lead value. | Z57: Local
A58: root canal near me | B58: Transactional | C58: Root Canal Treatment | D58: Root Canals | E58: Transactional | F58: BOFU | G58: Secondary | H58: 33100 | I58: 60 | J58: SERP Competition Analysis | K58: 11.2 | L58: Commercial Intent Analysis | M58: =LOOKUP(I58,Methodology!$B$46:$B$49,Methodology!$C$46:$C$49) -> Competitive | N58: Local GBP pack; nearby dental practices (Fort Payne / Scottsboro area); Yelp; Healthgrades | O58: 5 | P58: =LOOKUP(H58,Methodology!$B$15:$B$19,Methodology!$C$15:$C$19) -> 5 | Q58: =LOOKUP(I58,Methodology!$B$23:$B$27,Methodology!$C$23:$C$27) -> 1 | R58: {=INDEX(Methodology!$C$31:$C$34,MATCH(E58,Methodology!$B$31:$B$34,0))} -> 5 | S58: 5 | T58: 4 | U58: =ROUND((O58*Methodology!$C$5+P58*Methodology!$C$6+Q58*Methodology!$C$7+R58*Methodology!$C$8+S58*Methodology!$C$9+T58*Methodology!$C$10)*20,0) -> 82 | V58: =LOOKUP(U58,Methodology!$B$38:$B$42,Methodology!$C$38:$C$42) -> High | W58: /root-canals | X58: Optimize | Z58: National
A59: root canal cost | B59: Commercial | C59: Root Canal Treatment | D59: Root Canals | E59: Commercial | F59: MOFU | G59: Secondary | H59: 40500 | I59: 62 | J59: SERP Competition Analysis | K59: 9.1 | L59: Commercial Intent Analysis | M59: =LOOKUP(I59,Methodology!$B$46:$B$49,Methodology!$C$46:$C$49) -> Competitive | N59: Cost guides (Delta Dental, Colgate, Healthline); regional practices; directories | O59: 5 | P59: =LOOKUP(H59,Methodology!$B$15:$B$19,Methodology!$C$15:$C$19) -> 5 | Q59: =LOOKUP(I59,Methodology!$B$23:$B$27,Methodology!$C$23:$C$27) -> 1 | R59: {=INDEX(Methodology!$C$31:$C$34,MATCH(E59,Methodology!$B$31:$B$34,0))} -> 4 | S59: 3 | T59: 4 | U59: =ROUND((O59*Methodology!$C$5+P59*Methodology!$C$6+Q59*Methodology!$C$7+R59*Methodology!$C$8+S59*Methodology!$C$9+T59*Methodology!$C$10)*20,0) -> 73 | V59: =LOOKUP(U59,Methodology!$B$38:$B$42,Methodology!$C$38:$C$42) -> Medium | W59: /root-canals | X59: Optimize | Z59: National
A60: root canal symptoms | B60: Problem-Based | C60: Root Canal Treatment | D60: Root Canals | E60: Informational | F60: TOFU | G60: Secondary | H60: 27100 | I60: 52 | J60: SERP Competition Analysis | K60: 2.4 | L60: Commercial Intent Analysis | M60: =LOOKUP(I60,Methodology!$B$46:$B$49,Methodology!$C$46:$C$49) -> Competitive | N60: WebMD; Colgate; Healthline; Mayo Clinic; ADA MouthHealthy | O60: 4 | P60: =LOOKUP(H60,Methodology!$B$15:$B$19,Methodology!$C$15:$C$19) -> 5 | Q60: =LOOKUP(I60,Methodology!$B$23:$B$27,Methodology!$C$23:$C$27) -> 2 | R60: {=INDEX(Methodology!$C$31:$C$34,MATCH(E60,Methodology!$B$31:$B$34,0))} -> 2 | S60: 1 | T60: 3 | U60: =ROUND((O60*Methodology!$C$5+P60*Methodology!$C$6+Q60*Methodology!$C$7+R60*Methodology!$C$8+S60*Methodology!$C$9+T60*Methodology!$C$10)*20,0) -> 58 | V60: =LOOKUP(U60,Methodology!$B$38:$B$42,Methodology!$C$38:$C$42) -> Low | W60: /blog/signs-you-need-a-root-canal | X60: Create | Z60: National
A61: is a root canal painful | B61: Informational | C61: Root Canal Treatment | D61: Root Canals | E61: Informational | F61: TOFU | G61: Secondary | H61: 9900 | I61: 44 | J61: SERP Competition Analysis | K61: 1.8 | L61: Commercial Intent Analysis | M61: =LOOKUP(I61,Methodology!$B$46:$B$49,Methodology!$C$46:$C$49) -> Competitive | N61: WebMD; Colgate; Healthline; Mayo Clinic; ADA MouthHealthy | O61: 4 | P61: =LOOKUP(H61,Methodology!$B$15:$B$19,Methodology!$C$15:$C$19) -> 5 | Q61: =LOOKUP(I61,Methodology!$B$23:$B$27,Methodology!$C$23:$C$27) -> 2 | R61: {=INDEX(Methodology!$C$31:$C$34,MATCH(E61,Methodology!$B$31:$B$34,0))} -> 2 | S61: 1 | T61: 3 | U61: =ROUND((O61*Methodology!$C$5+P61*Methodology!$C$6+Q61*Methodology!$C$7+R61*Methodology!$C$8+S61*Methodology!$C$9+T61*Methodology!$C$10)*20,0) -> 58 | V61: =LOOKUP(U61,Methodology!$B$38:$B$42,Methodology!$C$38:$C$42) -> Low | W61: /blog/root-canal-pain-and-recovery | X61: Create | Z61: National
A62: root canal recovery time | B62: Informational | C62: Root Canal Treatment | D62: Root Canals | E62: Informational | F62: TOFU | G62: Secondary | H62: 5400 | I62: 40 | J62: SERP Competition Analysis | K62: 1.9 | L62: Commercial Intent Analysis | M62: =LOOKUP(I62,Methodology!$B$46:$B$49,Methodology!$C$46:$C$49) -> Moderate | N62: WebMD; Colgate; Healthline; Mayo Clinic; ADA MouthHealthy | O62: 4 | P62: =LOOKUP(H62,Methodology!$B$15:$B$19,Methodology!$C$15:$C$19) -> 5 | Q62: =LOOKUP(I62,Methodology!$B$23:$B$27,Methodology!$C$23:$C$27) -> 3 | R62: {=INDEX(Methodology!$C$31:$C$34,MATCH(E62,Methodology!$B$31:$B$34,0))} -> 2 | S62: 1 | T62: 3 | U62: =ROUND((O62*Methodology!$C$5+P62*Methodology!$C$6+Q62*Methodology!$C$7+R62*Methodology!$C$8+S62*Methodology!$C$9+T62*Methodology!$C$10)*20,0) -> 62 | V62: =LOOKUP(U62,Methodology!$B$38:$B$42,Methodology!$C$38:$C$42) -> Medium | W62: /blog/root-canal-pain-and-recovery | X62: Create | Z62: National
A63: root canal vs extraction | B63: Comparison | C63: Root Canal Treatment | D63: Root Canals | E63: Commercial | F63: MOFU | G63: Secondary | H63: 3600 | I63: 42 | J63: SERP Competition Analysis | K63: 4.6 | L63: Commercial Intent Analysis | M63: =LOOKUP(I63,Methodology!$B$46:$B$49,Methodology!$C$46:$C$49) -> Competitive | N63: WebMD; Colgate; Healthline; Mayo Clinic; ADA MouthHealthy | O63: 5 | P63: =LOOKUP(H63,Methodology!$B$15:$B$19,Methodology!$C$15:$C$19) -> 5 | Q63: =LOOKUP(I63,Methodology!$B$23:$B$27,Methodology!$C$23:$C$27) -> 2 | R63: {=INDEX(Methodology!$C$31:$C$34,MATCH(E63,Methodology!$B$31:$B$34,0))} -> 4 | S63: 3 | T63: 4 | U63: =ROUND((O63*Methodology!$C$5+P63*Methodology!$C$6+Q63*Methodology!$C$7+R63*Methodology!$C$8+S63*Methodology!$C$9+T63*Methodology!$C$10)*20,0) -> 77 | V63: =LOOKUP(U63,Methodology!$B$38:$B$42,Methodology!$C$38:$C$42) -> High | W63: /blog/root-canal-vs-extraction | X63: Create | Z63: National
A64: tooth extraction rainsville al | B64: Core Service | C64: Tooth Extractions | D64: Tooth Extractions | E64: Transactional | F64: BOFU | G64: Primary | H64: 20 | I64: 10 | J64: SERP Competition Analysis | K64: 6.8 | L64: Commercial Intent Analysis | M64: =LOOKUP(I64,Methodology!$B$46:$B$49,Methodology!$C$46:$C$49) -> Easy | N64: Local GBP pack; nearby dental practices (Fort Payne / Scottsboro area); Yelp; Healthgrades | O64: 4 | P64: =LOOKUP(H64,Methodology!$B$15:$B$19,Methodology!$C$15:$C$19) -> 2 | Q64: =LOOKUP(I64,Methodology!$B$23:$B$27,Methodology!$C$23:$C$27) -> 5 | R64: {=INDEX(Methodology!$C$31:$C$34,MATCH(E64,Methodology!$B$31:$B$34,0))} -> 5 | S64: 5 | T64: 4 | U64: =ROUND((O64*Methodology!$C$5+P64*Methodology!$C$6+Q64*Methodology!$C$7+R64*Methodology!$C$8+S64*Methodology!$C$9+T64*Methodology!$C$10)*20,0) -> 84 | V64: =LOOKUP(U64,Methodology!$B$38:$B$42,Methodology!$C$38:$C$42) -> High | W64: /extractions | X64: Optimize | Z64: Local
A65: wisdom tooth removal rainsville al | B65: Local Service | C65: Tooth Extractions | D65: Tooth Extractions | E65: Transactional | F65: BOFU | G65: Secondary | H65: 10 | I65: 10 | J65: SERP Competition Analysis | K65: 7.6 | L65: Commercial Intent Analysis | M65: =LOOKUP(I65,Methodology!$B$46:$B$49,Methodology!$C$46:$C$49) -> Easy | N65: Local GBP pack; nearby dental practices (Fort Payne / Scottsboro area); Yelp; Healthgrades | O65: 4 | P65: =LOOKUP(H65,Methodology!$B$15:$B$19,Methodology!$C$15:$C$19) -> 1 | Q65: =LOOKUP(I65,Methodology!$B$23:$B$27,Methodology!$C$23:$C$27) -> 5 | R65: {=INDEX(Methodology!$C$31:$C$34,MATCH(E65,Methodology!$B$31:$B$34,0))} -> 5 | S65: 5 | T65: 4 | U65: =ROUND((O65*Methodology!$C$5+P65*Methodology!$C$6+Q65*Methodology!$C$7+R65*Methodology!$C$8+S65*Methodology!$C$9+T65*Methodology!$C$10)*20,0) -> 81 | V65: =LOOKUP(U65,Methodology!$B$38:$B$42,Methodology!$C$38:$C$42) -> High | W65: /extractions | X65: Optimize | Y65: Verify wisdom-tooth extractions are performed in-house. | Z65: Local
A66: tooth extraction near me | B66: Transactional | C66: Tooth Extractions | D66: Tooth Extractions | E66: Transactional | F66: BOFU | G66: Secondary | H66: 22200 | I66: 58 | J66: SERP Competition Analysis | K66: 6.9 | L66: Commercial Intent Analysis | M66: =LOOKUP(I66,Methodology!$B$46:$B$49,Methodology!$C$46:$C$49) -> Competitive | N66: Local GBP pack; nearby dental practices (Fort Payne / Scottsboro area); Yelp; Healthgrades | O66: 4 | P66: =LOOKUP(H66,Methodology!$B$15:$B$19,Methodology!$C$15:$C$19) -> 5 | Q66: =LOOKUP(I66,Methodology!$B$23:$B$27,Methodology!$C$23:$C$27) -> 1 | R66: {=INDEX(Methodology!$C$31:$C$34,MATCH(E66,Methodology!$B$31:$B$34,0))} -> 5 | S66: 5 | T66: 4 | U66: =ROUND((O66*Methodology!$C$5+P66*Methodology!$C$6+Q66*Methodology!$C$7+R66*Methodology!$C$8+S66*Methodology!$C$9+T66*Methodology!$C$10)*20,0) -> 77 | V66: =LOOKUP(U66,Methodology!$B$38:$B$42,Methodology!$C$38:$C$42) -> High | W66: /extractions | X66: Optimize | Z66: National
A67: tooth extraction cost | B67: Commercial | C67: Tooth Extractions | D67: Tooth Extractions | E67: Commercial | F67: MOFU | G67: Secondary | H67: 14800 | I67: 55 | J67: SERP Competition Analysis | K67: 6.2 | L67: Commercial Intent Analysis | M67: =LOOKUP(I67,Methodology!$B$46:$B$49,Methodology!$C$46:$C$49) -> Competitive | N67: Cost guides (Delta Dental, Colgate, Healthline); regional practices; directories | O67: 4 | P67: =LOOKUP(H67,Methodology!$B$15:$B$19,Methodology!$C$15:$C$19) -> 5 | Q67: =LOOKUP(I67,Methodology!$B$23:$B$27,Methodology!$C$23:$C$27) -> 2 | R67: {=INDEX(Methodology!$C$31:$C$34,MATCH(E67,Methodology!$B$31:$B$34,0))} -> 4 | S67: 3 | T67: 4 | U67: =ROUND((O67*Methodology!$C$5+P67*Methodology!$C$6+Q67*Methodology!$C$7+R67*Methodology!$C$8+S67*Methodology!$C$9+T67*Methodology!$C$10)*20,0) -> 72 | V67: =LOOKUP(U67,Methodology!$B$38:$B$42,Methodology!$C$38:$C$42) -> Medium | W67: /extractions | X67: Optimize | Z67: National
A68: tooth extraction aftercare | B68: Informational | C68: Tooth Extractions | D68: Tooth Extractions | E68: Informational | F68: TOFU | G68: Secondary | H68: 5400 | I68: 40 | J68: SERP Competition Analysis | K68: 1.8 | L68: Commercial Intent Analysis | M68: =LOOKUP(I68,Methodology!$B$46:$B$49,Methodology!$C$46:$C$49) -> Moderate | N68: WebMD; Colgate; Healthline; Mayo Clinic; ADA MouthHealthy | O68: 3 | P68: =LOOKUP(H68,Methodology!$B$15:$B$19,Methodology!$C$15:$C$19) -> 5 | Q68: =LOOKUP(I68,Methodology!$B$23:$B$27,Methodology!$C$23:$C$27) -> 3 | R68: {=INDEX(Methodology!$C$31:$C$34,MATCH(E68,Methodology!$B$31:$B$34,0))} -> 2 | S68: 1 | T68: 3 | U68: =ROUND((O68*Methodology!$C$5+P68*Methodology!$C$6+Q68*Methodology!$C$7+R68*Methodology!$C$8+S68*Methodology!$C$9+T68*Methodology!$C$10)*20,0) -> 57 | V68: =LOOKUP(U68,Methodology!$B$38:$B$42,Methodology!$C$38:$C$42) -> Low | W68: /blog/tooth-extraction-aftercare-and-dry-socket | X68: Create | Z68: National
A69: dry socket symptoms | B69: Problem-Based | C69: Tooth Extractions | D69: Tooth Extractions | E69: Informational | F69: TOFU | G69: Secondary | H69: 18100 | I69: 44 | J69: SERP Competition Analysis | K69: 1.6 | L69: Commercial Intent Analysis | M69: =LOOKUP(I69,Methodology!$B$46:$B$49,Methodology!$C$46:$C$49) -> Competitive | N69: WebMD; Colgate; Healthline; Mayo Clinic; ADA MouthHealthy | O69: 3 | P69: =LOOKUP(H69,Methodology!$B$15:$B$19,Methodology!$C$15:$C$19) -> 5 | Q69: =LOOKUP(I69,Methodology!$B$23:$B$27,Methodology!$C$23:$C$27) -> 2 | R69: {=INDEX(Methodology!$C$31:$C$34,MATCH(E69,Methodology!$B$31:$B$34,0))} -> 2 | S69: 1 | T69: 3 | U69: =ROUND((O69*Methodology!$C$5+P69*Methodology!$C$6+Q69*Methodology!$C$7+R69*Methodology!$C$8+S69*Methodology!$C$9+T69*Methodology!$C$10)*20,0) -> 53 | V69: =LOOKUP(U69,Methodology!$B$38:$B$42,Methodology!$C$38:$C$42) -> Low | W69: /blog/tooth-extraction-aftercare-and-dry-socket | X69: Create | Z69: National
A70: dental implants rainsville al | B70: Core Service | C70: Dental Implants | D70: Dental Implants | E70: Transactional | F70: BOFU | G70: Primary | H70: 40 | I70: 16 | J70: SERP Competition Analysis | K70: 14.8 | L70: Commercial Intent Analysis | M70: =LOOKUP(I70,Methodology!$B$46:$B$49,Methodology!$C$46:$C$49) -> Easy | N70: Local GBP pack; nearby dental practices (Fort Payne / Scottsboro area); Yelp; Healthgrades | O70: 5 | P70: =LOOKUP(H70,Methodology!$B$15:$B$19,Methodology!$C$15:$C$19) -> 2 | Q70: =LOOKUP(I70,Methodology!$B$23:$B$27,Methodology!$C$23:$C$27) -> 4 | R70: {=INDEX(Methodology!$C$31:$C$34,MATCH(E70,Methodology!$B$31:$B$34,0))} -> 5 | S70: 5 | T70: 5 | U70: =ROUND((O70*Methodology!$C$5+P70*Methodology!$C$6+Q70*Methodology!$C$7+R70*Methodology!$C$8+S70*Methodology!$C$9+T70*Methodology!$C$10)*20,0) -> 87 | V70: =LOOKUP(U70,Methodology!$B$38:$B$42,Methodology!$C$38:$C$42) -> High | W70: /implants | X70: Optimize | Y70: Highest-value service – top priority page. | Z70: Local
A71: dental implants near me | B71: Transactional | C71: Dental Implants | D71: Dental Implants | E71: Transactional | F71: BOFU | G71: Secondary | H71: 74000 | I71: 72 | J71: SERP Competition Analysis | K71: 15.9 | L71: Commercial Intent Analysis | M71: =LOOKUP(I71,Methodology!$B$46:$B$49,Methodology!$C$46:$C$49) -> Very Competitive | N71: Local GBP pack; nearby dental practices (Fort Payne / Scottsboro area); Yelp; Healthgrades | O71: 5 | P71: =LOOKUP(H71,Methodology!$B$15:$B$19,Methodology!$C$15:$C$19) -> 5 | Q71: =LOOKUP(I71,Methodology!$B$23:$B$27,Methodology!$C$23:$C$27) -> 1 | R71: {=INDEX(Methodology!$C$31:$C$34,MATCH(E71,Methodology!$B$31:$B$34,0))} -> 5 | S71: 5 | T71: 5 | U71: =ROUND((O71*Methodology!$C$5+P71*Methodology!$C$6+Q71*Methodology!$C$7+R71*Methodology!$C$8+S71*Methodology!$C$9+T71*Methodology!$C$10)*20,0) -> 84 | V71: =LOOKUP(U71,Methodology!$B$38:$B$42,Methodology!$C$38:$C$42) -> High | W71: /implants | X71: Optimize | Y71: Benchmark head term. | Z71: National
A72: dental implant cost | B72: Commercial | C72: Dental Implants | D72: Dental Implants | E72: Commercial | F72: MOFU | G72: Secondary | H72: 60500 | I72: 68 | J72: SERP Competition Analysis | K72: 13.4 | L72: Commercial Intent Analysis | M72: =LOOKUP(I72,Methodology!$B$46:$B$49,Methodology!$C$46:$C$49) -> Competitive | N72: Cost guides (Delta Dental, Colgate, Healthline); regional practices; directories | O72: 5 | P72: =LOOKUP(H72,Methodology!$B$15:$B$19,Methodology!$C$15:$C$19) -> 5 | Q72: =LOOKUP(I72,Methodology!$B$23:$B$27,Methodology!$C$23:$C$27) -> 1 | R72: {=INDEX(Methodology!$C$31:$C$34,MATCH(E72,Methodology!$B$31:$B$34,0))} -> 4 | S72: 3 | T72: 5 | U72: =ROUND((O72*Methodology!$C$5+P72*Methodology!$C$6+Q72*Methodology!$C$7+R72*Methodology!$C$8+S72*Methodology!$C$9+T72*Methodology!$C$10)*20,0) -> 75 | V72: =LOOKUP(U72,Methodology!$B$38:$B$42,Methodology!$C$38:$C$42) -> High | W72: /implants | X72: Optimize | Z72: National
A73: how much do dental implants cost in alabama | B73: Commercial | C73: Dental Implants | D73: Dental Implants | E73: Commercial | F73: MOFU | G73: Secondary | H73: 210 | I73: 30 | J73: SERP Competition Analysis | K73: 11.8 | L73: Commercial Intent Analysis | M73: =LOOKUP(I73,Methodology!$B$46:$B$49,Methodology!$C$46:$C$49) -> Moderate | N73: Cost guides (Delta Dental, Colgate, Healthline); regional practices; directories | O73: 5 | P73: =LOOKUP(H73,Methodology!$B$15:$B$19,Methodology!$C$15:$C$19) -> 4 | Q73: =LOOKUP(I73,Methodology!$B$23:$B$27,Methodology!$C$23:$C$27) -> 3 | R73: {=INDEX(Methodology!$C$31:$C$34,MATCH(E73,Methodology!$B$31:$B$34,0))} -> 4 | S73: 3 | T73: 5 | U73: =ROUND((O73*Methodology!$C$5+P73*Methodology!$C$6+Q73*Methodology!$C$7+R73*Methodology!$C$8+S73*Methodology!$C$9+T73*Methodology!$C$10)*20,0) -> 80 | V73: =LOOKUP(U73,Methodology!$B$38:$B$42,Methodology!$C$38:$C$42) -> High | W73: /blog/dental-implant-cost-in-alabama | X73: Create | Z73: Regional
A74: dental implants vs dentures | B74: Comparison | C74: Dental Implants | D74: Dental Implants | E74: Commercial | F74: MOFU | G74: Secondary | H74: 8100 | I74: 50 | J74: SERP Competition Analysis | K74: 6.9 | L74: Commercial Intent Analysis | M74: =LOOKUP(I74,Methodology!$B$46:$B$49,Methodology!$C$46:$C$49) -> Competitive | N74: WebMD; Colgate; Healthline; Mayo Clinic; ADA MouthHealthy | O74: 5 | P74: =LOOKUP(H74,Methodology!$B$15:$B$19,Methodology!$C$15:$C$19) -> 5 | Q74: =LOOKUP(I74,Methodology!$B$23:$B$27,Methodology!$C$23:$C$27) -> 2 | R74: {=INDEX(Methodology!$C$31:$C$34,MATCH(E74,Methodology!$B$31:$B$34,0))} -> 4 | S74: 3 | T74: 5 | U74: =ROUND((O74*Methodology!$C$5+P74*Methodology!$C$6+Q74*Methodology!$C$7+R74*Methodology!$C$8+S74*Methodology!$C$9+T74*Methodology!$C$10)*20,0) -> 79 | V74: =LOOKUP(U74,Methodology!$B$38:$B$42,Methodology!$C$38:$C$42) -> High | W74: /blog/dental-implants-vs-dentures | X74: Create | Z74: National
A75: are dental implants worth it | B75: Commercial | C75: Dental Implants | D75: Dental Implants | E75: Commercial | F75: MOFU | G75: Secondary | H75: 3600 | I75: 40 | J75: SERP Competition Analysis | K75: 5.8 | L75: Commercial Intent Analysis | M75: =LOOKUP(I75,Methodology!$B$46:$B$49,Methodology!$C$46:$C$49) -> Moderate | N75: WebMD; Colgate; Healthline; Mayo Clinic; ADA MouthHealthy | O75: 5 | P75: =LOOKUP(H75,Methodology!$B$15:$B$19,Methodology!$C$15:$C$19) -> 5 | Q75: =LOOKUP(I75,Methodology!$B$23:$B$27,Methodology!$C$23:$C$27) -> 3 | R75: {=INDEX(Methodology!$C$31:$C$34,MATCH(E75,Methodology!$B$31:$B$34,0))} -> 4 | S75: 3 | T75: 5 | U75: =ROUND((O75*Methodology!$C$5+P75*Methodology!$C$6+Q75*Methodology!$C$7+R75*Methodology!$C$8+S75*Methodology!$C$9+T75*Methodology!$C$10)*20,0) -> 83 | V75: =LOOKUP(U75,Methodology!$B$38:$B$42,Methodology!$C$38:$C$42) -> High | W75: /implants | X75: Optimize | Z75: National
A76: dental implant procedure steps | B76: Informational | C76: Dental Implants | D76: Dental Implants | E76: Informational | F76: TOFU | G76: Secondary | H76: 6600 | I76: 42 | J76: SERP Competition Analysis | K76: 3.1 | L76: Commercial Intent Analysis | M76: =LOOKUP(I76,Methodology!$B$46:$B$49,Methodology!$C$46:$C$49) -> Competitive | N76: WebMD; Colgate; Healthline; Mayo Clinic; ADA MouthHealthy | O76: 4 | P76: =LOOKUP(H76,Methodology!$B$15:$B$19,Methodology!$C$15:$C$19) -> 5 | Q76: =LOOKUP(I76,Methodology!$B$23:$B$27,Methodology!$C$23:$C$27) -> 2 | R76: {=INDEX(Methodology!$C$31:$C$34,MATCH(E76,Methodology!$B$31:$B$34,0))} -> 2 | S76: 1 | T76: 4 | U76: =ROUND((O76*Methodology!$C$5+P76*Methodology!$C$6+Q76*Methodology!$C$7+R76*Methodology!$C$8+S76*Methodology!$C$9+T76*Methodology!$C$10)*20,0) -> 60 | V76: =LOOKUP(U76,Methodology!$B$38:$B$42,Methodology!$C$38:$C$42) -> Medium | W76: /implants | X76: Optimize | Z76: National
A77: dental implant recovery time | B77: Informational | C77: Dental Implants | D77: Dental Implants | E77: Informational | F77: TOFU | G77: Secondary | H77: 5400 | I77: 40 | J77: SERP Competition Analysis | K77: 2.7 | L77: Commercial Intent Analysis | M77: =LOOKUP(I77,Methodology!$B$46:$B$49,Methodology!$C$46:$C$49) -> Moderate | N77: WebMD; Colgate; Healthline; Mayo Clinic; ADA MouthHealthy | O77: 4 | P77: =LOOKUP(H77,Methodology!$B$15:$B$19,Methodology!$C$15:$C$19) -> 5 | Q77: =LOOKUP(I77,Methodology!$B$23:$B$27,Methodology!$C$23:$C$27) -> 3 | R77: {=INDEX(Methodology!$C$31:$C$34,MATCH(E77,Methodology!$B$31:$B$34,0))} -> 2 | S77: 1 | T77: 4 | U77: =ROUND((O77*Methodology!$C$5+P77*Methodology!$C$6+Q77*Methodology!$C$7+R77*Methodology!$C$8+S77*Methodology!$C$9+T77*Methodology!$C$10)*20,0) -> 64 | V77: =LOOKUP(U77,Methodology!$B$38:$B$42,Methodology!$C$38:$C$42) -> Medium | W77: /implants | X77: Optimize | Z77: National
A78: single tooth implant cost | B78: Commercial | C78: Dental Implants | D78: Dental Implants | E78: Commercial | F78: MOFU | G78: Secondary | H78: 5400 | I78: 50 | J78: SERP Competition Analysis | K78: 12.1 | L78: Commercial Intent Analysis | M78: =LOOKUP(I78,Methodology!$B$46:$B$49,Methodology!$C$46:$C$49) -> Competitive | N78: Cost guides (Delta Dental, Colgate, Healthline); regional practices; directories | O78: 5 | P78: =LOOKUP(H78,Methodology!$B$15:$B$19,Methodology!$C$15:$C$19) -> 5 | Q78: =LOOKUP(I78,Methodology!$B$23:$B$27,Methodology!$C$23:$C$27) -> 2 | R78: {=INDEX(Methodology!$C$31:$C$34,MATCH(E78,Methodology!$B$31:$B$34,0))} -> 4 | S78: 3 | T78: 5 | U78: =ROUND((O78*Methodology!$C$5+P78*Methodology!$C$6+Q78*Methodology!$C$7+R78*Methodology!$C$8+S78*Methodology!$C$9+T78*Methodology!$C$10)*20,0) -> 79 | V78: =LOOKUP(U78,Methodology!$B$38:$B$42,Methodology!$C$38:$C$42) -> High | W78: /implants | X78: Optimize | Z78: National
A79: dental implants financing | B79: Commercial | C79: Dental Implants | D79: Dental Implants | E79: Commercial | F79: MOFU | G79: Secondary | H79: 1300 | I79: 34 | J79: SERP Competition Analysis | K79: 9.5 | L79: Commercial Intent Analysis | M79: =LOOKUP(I79,Methodology!$B$46:$B$49,Methodology!$C$46:$C$49) -> Moderate | N79: Cost guides (Delta Dental, Colgate, Healthline); regional practices; directories | O79: 5 | P79: =LOOKUP(H79,Methodology!$B$15:$B$19,Methodology!$C$15:$C$19) -> 5 | Q79: =LOOKUP(I79,Methodology!$B$23:$B$27,Methodology!$C$23:$C$27) -> 3 | R79: {=INDEX(Methodology!$C$31:$C$34,MATCH(E79,Methodology!$B$31:$B$34,0))} -> 4 | S79: 3 | T79: 5 | U79: =ROUND((O79*Methodology!$C$5+P79*Methodology!$C$6+Q79*Methodology!$C$7+R79*Methodology!$C$8+S79*Methodology!$C$9+T79*Methodology!$C$10)*20,0) -> 83 | V79: =LOOKUP(U79,Methodology!$B$38:$B$42,Methodology!$C$38:$C$42) -> High | W79: /dental-insurance-payment | X79: Create | Y79: Verify financing options are offered before publishing. | Z79: National
A80: dentures rainsville al | B80: Core Service | C80: Dentures | D80: Dentures | E80: Transactional | F80: BOFU | G80: Primary | H80: 30 | I80: 12 | J80: SERP Competition Analysis | K80: 7.8 | L80: Commercial Intent Analysis | M80: =LOOKUP(I80,Methodology!$B$46:$B$49,Methodology!$C$46:$C$49) -> Easy | N80: Local GBP pack; nearby dental practices (Fort Payne / Scottsboro area); Yelp; Healthgrades | O80: 4 | P80: =LOOKUP(H80,Methodology!$B$15:$B$19,Methodology!$C$15:$C$19) -> 2 | Q80: =LOOKUP(I80,Methodology!$B$23:$B$27,Methodology!$C$23:$C$27) -> 5 | R80: {=INDEX(Methodology!$C$31:$C$34,MATCH(E80,Methodology!$B$31:$B$34,0))} -> 5 | S80: 5 | T80: 4 | U80: =ROUND((O80*Methodology!$C$5+P80*Methodology!$C$6+Q80*Methodology!$C$7+R80*Methodology!$C$8+S80*Methodology!$C$9+T80*Methodology!$C$10)*20,0) -> 84 | V80: =LOOKUP(U80,Methodology!$B$38:$B$42,Methodology!$C$38:$C$42) -> High | W80: /dentures | X80: Optimize | Z80: Local
A81: dentures near me | B81: Transactional | C81: Dentures | D81: Dentures | E81: Transactional | F81: BOFU | G81: Secondary | H81: 60500 | I81: 62 | J81: SERP Competition Analysis | K81: 8.4 | L81: Commercial Intent Analysis | M81: =LOOKUP(I81,Methodology!$B$46:$B$49,Methodology!$C$46:$C$49) -> Competitive | N81: Local GBP pack; nearby dental practices (Fort Payne / Scottsboro area); Yelp; Healthgrades | O81: 4 | P81: =LOOKUP(H81,Methodology!$B$15:$B$19,Methodology!$C$15:$C$19) -> 5 | Q81: =LOOKUP(I81,Methodology!$B$23:$B$27,Methodology!$C$23:$C$27) -> 1 | R81: {=INDEX(Methodology!$C$31:$C$34,MATCH(E81,Methodology!$B$31:$B$34,0))} -> 5 | S81: 5 | T81: 4 | U81: =ROUND((O81*Methodology!$C$5+P81*Methodology!$C$6+Q81*Methodology!$C$7+R81*Methodology!$C$8+S81*Methodology!$C$9+T81*Methodology!$C$10)*20,0) -> 77 | V81: =LOOKUP(U81,Methodology!$B$38:$B$42,Methodology!$C$38:$C$42) -> High | W81: /dentures | X81: Optimize | Z81: National
A82: how much do dentures cost | B82: Commercial | C82: Dentures | D82: Dentures | E82: Commercial | F82: MOFU | G82: Secondary | H82: 33100 | I82: 56 | J82: SERP Competition Analysis | K82: 6.7 | L82: Commercial Intent Analysis | M82: =LOOKUP(I82,Methodology!$B$46:$B$49,Methodology!$C$46:$C$49) -> Competitive | N82: Cost guides (Delta Dental, Colgate, Healthline); regional practices; directories | O82: 4 | P82: =LOOKUP(H82,Methodology!$B$15:$B$19,Methodology!$C$15:$C$19) -> 5 | Q82: =LOOKUP(I82,Methodology!$B$23:$B$27,Methodology!$C$23:$C$27) -> 1 | R82: {=INDEX(Methodology!$C$31:$C$34,MATCH(E82,Methodology!$B$31:$B$34,0))} -> 4 | S82: 3 | T82: 4 | U82: =ROUND((O82*Methodology!$C$5+P82*Methodology!$C$6+Q82*Methodology!$C$7+R82*Methodology!$C$8+S82*Methodology!$C$9+T82*Methodology!$C$10)*20,0) -> 68 | V82: =LOOKUP(U82,Methodology!$B$38:$B$42,Methodology!$C$38:$C$42) -> Medium | W82: /dentures | X82: Optimize | Z82: National
A83: affordable dentures alabama | B83: Commercial | C83: Dentures | D83: Dentures | E83: Commercial | F83: MOFU | G83: Secondary | H83: 320 | I83: 28 | J83: SERP Competition Analysis | K83: 6.2 | L83: Commercial Intent Analysis | M83: =LOOKUP(I83,Methodology!$B$46:$B$49,Methodology!$C$46:$C$49) -> Moderate | N83: Cost guides (Delta Dental, Colgate, Healthline); regional practices; directories | O83: 4 | P83: =LOOKUP(H83,Methodology!$B$15:$B$19,Methodology!$C$15:$C$19) -> 4 | Q83: =LOOKUP(I83,Methodology!$B$23:$B$27,Methodology!$C$23:$C$27) -> 3 | R83: {=INDEX(Methodology!$C$31:$C$34,MATCH(E83,Methodology!$B$31:$B$34,0))} -> 4 | S83: 3 | T83: 4 | U83: =ROUND((O83*Methodology!$C$5+P83*Methodology!$C$6+Q83*Methodology!$C$7+R83*Methodology!$C$8+S83*Methodology!$C$9+T83*Methodology!$C$10)*20,0) -> 73 | V83: =LOOKUP(U83,Methodology!$B$38:$B$42,Methodology!$C$38:$C$42) -> Medium | W83: /dentures | X83: Optimize | Z83: Regional
A84: immediate dentures | B84: Informational | C84: Dentures | D84: Dentures | E84: Informational | F84: TOFU | G84: Secondary | H84: 3600 | I84: 36 | J84: SERP Competition Analysis | K84: 2.3 | L84: Commercial Intent Analysis | M84: =LOOKUP(I84,Methodology!$B$46:$B$49,Methodology!$C$46:$C$49) -> Moderate | N84: WebMD; Colgate; Healthline; Mayo Clinic; ADA MouthHealthy | O84: 3 | P84: =LOOKUP(H84,Methodology!$B$15:$B$19,Methodology!$C$15:$C$19) -> 5 | Q84: =LOOKUP(I84,Methodology!$B$23:$B$27,Methodology!$C$23:$C$27) -> 3 | R84: {=INDEX(Methodology!$C$31:$C$34,MATCH(E84,Methodology!$B$31:$B$34,0))} -> 2 | S84: 1 | T84: 3 | U84: =ROUND((O84*Methodology!$C$5+P84*Methodology!$C$6+Q84*Methodology!$C$7+R84*Methodology!$C$8+S84*Methodology!$C$9+T84*Methodology!$C$10)*20,0) -> 57 | V84: =LOOKUP(U84,Methodology!$B$38:$B$42,Methodology!$C$38:$C$42) -> Low | W84: /dentures | X84: Optimize | Z84: National
A85: full dentures vs partial dentures | B85: Comparison | C85: Dentures | D85: Dentures | E85: Commercial | F85: MOFU | G85: Secondary | H85: 880 | I85: 30 | J85: SERP Competition Analysis | K85: 3.2 | L85: Commercial Intent Analysis | M85: =LOOKUP(I85,Methodology!$B$46:$B$49,Methodology!$C$46:$C$49) -> Moderate | N85: WebMD; Colgate; Healthline; Mayo Clinic; ADA MouthHealthy | O85: 4 | P85: =LOOKUP(H85,Methodology!$B$15:$B$19,Methodology!$C$15:$C$19) -> 4 | Q85: =LOOKUP(I85,Methodology!$B$23:$B$27,Methodology!$C$23:$C$27) -> 3 | R85: {=INDEX(Methodology!$C$31:$C$34,MATCH(E85,Methodology!$B$31:$B$34,0))} -> 4 | S85: 3 | T85: 4 | U85: =ROUND((O85*Methodology!$C$5+P85*Methodology!$C$6+Q85*Methodology!$C$7+R85*Methodology!$C$8+S85*Methodology!$C$9+T85*Methodology!$C$10)*20,0) -> 73 | V85: =LOOKUP(U85,Methodology!$B$38:$B$42,Methodology!$C$38:$C$42) -> Medium | W85: /dentures | X85: Optimize | Z85: National
A86: partial dentures rainsville al | B86: Core Service | C86: Partial Dentures | D86: Partial Dentures | E86: Transactional | F86: BOFU | G86: Primary | H86: 20 | I86: 11 | J86: SERP Competition Analysis | K86: 7.1 | L86: Commercial Intent Analysis | M86: =LOOKUP(I86,Methodology!$B$46:$B$49,Methodology!$C$46:$C$49) -> Easy | N86: Local GBP pack; nearby dental practices (Fort Payne / Scottsboro area); Yelp; Healthgrades | O86: 3 | P86: =LOOKUP(H86,Methodology!$B$15:$B$19,Methodology!$C$15:$C$19) -> 2 | Q86: =LOOKUP(I86,Methodology!$B$23:$B$27,Methodology!$C$23:$C$27) -> 5 | R86: {=INDEX(Methodology!$C$31:$C$34,MATCH(E86,Methodology!$B$31:$B$34,0))} -> 5 | S86: 5 | T86: 3 | U86: =ROUND((O86*Methodology!$C$5+P86*Methodology!$C$6+Q86*Methodology!$C$7+R86*Methodology!$C$8+S86*Methodology!$C$9+T86*Methodology!$C$10)*20,0) -> 77 | V86: =LOOKUP(U86,Methodology!$B$38:$B$42,Methodology!$C$38:$C$42) -> High | W86: /partial-dentures | X86: Optimize | Z86: Local
A87: partial dentures near me | B87: Transactional | C87: Partial Dentures | D87: Partial Dentures | E87: Transactional | F87: BOFU | G87: Secondary | H87: 4400 | I87: 48 | J87: SERP Competition Analysis | K87: 6.9 | L87: Commercial Intent Analysis | M87: =LOOKUP(I87,Methodology!$B$46:$B$49,Methodology!$C$46:$C$49) -> Competitive | N87: Local GBP pack; nearby dental practices (Fort Payne / Scottsboro area); Yelp; Healthgrades | O87: 3 | P87: =LOOKUP(H87,Methodology!$B$15:$B$19,Methodology!$C$15:$C$19) -> 5 | Q87: =LOOKUP(I87,Methodology!$B$23:$B$27,Methodology!$C$23:$C$27) -> 2 | R87: {=INDEX(Methodology!$C$31:$C$34,MATCH(E87,Methodology!$B$31:$B$34,0))} -> 5 | S87: 5 | T87: 3 | U87: =ROUND((O87*Methodology!$C$5+P87*Methodology!$C$6+Q87*Methodology!$C$7+R87*Methodology!$C$8+S87*Methodology!$C$9+T87*Methodology!$C$10)*20,0) -> 74 | V87: =LOOKUP(U87,Methodology!$B$38:$B$42,Methodology!$C$38:$C$42) -> Medium | W87: /partial-dentures | X87: Optimize | Z87: National
A88: partial dentures cost | B88: Commercial | C88: Partial Dentures | D88: Partial Dentures | E88: Commercial | F88: MOFU | G88: Secondary | H88: 6600 | I88: 46 | J88: SERP Competition Analysis | K88: 5.9 | L88: Commercial Intent Analysis | M88: =LOOKUP(I88,Methodology!$B$46:$B$49,Methodology!$C$46:$C$49) -> Competitive | N88: Cost guides (Delta Dental, Colgate, Healthline); regional practices; directories | O88: 3 | P88: =LOOKUP(H88,Methodology!$B$15:$B$19,Methodology!$C$15:$C$19) -> 5 | Q88: =LOOKUP(I88,Methodology!$B$23:$B$27,Methodology!$C$23:$C$27) -> 2 | R88: {=INDEX(Methodology!$C$31:$C$34,MATCH(E88,Methodology!$B$31:$B$34,0))} -> 4 | S88: 3 | T88: 3 | U88: =ROUND((O88*Methodology!$C$5+P88*Methodology!$C$6+Q88*Methodology!$C$7+R88*Methodology!$C$8+S88*Methodology!$C$9+T88*Methodology!$C$10)*20,0) -> 65 | V88: =LOOKUP(U88,Methodology!$B$38:$B$42,Methodology!$C$38:$C$42) -> Medium | W88: /partial-dentures | X88: Optimize | Z88: National
A89: flexible partial dentures | B89: Commercial | C89: Partial Dentures | D89: Partial Dentures | E89: Commercial | F89: MOFU | G89: Secondary | H89: 2400 | I89: 36 | J89: SERP Competition Analysis | K89: 3.8 | L89: Commercial Intent Analysis | M89: =LOOKUP(I89,Methodology!$B$46:$B$49,Methodology!$C$46:$C$49) -> Moderate | N89: WebMD; Colgate; Healthline; Mayo Clinic; ADA MouthHealthy | O89: 3 | P89: =LOOKUP(H89,Methodology!$B$15:$B$19,Methodology!$C$15:$C$19) -> 5 | Q89: =LOOKUP(I89,Methodology!$B$23:$B$27,Methodology!$C$23:$C$27) -> 3 | R89: {=INDEX(Methodology!$C$31:$C$34,MATCH(E89,Methodology!$B$31:$B$34,0))} -> 4 | S89: 3 | T89: 3 | U89: =ROUND((O89*Methodology!$C$5+P89*Methodology!$C$6+Q89*Methodology!$C$7+R89*Methodology!$C$8+S89*Methodology!$C$9+T89*Methodology!$C$10)*20,0) -> 69 | V89: =LOOKUP(U89,Methodology!$B$38:$B$42,Methodology!$C$38:$C$42) -> Medium | W89: /partial-dentures | X89: Optimize | Y89: Verify materials offered. | Z89: National
A90: how long do partial dentures last | B90: Informational | C90: Partial Dentures | D90: Partial Dentures | E90: Informational | F90: TOFU | G90: Secondary | H90: 1600 | I90: 32 | J90: SERP Competition Analysis | K90: 2.1 | L90: Commercial Intent Analysis | M90: =LOOKUP(I90,Methodology!$B$46:$B$49,Methodology!$C$46:$C$49) -> Moderate | N90: WebMD; Colgate; Healthline; Mayo Clinic; ADA MouthHealthy | O90: 2 | P90: =LOOKUP(H90,Methodology!$B$15:$B$19,Methodology!$C$15:$C$19) -> 5 | Q90: =LOOKUP(I90,Methodology!$B$23:$B$27,Methodology!$C$23:$C$27) -> 3 | R90: {=INDEX(Methodology!$C$31:$C$34,MATCH(E90,Methodology!$B$31:$B$34,0))} -> 2 | S90: 1 | T90: 2 | U90: =ROUND((O90*Methodology!$C$5+P90*Methodology!$C$6+Q90*Methodology!$C$7+R90*Methodology!$C$8+S90*Methodology!$C$9+T90*Methodology!$C$10)*20,0) -> 50 | V90: =LOOKUP(U90,Methodology!$B$38:$B$42,Methodology!$C$38:$C$42) -> Low | W90: /partial-dentures | X90: Optimize | Z90: National
A91: partial denture vs bridge | B91: Comparison | C91: Partial Dentures | D91: Partial Dentures | E91: Commercial | F91: MOFU | G91: Secondary | H91: 1000 | I91: 34 | J91: SERP Competition Analysis | K91: 4.2 | L91: Commercial Intent Analysis | M91: =LOOKUP(I91,Methodology!$B$46:$B$49,Methodology!$C$46:$C$49) -> Moderate | N91: WebMD; Colgate; Healthline; Mayo Clinic; ADA MouthHealthy | O91: 3 | P91: =LOOKUP(H91,Methodology!$B$15:$B$19,Methodology!$C$15:$C$19) -> 5 | Q91: =LOOKUP(I91,Methodology!$B$23:$B$27,Methodology!$C$23:$C$27) -> 3 | R91: {=INDEX(Methodology!$C$31:$C$34,MATCH(E91,Methodology!$B$31:$B$34,0))} -> 4 | S91: 3 | T91: 3 | U91: =ROUND((O91*Methodology!$C$5+P91*Methodology!$C$6+Q91*Methodology!$C$7+R91*Methodology!$C$8+S91*Methodology!$C$9+T91*Methodology!$C$10)*20,0) -> 69 | V91: =LOOKUP(U91,Methodology!$B$38:$B$42,Methodology!$C$38:$C$42) -> Medium | W91: /blog/partial-denture-vs-bridge | X91: Create | Z91: National
A92: veneers rainsville al | B92: Core Service | C92: Veneers & Cosmetic | D92: Veneers & Cosmetic Dentistry | E92: Transactional | F92: BOFU | G92: Primary | H92: 10 | I92: 10 | J92: SERP Competition Analysis | K92: 8.5 | L92: Commercial Intent Analysis | M92: =LOOKUP(I92,Methodology!$B$46:$B$49,Methodology!$C$46:$C$49) -> Easy | N92: Local GBP pack; nearby dental practices (Fort Payne / Scottsboro area); Yelp; Healthgrades | O92: 4 | P92: =LOOKUP(H92,Methodology!$B$15:$B$19,Methodology!$C$15:$C$19) -> 1 | Q92: =LOOKUP(I92,Methodology!$B$23:$B$27,Methodology!$C$23:$C$27) -> 5 | R92: {=INDEX(Methodology!$C$31:$C$34,MATCH(E92,Methodology!$B$31:$B$34,0))} -> 5 | S92: 5 | T92: 4 | U92: =ROUND((O92*Methodology!$C$5+P92*Methodology!$C$6+Q92*Methodology!$C$7+R92*Methodology!$C$8+S92*Methodology!$C$9+T92*Methodology!$C$10)*20,0) -> 81 | V92: =LOOKUP(U92,Methodology!$B$38:$B$42,Methodology!$C$38:$C$42) -> High | W92: /veneers | X92: Optimize | Z92: Local
A93: cosmetic dentist rainsville al | B93: Local Service | C93: Veneers & Cosmetic | D93: Veneers & Cosmetic Dentistry | E93: Transactional | F93: BOFU | G93: Secondary | H93: 20 | I93: 14 | J93: SERP Competition Analysis | K93: 9 | L93: Commercial Intent Analysis | M93: =LOOKUP(I93,Methodology!$B$46:$B$49,Methodology!$C$46:$C$49) -> Easy | N93: Local GBP pack; nearby dental practices (Fort Payne / Scottsboro area); Yelp; Healthgrades | O93: 4 | P93: =LOOKUP(H93,Methodology!$B$15:$B$19,Methodology!$C$15:$C$19) -> 2 | Q93: =LOOKUP(I93,Methodology!$B$23:$B$27,Methodology!$C$23:$C$27) -> 5 | R93: {=INDEX(Methodology!$C$31:$C$34,MATCH(E93,Methodology!$B$31:$B$34,0))} -> 5 | S93: 5 | T93: 4 | U93: =ROUND((O93*Methodology!$C$5+P93*Methodology!$C$6+Q93*Methodology!$C$7+R93*Methodology!$C$8+S93*Methodology!$C$9+T93*Methodology!$C$10)*20,0) -> 84 | V93: =LOOKUP(U93,Methodology!$B$38:$B$42,Methodology!$C$38:$C$42) -> High | W93: /veneers | X93: Optimize | Z93: Local
A94: veneers near me | B94: Transactional | C94: Veneers & Cosmetic | D94: Veneers & Cosmetic Dentistry | E94: Transactional | F94: BOFU | G94: Secondary | H94: 33100 | I94: 58 | J94: SERP Competition Analysis | K94: 8.9 | L94: Commercial Intent Analysis | M94: =LOOKUP(I94,Methodology!$B$46:$B$49,Methodology!$C$46:$C$49) -> Competitive | N94: Local GBP pack; nearby dental practices (Fort Payne / Scottsboro area); Yelp; Healthgrades | O94: 4 | P94: =LOOKUP(H94,Methodology!$B$15:$B$19,Methodology!$C$15:$C$19) -> 5 | Q94: =LOOKUP(I94,Methodology!$B$23:$B$27,Methodology!$C$23:$C$27) -> 1 | R94: {=INDEX(Methodology!$C$31:$C$34,MATCH(E94,Methodology!$B$31:$B$34,0))} -> 5 | S94: 5 | T94: 4 | U94: =ROUND((O94*Methodology!$C$5+P94*Methodology!$C$6+Q94*Methodology!$C$7+R94*Methodology!$C$8+S94*Methodology!$C$9+T94*Methodology!$C$10)*20,0) -> 77 | V94: =LOOKUP(U94,Methodology!$B$38:$B$42,Methodology!$C$38:$C$42) -> High | W94: /veneers | X94: Optimize | Z94: National
A95: porcelain veneers cost | B95: Commercial | C95: Veneers & Cosmetic | D95: Veneers & Cosmetic Dentistry | E95: Commercial | F95: MOFU | G95: Secondary | H95: 22200 | I95: 60 | J95: SERP Competition Analysis | K95: 10.2 | L95: Commercial Intent Analysis | M95: =LOOKUP(I95,Methodology!$B$46:$B$49,Methodology!$C$46:$C$49) -> Competitive | N95: Cost guides (Delta Dental, Colgate, Healthline); regional practices; directories | O95: 4 | P95: =LOOKUP(H95,Methodology!$B$15:$B$19,Methodology!$C$15:$C$19) -> 5 | Q95: =LOOKUP(I95,Methodology!$B$23:$B$27,Methodology!$C$23:$C$27) -> 1 | R95: {=INDEX(Methodology!$C$31:$C$34,MATCH(E95,Methodology!$B$31:$B$34,0))} -> 4 | S95: 3 | T95: 4 | U95: =ROUND((O95*Methodology!$C$5+P95*Methodology!$C$6+Q95*Methodology!$C$7+R95*Methodology!$C$8+S95*Methodology!$C$9+T95*Methodology!$C$10)*20,0) -> 68 | V95: =LOOKUP(U95,Methodology!$B$38:$B$42,Methodology!$C$38:$C$42) -> Medium | W95: /veneers | X95: Optimize | Z95: National
A96: are veneers worth it | B96: Commercial | C96: Veneers & Cosmetic | D96: Veneers & Cosmetic Dentistry | E96: Commercial | F96: MOFU | G96: Secondary | H96: 2900 | I96: 38 | J96: SERP Competition Analysis | K96: 3.7 | L96: Commercial Intent Analysis | M96: =LOOKUP(I96,Methodology!$B$46:$B$49,Methodology!$C$46:$C$49) -> Moderate | N96: WebMD; Colgate; Healthline; Mayo Clinic; ADA MouthHealthy | O96: 4 | P96: =LOOKUP(H96,Methodology!$B$15:$B$19,Methodology!$C$15:$C$19) -> 5 | Q96: =LOOKUP(I96,Methodology!$B$23:$B$27,Methodology!$C$23:$C$27) -> 3 | R96: {=INDEX(Methodology!$C$31:$C$34,MATCH(E96,Methodology!$B$31:$B$34,0))} -> 4 | S96: 3 | T96: 4 | U96: =ROUND((O96*Methodology!$C$5+P96*Methodology!$C$6+Q96*Methodology!$C$7+R96*Methodology!$C$8+S96*Methodology!$C$9+T96*Methodology!$C$10)*20,0) -> 76 | V96: =LOOKUP(U96,Methodology!$B$38:$B$42,Methodology!$C$38:$C$42) -> High | W96: /veneers | X96: Optimize | Z96: National
A97: how long do veneers last | B97: Informational | C97: Veneers & Cosmetic | D97: Veneers & Cosmetic Dentistry | E97: Informational | F97: TOFU | G97: Secondary | H97: 6600 | I97: 44 | J97: SERP Competition Analysis | K97: 2.5 | L97: Commercial Intent Analysis | M97: =LOOKUP(I97,Methodology!$B$46:$B$49,Methodology!$C$46:$C$49) -> Competitive | N97: WebMD; Colgate; Healthline; Mayo Clinic; ADA MouthHealthy | O97: 3 | P97: =LOOKUP(H97,Methodology!$B$15:$B$19,Methodology!$C$15:$C$19) -> 5 | Q97: =LOOKUP(I97,Methodology!$B$23:$B$27,Methodology!$C$23:$C$27) -> 2 | R97: {=INDEX(Methodology!$C$31:$C$34,MATCH(E97,Methodology!$B$31:$B$34,0))} -> 2 | S97: 1 | T97: 3 | U97: =ROUND((O97*Methodology!$C$5+P97*Methodology!$C$6+Q97*Methodology!$C$7+R97*Methodology!$C$8+S97*Methodology!$C$9+T97*Methodology!$C$10)*20,0) -> 53 | V97: =LOOKUP(U97,Methodology!$B$38:$B$42,Methodology!$C$38:$C$42) -> Low | W97: /veneers | X97: Optimize | Z97: National
A98: composite vs porcelain veneers | B98: Comparison | C98: Veneers & Cosmetic | D98: Veneers & Cosmetic Dentistry | E98: Commercial | F98: MOFU | G98: Secondary | H98: 3600 | I98: 40 | J98: SERP Competition Analysis | K98: 4.1 | L98: Commercial Intent Analysis | M98: =LOOKUP(I98,Methodology!$B$46:$B$49,Methodology!$C$46:$C$49) -> Moderate | N98: WebMD; Colgate; Healthline; Mayo Clinic; ADA MouthHealthy | O98: 4 | P98: =LOOKUP(H98,Methodology!$B$15:$B$19,Methodology!$C$15:$C$19) -> 5 | Q98: =LOOKUP(I98,Methodology!$B$23:$B$27,Methodology!$C$23:$C$27) -> 3 | R98: {=INDEX(Methodology!$C$31:$C$34,MATCH(E98,Methodology!$B$31:$B$34,0))} -> 4 | S98: 3 | T98: 4 | U98: =ROUND((O98*Methodology!$C$5+P98*Methodology!$C$6+Q98*Methodology!$C$7+R98*Methodology!$C$8+S98*Methodology!$C$9+T98*Methodology!$C$10)*20,0) -> 76 | V98: =LOOKUP(U98,Methodology!$B$38:$B$42,Methodology!$C$38:$C$42) -> High | W98: /blog/composite-vs-porcelain-veneers | X98: Create | Z98: National
A99: dental x-rays rainsville al | B99: Core Service | C99: Dental X-Rays | D99: Digital Imaging & X-Rays | E99: Transactional | F99: BOFU | G99: Primary | H99: 10 | I99: 8 | J99: SERP Competition Analysis | K99: 4.2 | L99: Commercial Intent Analysis | M99: =LOOKUP(I99,Methodology!$B$46:$B$49,Methodology!$C$46:$C$49) -> Easy | N99: Local GBP pack; nearby dental practices (Fort Payne / Scottsboro area); Yelp; Healthgrades | O99: 2 | P99: =LOOKUP(H99,Methodology!$B$15:$B$19,Methodology!$C$15:$C$19) -> 1 | Q99: =LOOKUP(I99,Methodology!$B$23:$B$27,Methodology!$C$23:$C$27) -> 5 | R99: {=INDEX(Methodology!$C$31:$C$34,MATCH(E99,Methodology!$B$31:$B$34,0))} -> 5 | S99: 5 | T99: 3 | U99: =ROUND((O99*Methodology!$C$5+P99*Methodology!$C$6+Q99*Methodology!$C$7+R99*Methodology!$C$8+S99*Methodology!$C$9+T99*Methodology!$C$10)*20,0) -> 69 | V99: =LOOKUP(U99,Methodology!$B$38:$B$42,Methodology!$C$38:$C$42) -> Medium | W99: /digital-imaging | X99: Optimize | Z99: Local
A100: digital dental x-rays | B100: Informational | C100: Dental X-Rays | D100: Digital Imaging & X-Rays | E100: Informational | F100: TOFU | G100: Secondary | H100: 1600 | I100: 30 | J100: SERP Competition Analysis | K100: 2.3 | L100: Commercial Intent Analysis | M100: =LOOKUP(I100,Methodology!$B$46:$B$49,Methodology!$C$46:$C$49) -> Moderate | N100: WebMD; Colgate; Healthline; Mayo Clinic; ADA MouthHealthy | O100: 1 | P100: =LOOKUP(H100,Methodology!$B$15:$B$19,Methodology!$C$15:$C$19) -> 5 | Q100: =LOOKUP(I100,Methodology!$B$23:$B$27,Methodology!$C$23:$C$27) -> 3 | R100: {=INDEX(Methodology!$C$31:$C$34,MATCH(E100,Methodology!$B$31:$B$34,0))} -> 2 | S100: 1 | T100: 2 | U100: =ROUND((O100*Methodology!$C$5+P100*Methodology!$C$6+Q100*Methodology!$C$7+R100*Methodology!$C$8+S100*Methodology!$C$9+T100*Methodology!$C$10)*20,0) -> 45 | V100: =LOOKUP(U100,Methodology!$B$38:$B$42,Methodology!$C$38:$C$42) -> Low | W100: /digital-imaging | X100: Optimize | Z100: National
...

Sheet Keyword Clusters
A1: Cluster Name | B1: Primary Keyword | C1: Secondary Keywords | D1: Questions | E1: Entities | F1: Intent | G1: Funnel Stage | H1: Recommended Page | I1: Page Type | J1: # Keywords in Cluster | K1: Est. Local + Regional Monthly Volume
A2: Brand & Navigational | B2: carter family dentistry rainsville al | C2: carter family dentistry; carterdentistry.com; carter family dentistry reviews; carter family dentistry phone number; carter family dentistry hours | D2: Where is Carter Family Dentistry in Rainsville? What are Carter Family Dentistry's hours? | E2: Carter Family Dentistry, LLC; Rainsville AL; 20 Bartlett Ave; (256) 638-2121 | F2: Navigational | G2: BOFU | H2: / | I2: Homepage | J2: =COUNTIF('Keyword Master Database'!$D$2:$D$137,A2) -> 7 | K2: =SUMIFS('Keyword Master Database'!$H$2:$H$137,'Keyword Master Database'!$D$2:$D$137,A2,'Keyword Master Database'!$Z$2:$Z$137,"<>National") -> 250
A3: Local Dentist – Rainsville & DeKalb | B3: dentist in rainsville al | C3: dentist rainsville alabama; dental office rainsville al; general dentist rainsville al; best dentist in rainsville al; dentist near me | D3: Who is the best dentist in Rainsville, AL? Is there a dentist near me accepting new patients? | E3: Rainsville; DeKalb County; Sand Mountain; Google Business Profile | F3: Transactional | G3: BOFU | H3: / | I3: Homepage | J3: =COUNTIF('Keyword Master Database'!$D$2:$D$137,A3) -> 9 | K3: =SUMIFS('Keyword Master Database'!$H$2:$H$137,'Keyword Master Database'!$D$2:$D$137,A3,'Keyword Master Database'!$Z$2:$Z$137,"<>National") -> 290
A4: Exams & Preventive Care | B4: dental exam rainsville al | C4: dental cleaning rainsville al; new patient dental exam; dental checkup near me; family dentist rainsville al; kids dentist rainsville al | D4: What happens at a dental exam? How often should I get a cleaning? | E4: Dental exam; prophylaxis; oral cancer screening; hygienist | F4: Transactional | G4: BOFU | H4: /dental-exams | I4: Service Page | J4: =COUNTIF('Keyword Master Database'!$D$2:$D$137,A4) -> 8 | K4: =SUMIFS('Keyword Master Database'!$H$2:$H$137,'Keyword Master Database'!$D$2:$D$137,A4,'Keyword Master Database'!$Z$2:$Z$137,"<>National") -> 120
A5: Emergency Dental Care | B5: emergency dentist rainsville al | C5: emergency dentist dekalb county al; dentist for tooth pain rainsville al; same day dentist appointment near me; dental abscess symptoms; chipped tooth what to do | D5: What counts as a dental emergency? What do I do about a toothache at night? | E5: Toothache; abscess; broken tooth; swelling; emergency exam | F5: Transactional | G5: BOFU | H5: /emergency-exam | I5: Service Page | J5: =COUNTIF('Keyword Master Database'!$D$2:$D$137,A5) -> 9 | K5: =SUMIFS('Keyword Master Database'!$H$2:$H$137,'Keyword Master Database'!$D$2:$D$137,A5,'Keyword Master Database'!$Z$2:$Z$137,"<>National") -> 70
A6: Fillings & Cavity Care | B6: dental fillings rainsville al | C6: tooth filling near me; cavity filling cost; white fillings; composite vs amalgam fillings; signs of a cavity | D6: How much does a filling cost? Are white fillings better than silver? | E6: Composite resin; amalgam; tooth decay; cavity | F6: Transactional | G6: BOFU | H6: /fillings | I6: Service Page | J6: =COUNTIF('Keyword Master Database'!$D$2:$D$137,A6) -> 7 | K6: =SUMIFS('Keyword Master Database'!$H$2:$H$137,'Keyword Master Database'!$D$2:$D$137,A6,'Keyword Master Database'!$Z$2:$Z$137,"<>National") -> 20
A7: Silver Diamine Fluoride (SDF) | B7: silver diamine fluoride rainsville al | C7: silver diamine fluoride; silver diamine fluoride for adults; silver diamine fluoride cost; silver diamine fluoride side effects | D7: What is silver diamine fluoride? Does SDF stain teeth? | E7: SDF; fluoride; non-invasive cavity arrest; tooth decay | F7: Transactional | G7: BOFU | H7: /silver-diamine-fluoride | I7: Service Page | J7: =COUNTIF('Keyword Master Database'!$D$2:$D$137,A7) -> 5 | K7: =SUMIFS('Keyword Master Database'!$H$2:$H$137,'Keyword Master Database'!$D$2:$D$137,A7,'Keyword Master Database'!$Z$2:$Z$137,"<>National") -> 10
A8: Dental Crowns | B8: dental crowns rainsville al | C8: dental crown cost; crown vs filling; tooth crown procedure; how long do dental crowns last; same day crowns near me | D8: How much does a dental crown cost? How long do crowns last? | E8: Porcelain; ceramic; zirconia; cap; tooth restoration | F8: Transactional | G8: BOFU | H8: /crowns | I8: Service Page | J8: =COUNTIF('Keyword Master Database'!$D$2:$D$137,A8) -> 6 | K8: =SUMIFS('Keyword Master Database'!$H$2:$H$137,'Keyword Master Database'!$D$2:$D$137,A8,'Keyword Master Database'!$Z$2:$Z$137,"<>National") -> 20
A9: Dental Bridges | B9: dental bridges rainsville al | C9: dental bridge cost; how long does a dental bridge last; dental bridge vs implant | D9: Is a bridge or an implant better? How long does a bridge last? | E9: Pontic; abutment teeth; fixed bridge; tooth replacement | F9: Transactional | G9: BOFU | H9: /bridges | I9: Service Page | J9: =COUNTIF('Keyword Master Database'!$D$2:$D$137,A9) -> 4 | K9: =SUMIFS('Keyword Master Database'!$H$2:$H$137,'Keyword Master Database'!$D$2:$D$137,A9,'Keyword Master Database'!$Z$2:$Z$137,"<>National") -> 10
A10: Root Canals | B10: root canal rainsville al | C10: root canal near me; root canal cost; root canal symptoms; is a root canal painful; root canal vs extraction | D10: Is a root canal painful? How much does a root canal cost? | E10: Endodontic therapy; pulp; infection; crown after root canal | F10: Transactional | G10: BOFU | H10: /root-canals | I10: Service Page | J10: =COUNTIF('Keyword Master Database'!$D$2:$D$137,A10) -> 7 | K10: =SUMIFS('Keyword Master Database'!$H$2:$H$137,'Keyword Master Database'!$D$2:$D$137,A10,'Keyword Master Database'!$Z$2:$Z$137,"<>National") -> 30
A11: Tooth Extractions | B11: tooth extraction rainsville al | C11: tooth extraction near me; tooth extraction cost; wisdom tooth removal rainsville al; tooth extraction aftercare; dry socket symptoms | D11: How long does extraction healing take? What is dry socket? | E11: Simple extraction; surgical extraction; wisdom teeth; socket | F11: Transactional | G11: BOFU | H11: /extractions | I11: Service Page | J11: =COUNTIF('Keyword Master Database'!$D$2:$D$137,A11) -> 6 | K11: =SUMIFS('Keyword Master Database'!$H$2:$H$137,'Keyword Master Database'!$D$2:$D$137,A11,'Keyword Master Database'!$Z$2:$Z$137,"<>National") -> 30
A12: Dental Implants | B12: dental implants rainsville al | C12: dental implants near me; dental implant cost; dental implants vs dentures; are dental implants worth it; single tooth implant cost | D12: How much do dental implants cost in Alabama? Are implants better than dentures? | E12: Titanium post; abutment; osseointegration; implant crown | F12: Transactional | G12: BOFU | H12: /implants | I12: Service Page | J12: =COUNTIF('Keyword Master Database'!$D$2:$D$137,A12) -> 10 | K12: =SUMIFS('Keyword Master Database'!$H$2:$H$137,'Keyword Master Database'!$D$2:$D$137,A12,'Keyword Master Database'!$Z$2:$Z$137,"<>National") -> 250
A13: Dentures | B13: dentures rainsville al | C13: dentures near me; how much do dentures cost; affordable dentures alabama; immediate dentures; full dentures vs partial dentures | D13: How much do dentures cost? How long do dentures last? | E13: Full dentures; immediate dentures; denture fitting; edentulism | F13: Transactional | G13: BOFU | H13: /dentures | I13: Service Page | J13: =COUNTIF('Keyword Master Database'!$D$2:$D$137,A13) -> 6 | K13: =SUMIFS('Keyword Master Database'!$H$2:$H$137,'Keyword Master Database'!$D$2:$D$137,A13,'Keyword Master Database'!$Z$2:$Z$137,"<>National") -> 350
... A20: Dr. Emily Carter & Female Dentist | B20: female dentist rainsville al | C20: dr emily carter rainsville al; dr emily carter dentist; female dentist near me | D20: Is there a female dentist in Rainsville? Who is Dr. Emily Carter? | E20: Dr. Emily Carter; female dentist; credentials; patient care philosophy | F20: Transactional | G20: BOFU | H20: /meet-dr-emily-carter | I20: Trust / E-E-A-T Page | J20: =COUNTIF('Keyword Master Database'!$D$2:$D$137,A20) -> 4 | K20: =SUMIFS('Keyword Master Database'!$H$2:$H$137,'Keyword Master Database'!$D$2:$D$137,A20,'Keyword Master Database'!$Z$2:$Z$137,"<>National") -> 130

Sheet Competitor Analysis
A1: Competitor | B1: URL | C1: Ranking Topics | D1: Strong Pages | E1: Weakness | F1: Content Gap | G1: Opportunity | H1: Verification Status
A2: Carter Family Dentistry (Boise, ID) | B2: carterfamilydds.com | C2: Branded 'Carter Family Dentistry' queries; Boise / Treasure Valley general dentistry, cosmetic, Invisalign and veneers (per public listings). | D2: Not audited – organic data unavailable. Public listings show a family-owned practice established 1973 with strong Google ratings. | E2: Located in Boise, Idaho – no local-pack overlap with Rainsville, AL. Competes only for the shared brand name. | F2: No Alabama relevance; Rainsville-specific, DeKalb/Jackson County content is entirely absent. | G2: Own the branded SERP with city + Dr. Emily Carter in titles, LocalBusiness schema, consistent NAP and GBP. Always use 'Rainsville, AL' in brand anchors. | H2: Partially verified (public listings). Organic keywords to be pulled in Semrush.
A3: Dr. Tara's Dental Village | B3: drtarasdentalvillage.com | C3: To be validated in Semrush Organic Research. | D3: To be validated. | E3: Could not be confirmed as a Rainsville-area practice through public search – location/relevance unverified. | F3: To be determined after Semrush export. | G3: If confirmed local, mine its ranking service pages for keyword gaps (implants, dentures, emergency). | H3: Unverified – client-supplied. Confirm location and organic footprint.
A4: Carter Orthodontics / Carter Braces (Rainsville, AL) | B4: carterbraces.com | C4: Orthodontics / braces in Rainsville, AL (practice of Dr. Jared Carter, DMD, MS, per AAO and directory listings). | D4: Not audited. | E4: Specialty orthodontic practice – little overlap with general, restorative and emergency services. Similar Carter name can cause local brand confusion. | F4: General dentistry, restorative and tooth-replacement content is outside its scope. | G4: Differentiate on general/family/restorative care; keep branded SERP clean; consider a referral relationship for ortho cases. | H4: Partially verified (AAO / directory listings). Organic data to be pulled.
A5: Fort Payne & Scottsboro general dental practices | B5: (identify in Semrush / local-pack check) | C5: dentist fort payne al; dentist scottsboro al; implants, dentures and emergency dentist in nearby towns. | D5: Typically service pages and location pages for the larger towns. | E5: Pattern-based: many small-practice sites have thin service pages and no FAQ/blog content. | F5: Rainsville and smaller-town (Henagar, Valley Head, Sylvania, Section) demand is often under-served. | G5: Create Fort Payne / Scottsboro pages and a service-area hub to capture overflow demand. | H5: Pattern-based estimate – named competitors not verified.
A6: Dental directories (Healthgrades, Vitals, WebMD Care, Yelp) | B6: healthgrades.com / vitals.com / doctor.webmd.com / yelp.com | C6: Provider and practice name searches; 'dentist in [town]' directory pages. | D6: Practice and provider profile pages. | E6: Generic profiles, no service depth, no conversion path owned by the practice. | F6: Detailed service, cost and insurance information. | G6: Claim and complete profiles with consistent NAP; use reviews and service lists to feed citation signals. | H6: Observed in public search results for Carter-name dentist queries.
A7: Practice-finder / AI-profile aggregators | B7: local.newpatientsinc.com / lantern.llc | C7: Practice-name and 'dentist in [city]' queries. | D7: Auto-generated practice pages. | E7: Third-party data may be incomplete or outdated. | F7: Accurate hours, services and insurance details. | G7: Keep website facts identical to listings; add structured data so AI search tools read accurate details. | H7: Observed in public search results.
A8: National dental education publishers (Colgate, Healthline, Delta Dental, Mayo Clinic, ADA MouthHealthy) | B8: colgate.com / healthline.com / deltadental.com / mayoclinic.org | C8: Informational and problem keywords: root canal symptoms, dry socket, implant procedure, x-ray safety. | D8: Long-form guides with high domain authority. | E8: Not local, no appointment path, no Alabama pricing or insurance context. | F8: Local cost context (Alabama), BCBS of Alabama / Southland insurance questions, Dr. Emily Carter's expert voice. | G8: Publish concise, locally framed answers with FAQ schema; target the lowest-KD questions first. | H8: Pattern-based estimate for these SERPs.

Sheet Keyword Mapping
A1: URL | B1: Page Name | C1: Primary Keyword | D1: Secondary Keywords | E1: Intent | F1: Funnel Stage | G1: Existing / New | H1: Action | I1: Cannibalization Risk
A2: / | B2: Homepage | C2: dentist in rainsville al | D2: carter family dentistry rainsville al; carter family dentistry; carterdentistry.com; dentist rainsville alabama; dental office rainsville al; best dentist in rainsville al; dentist near me | E2: {=INDEX('Keyword Master Database'!$E$2:$E$137,MATCH(C2,'Keyword Master Database'!$A$2:$A$137,0))} -> Transactional | F2: {=INDEX('Keyword Master Database'!$F$2:$F$137,MATCH(C2,'Keyword Master Database'!$A$2:$A$137,0))} -> BOFU | G2: Existing | H2: Optimize | I2: Medium
A3: /services | B3: Services Hub | C3: general dentist rainsville al | D3: – | E3: {=INDEX('Keyword Master Database'!$E$2:$E$137,MATCH(C3,'Keyword Master Database'!$A$2:$A$137,0))} -> Transactional | F3: {=INDEX('Keyword Master Database'!$F$2:$F$137,MATCH(C3,'Keyword Master Database'!$A$2:$A$137,0))} -> BOFU | G3: Existing | H3: Optimize | I3: Low
A4: /dental-exams | B4: Dental Exams | C4: dental exam rainsville al | D4: dental cleaning rainsville al; new patient dental exam; dental checkup near me; teeth cleaning near me | E4: {=INDEX('Keyword Master Database'!$E$2:$E$137,MATCH(C4,'Keyword Master Database'!$A$2:$A$137,0))} -> Transactional | F4: {=INDEX('Keyword Master Database'!$F$2:$F$137,MATCH(C4,'Keyword Master Database'!$A$2:$A$137,0))} -> BOFU | G4: Existing | H4: Optimize | I4: Low
A5: /emergency-exam | B5: Emergency Exam | C5: emergency dentist rainsville al | D5: emergency dentist dekalb county al; dentist for tooth pain rainsville al; emergency dentist near me; same day dentist appointment near me | E5: {=INDEX('Keyword Master Database'!$E$2:$E$137,MATCH(C5,'Keyword Master Database'!$A$2:$A$137,0))} -> Transactional | F5: {=INDEX('Keyword Master Database'!$F$2:$F$137,MATCH(C5,'Keyword Master Database'!$A$2:$A$137,0))} -> BOFU | G5: Existing | H5: Optimize | I5: Low
A6: /digital-imaging | B6: Digital Imaging | C6: dental x-rays rainsville al | D6: digital dental x-rays; digital x-rays vs traditional | E6: {=INDEX('Keyword Master Database'!$E$2:$E$137,MATCH(C6,'Keyword Master Database'!$A$2:$A$137,0))} -> Transactional | F6: {=INDEX('Keyword Master Database'!$F$2:$F$137,MATCH(C6,'Keyword Master Database'!$A$2:$A$137,0))} -> BOFU | G6: Existing | H6: Optimize | I6: Low
A7: /fillings | B7: Fillings | C7: dental fillings rainsville al | D7: tooth filling near me; cavity filling cost; white fillings | E7: {=INDEX('Keyword Master Database'!$E$2:$E$137,MATCH(C7,'Keyword Master Database'!$A$2:$A$137,0))} -> Transactional | F7: {=INDEX('Keyword Master Database'!$F$2:$F$137,MATCH(C7,'Keyword Master Database'!$A$2:$A$137,0))} -> BOFU | G7: Existing | H7: Optimize | I7: Low
A8: /silver-diamine-fluoride | B8: Silver Diamine Fluoride (SDF) | C8: silver diamine fluoride rainsville al | D8: silver diamine fluoride; silver diamine fluoride for adults; silver diamine fluoride cost | E8: {=INDEX('Keyword Master Database'!$E$2:$E$137,MATCH(C8,'Keyword Master Database'!$A$2:$A$137,0))} -> Transactional | F8: {=INDEX('Keyword Master Database'!$F$2:$F$137,MATCH(C8,'Keyword Master Database'!$A$2:$A$137,0))} -> BOFU | G8: Existing | H8: Optimize | I8: Low
A9: /crowns | B9: Crowns | C9: dental crowns rainsville al | D9: dental crown cost; crown vs filling; tooth crown procedure; same day crowns near me | E9: {=INDEX('Keyword Master Database'!$E$2:$E$137,MATCH(C9,'Keyword Master Database'!$A$2:$A$137,0))} -> Transactional | F9: {=INDEX('Keyword Master Database'!$F$2:$F$137,MATCH(C9,'Keyword Master Database'!$A$2:$A$137,0))} -> BOFU | G9: Existing | H9: Optimize | I9: Low
A10: /veneers | B10: Veneers | C10: veneers rainsville al | D10: cosmetic dentist rainsville al; veneers near me; porcelain veneers cost; are veneers worth it; how long do veneers last | E10: {=INDEX('Keyword Master Database'!$E$2:$E$137,MATCH(C10,'Keyword Master Database'!$A$2:$A$137,0))} -> Transactional | F10: {=INDEX('Keyword Master Database'!$F$2:$F$137,MATCH(C10,'Keyword Master Database'!$A$2:$A$137,0))} -> BOFU | G10: Existing | H10: Optimize | I10: Medium
A11: /bridges | B11: Bridges | C11: dental bridges rainsville al | D11: dental bridge cost; how long does a dental bridge last | E11: {=INDEX('Keyword Master Database'!$E$2:$E$137,MATCH(C11,'Keyword Master Database'!$A$2:$A$137,0))} -> Transactional | F11: {=INDEX('Keyword Master Database'!$F$2:$F$137,MATCH(C11,'Keyword Master Database'!$A$2:$A$137,0))} -> BOFU | G11: Existing | H11: Optimize | I11: Medium
A12: /root-canals | B12: Root Canals | C12: root canal rainsville al | D12: root canal near me; root canal cost | E12: {=INDEX('Keyword Master Database'!$E$2:$E$137,MATCH(C12,'Keyword Master Database'!$A$2:$A$137,0))} -> Transactional | F12: {=INDEX('Keyword Master Database'!$F$2:$F$137,MATCH(C12,'Keyword Master Database'!$A$2:$A$137,0))} -> BOFU | G12: Existing | H12: Optimize | I12: Low
A13: /extractions | B13: Extractions | C13: tooth extraction rainsville al | D13: wisdom tooth removal rainsville al; tooth extraction near me; tooth extraction cost | E13: {=INDEX('Keyword Master Database'!$E$2:$E$137,MATCH(C13,'Keyword Master Database'!$A$2:$A$137,0))} -> Transactional | F13: {=INDEX('Keyword Master Database'!$F$2:$F$137,MATCH(C13,'Keyword Master Database'!$A$2:$A$137,0))} -> BOFU | G13: Existing | H13: Optimize | I13: Low
... A51: /blog/how-to-prevent-cavities | B51: How to Prevent Cavities: A Family Guide | C51: how to prevent cavities | D51: – | E51: {=INDEX('Keyword Master Database'!$E$2:$E$137,MATCH(C51,'Keyword Master Database'!$A$2:$A$137,0))} -> Informational | F51: {=INDEX('Keyword Master Database'!$F$2:$F$137,MATCH(C51,'Keyword Master Database'!$A$2:$A$137,0))} -> TOFU | G51: New | H51: Create | I51: Low

Sheet Topical Authority Map
A1: Main Topic | B1: Sub Topics | C1: Supporting Content | D1: Entities | E1: Commercial Connection
A2: Tooth Replacement (Implants, Bridges, Dentures, Partials) | B2: Dental implants; dental bridges; full dentures; partial dentures; extractions; missing-tooth options; cost and financing | C2: Implants vs dentures; bridge vs implant; partial denture vs bridge; implant cost in Alabama; missing tooth options hub; extraction aftercare | D2: Titanium implant; abutment; pontic; denture base; edentulism; bone density | E2: /implants, /bridges, /dentures, /partial-dentures, /extractions → appointment request
A3: Emergency & Urgent Dental Care | B3: Toothache; abscess; chipped / knocked-out tooth; swelling; same-day care | C3: Toothache at night; dental abscess symptoms; chipped or knocked-out tooth; tooth pain when biting down | D3: Dental emergency; pulp infection; trauma; pain management | E3: /emergency-exam, /root-canals → call now / same-day request
A4: Root Canals & Endodontics | B4: Root canal procedure; symptoms; pain and recovery; root canal vs extraction; crown after root canal | C4: Signs you need a root canal; is a root canal painful; recovery time; root canal vs extraction | D4: Endodontic therapy; pulp; infection; crown | E4: /root-canals, /crowns → appointment request
A5: Restorative Dentistry (Fillings, Crowns, SDF) | B5: Cavity detection; composite vs amalgam; crowns; silver diamine fluoride; prevention | C5: Signs of a cavity; composite vs amalgam fillings; how long crowns last; SDF side effects; how to prevent cavities | D5: Composite; amalgam; porcelain; zirconia; fluoride; enamel | E5: /fillings, /crowns, /silver-diamine-fluoride → appointment request
A6: Preventive Care & Diagnostics | B6: Exams; cleanings; digital x-rays; first visit; visit frequency | C6: What happens at a dental exam; how often to visit; are dental x-rays safe; first dental visit | D6: Bitewing x-ray; prophylaxis; hygienist; oral exam | E6: /dental-exams, /digital-imaging → new patient appointment
A7: Cosmetic Dentistry (Veneers) | B7: Porcelain vs composite veneers; longevity; cost; smile makeover | C7: Composite vs porcelain veneers; are veneers worth it; how long veneers last | D7: Porcelain; composite resin; enamel; shade matching | E7: /veneers → consultation request
A8: Insurance, Cost & Affordability | B8: BCBS of Alabama; Southland; payment options; cost without insurance | C8: Insurance & payment page; dental exam cost without insurance; implant and denture cost pages | D8: Blue Cross Blue Shield of Alabama; Southland; in-network; payment plans | E8: /dental-insurance-payment → new patient appointment
A9: Local Authority (Rainsville, DeKalb & Jackson County) | B9: Rainsville; Fort Payne; Scottsboro; Henagar; Valley Head; Sylvania; Section | C9: Service-area hub; Fort Payne page; Scottsboro page; community and patient stories; GBP posts | D9: Rainsville AL; DeKalb County; Jackson County; Sand Mountain | E9: /, /service-area, location pages → call / directions / appointment
A10: Trust & Provider Expertise (E-E-A-T) | B10: Dr. Emily Carter bio; credentials; female dentist; reviews; office tour | C10: Expanded Dr. Carter bio with credentials; reviewed-by byline on clinical posts; testimonials with schema | D10: Dr. Emily Carter; Carter Family Dentistry team; patient reviews | E10: /meet-dr-emily-carter, /testimonials → trust for every BOFU page

Sheet SEO Silo Architecture
A1: Silo | B1: Parent Page | C1: Child Pages | D1: Purpose | E1: Internal Linking Flow
A2: Silo 1 – Tooth Replacement | B2: /implants | C2: /bridges /dentures /partial-dentures /extractions /blog/dental-implant-cost-in-alabama /blog/dental-implants-vs-dentures /blog/dental-bridge-vs-implant /blog/partial-denture-vs-bridge /blog/missing-tooth-replacement-options /blog/tooth-extraction-aftercare-and-dry-socket | D2: Capture the highest-value searches (implants, dentures, bridges) and educate on options. | E2: Services hub → parent → child service pages; every blog links up to its service page and across to the 'missing tooth replacement options' hub; service pages cross-link by 'alternative option'.
A3: Silo 2 – Emergency & Endodontic Care | B3: /emergency-exam | C3: /root-canals /extractions /blog/dental-emergencies-chipped-or-knocked-out-tooth /blog/root-canal-vs-extraction /blog/signs-you-need-a-root-canal /blog/root-canal-pain-and-recovery /blog/dental-abscess-symptoms-when-to-seek-care /blog/toothache-at-night-what-to-do /blog/tooth-pain-when-biting-down | D3: Own urgent, high-CPC searches in Rainsville and DeKalb County. | E3: Homepage → /emergency-exam (prominent call-out); emergency page → root canals / extractions; blog posts link to emergency page with call-to-action.
A4: Silo 3 – Restorative Dentistry | B4: /services | C4: /fillings /crowns /blog/how-long-do-dental-crowns-last /blog/composite-vs-amalgam-fillings /blog/signs-of-a-cavity /blog/how-to-prevent-cavities | D4: Support everyday restorative demand and funnel patients to crowns/implants when needed. | E4: Fillings ↔ crowns; fillings → SDF; crowns → root canals; blogs link up to their service page.
A5: Silo 4 – Preventive & Diagnostics | B5: /dental-exams | C5: /digital-imaging /silver-diamine-fluoride /blog/are-dental-x-rays-safe /blog/silver-diamine-fluoride-side-effects /blog/what-happens-at-a-dental-exam /blog/how-often-should-you-go-to-the-dentist /blog/sensitive-teeth-causes-and-treatment /blog/how-to-choose-a-family-dentist /blog/first-dental-visit-what-to-expect | D5: Attract new patients and families; feed appointment requests. | E5: Exams ↔ digital imaging; exams → family dentistry; blogs link up to exams / appointment.
A6: Silo 5 – Cosmetic Dentistry | B6: /veneers | C6: /crowns /blog/composite-vs-porcelain-veneers | D6: Capture high-CPC cosmetic demand with a small, focused cluster. | E6: Veneers ↔ crowns; veneer blog → veneers page → consultation.
A7: Silo 6 – Local & Trust | B7: / (Homepage) | C7: /service-area /dentist-fort-payne-al /dentist-scottsboro-al /meet-dr-emily-carter /testimonials /contact /appointment | D7: Build local relevance across DeKalb and Jackson County and reinforce E-E-A-T. | E7: Homepage → area hub → town pages → services; every page footer → contact / appointment; bio and testimonials linked from every service page.
A8: Silo 7 – Insurance & Cost | B8: /dental-insurance-payment | C8: /blog/dental-implant-cost-in-alabama /blog/dental-exam-cost-without-insurance | D8: Convert price- and insurance-sensitive searchers (BCBS of Alabama, Southland). | E8: Insurance page linked from implants, dentures, crowns and homepage; cost posts link back to the insurance page and the related service.

Sheet Internal Linking Blueprint
A1: Source Page | B1: Target Page | C1: Anchor Concept | D1: Purpose
A2: /services | B2: /dental-exams | C2: dental exams in Rainsville | D2: Hub-to-spoke: pass authority and crawl paths to every service page.
A3: /services | B3: /emergency-exam | C3: emergency exam in Rainsville | D3: Hub-to-spoke: pass authority and crawl paths to every service page.
A4: /services | B4: /digital-imaging | C4: digital imaging in Rainsville | D4: Hub-to-spoke: pass authority and crawl paths to every service page.
A5: /services | B5: /fillings | C5: fillings in Rainsville | D5: Hub-to-spoke: pass authority and crawl paths to every service page.
A6: /services | B6: /silver-diamine-fluoride | C6: silver diamine fluoride (sdf) in Rainsville | D6: Hub-to-spoke: pass authority and crawl paths to every service page.
A7: /services | B7: /crowns | C7: crowns in Rainsville | D7: Hub-to-spoke: pass authority and crawl paths to every service page.
A8: /services | B8: /veneers | C8: veneers in Rainsville | D8: Hub-to-spoke: pass authority and crawl paths to every service page.
A9: /services | B9: /bridges | C9: bridges in Rainsville | D9: Hub-to-spoke: pass authority and crawl paths to every service page.
A10: /services | B10: /root-canals | C10: root canals in Rainsville | D10: Hub-to-spoke: pass authority and crawl paths to every service page.
A11: /services | B11: /extractions | C11: extractions in Rainsville | D11: Hub-to-spoke: pass authority and crawl paths to every service page.
A12: /services | B12: /implants | C12: implants in Rainsville | D12: Hub-to-spoke: pass authority and crawl paths to every service page.
... A129: /blog/partial-denture-vs-bridge | B129: /bridges | C129: dental bridge | D129: Comparison post → both options.

Sheet Content Roadmap
A1: Timeline | B1: Priority | C1: Content Type | D1: Title | E1: Target Keyword | F1: Search Intent | G1: Funnel Stage | H1: URL | I1: Business Goal
A2: Weeks 1–2 | B2: {=INDEX('Keyword Master Database'!$V$2:$V$137,MATCH(E2,'Keyword Master Database'!$A$2:$A$137,0))} -> High | C2: Local SEO / GBP | D2: Google Business Profile optimization: primary category, services list, photos, Q&A, weekly posts | E2: dentist near me | F2: {=INDEX('Keyword Master Database'!$E$2:$E$137,MATCH(E2,'Keyword Master Database'!$A$2:$A$137,0))} -> Transactional | G2: {=INDEX('Keyword Master Database'!$F$2:$F$137,MATCH(E2,'Keyword Master Database'!$A$2:$A$137,0))} -> BOFU | H2: / | I2: Increase local-pack visibility and calls
A3: Weeks 1–2 | B3: {=INDEX('Keyword Master Database'!$V$2:$V$137,MATCH(E3,'Keyword Master Database'!$A$2:$A$137,0))} -> Critical | C3: Page Optimization | D3: Homepage rewrite: Dentist in Rainsville, AL (shorter title, keyword H1, service and location copy, FAQ) | E3: dentist in rainsville al | F3: {=INDEX('Keyword Master Database'!$E$2:$E$137,MATCH(E3,'Keyword Master Database'!$A$2:$A$137,0))} -> Transactional | G3: {=INDEX('Keyword Master Database'!$F$2:$F$137,MATCH(E3,'Keyword Master Database'!$A$2:$A$137,0))} -> BOFU | H3: / | I3: Increase local leads
A4: Weeks 1–2 | B4: {=INDEX('Keyword Master Database'!$V$2:$V$137,MATCH(E4,'Keyword Master Database'!$A$2:$A$137,0))} -> High | C4: Page Optimization | D4: Implants page: procedure, candidacy, cost range, FAQ and CTA | E4: dental implants rainsville al | F4: {=INDEX('Keyword Master Database'!$E$2:$E$137,MATCH(E4,'Keyword Master Database'!$A$2:$A$137,0))} -> Transactional | G4: {=INDEX('Keyword Master Database'!$F$2:$F$137,MATCH(E4,'Keyword Master Database'!$A$2:$A$137,0))} -> BOFU | H4: /implants | I4: Improve service page rankings
A5: Weeks 1–2 | B5: {=INDEX('Keyword Master Database'!$V$2:$V$137,MATCH(E5,'Keyword Master Database'!$A$2:$A$137,0))} -> High | C5: Page Optimization | D5: Emergency exam page: symptoms list, same-day call CTA, hours | E5: emergency dentist rainsville al | F5: {=INDEX('Keyword Master Database'!$E$2:$E$137,MATCH(E5,'Keyword Master Database'!$A$2:$A$137,0))} -> Transactional | G5: {=INDEX('Keyword Master Database'!$F$2:$F$137,MATCH(E5,'Keyword Master Database'!$A$2:$A$137,0))} -> BOFU | H5: /emergency-exam | I5: Increase local leads
A6: Weeks 1–2 | B6: {=INDEX('Keyword Master Database'!$V$2:$V$137,MATCH(E6,'Keyword Master Database'!$A$2:$A$137,0))} -> High | C6: Page Optimization | D6: Root canals page: process, pain myths, recovery, CTA | E6: root canal rainsville al | F6: {=INDEX('Keyword Master Database'!$E$2:$E$137,MATCH(E6,'Keyword Master Database'!$A$2:$A$137,0))} -> Transactional | G6: {=INDEX('Keyword Master Database'!$F$2:$F$137,MATCH(E6,'Keyword Master Database'!$A$2:$A$137,0))} -> BOFU | H6: /root-canals | I6: Improve service page rankings
A7: Weeks 1–2 | B7: {=INDEX('Keyword Master Database'!$V$2:$V$137,MATCH(E7,'Keyword Master Database'!$A$2:$A$137,0))} -> High | C7: Page Optimization | D7: Dentures page: types, fitting process, insurance mention | E7: dentures rainsville al | F7: {=INDEX('Keyword Master Database'!$E$2:$E$137,MATCH(E7,'Keyword Master Database'!$A$2:$A$137,0))} -> Transactional | G7: {=INDEX('Keyword Master Database'!$F$2:$F$137,MATCH(E7,'Keyword Master Database'!$A$2:$A$137,0))} -> BOFU | H7: /dentures | I7: Improve service page rankings
A8: Weeks 1–2 | B8: {=INDEX('Keyword Master Database'!$V$2:$V$137,MATCH(E8,'Keyword Master Database'!$A$2:$A$137,0))} -> Medium | C8: Page Optimization | D8: Meet Dr. Emily Carter: credentials, philosophy, female-dentist positioning, Person schema | E8: female dentist rainsville al | F8: {=INDEX('Keyword Master Database'!$E$2:$E$137,MATCH(E8,'Keyword Master Database'!$A$2:$A$137,0))} -> Transactional | G8: {=INDEX('Keyword Master Database'!$F$2:$F$137,MATCH(E8,'Keyword Master Database'!$A$2:$A$137,0))} -> BOFU | H8: /meet-dr-emily-carter | I8: Build trust / E-E-A-T
A9: Weeks 3–4 | B9: {=INDEX('Keyword Master Database'!$V$2:$V$137,MATCH(E9,'Keyword Master Database'!$A$2:$A$137,0))} -> High | C9: Page Optimization | D9: Partial dentures page | E9: partial dentures rainsville al | F9: {=INDEX('Keyword Master Database'!$E$2:$E$137,MATCH(E9,'Keyword Master Database'!$A$2:$A$137,0))} -> Transactional | G9: {=INDEX('Keyword Master Database'!$F$2:$F$137,MATCH(E9,'Keyword Master Database'!$A$2:$A$137,0))} -> BOFU | H9: /partial-dentures | I9: Improve service page rankings
A10: Weeks 3–4 | B10: {=INDEX('Keyword Master Database'!$V$2:$V$137,MATCH(E10,'Keyword Master Database'!$A$2:$A$137,0))} -> High | C10: Page Optimization | D10: Crowns page | E10: dental crowns rainsville al | F10: {=INDEX('Keyword Master Database'!$E$2:$E$137,MATCH(E10,'Keyword Master Database'!$A$2:$A$137,0))} -> Transactional | G10: {=INDEX('Keyword Master Database'!$F$2:$F$137,MATCH(E10,'Keyword Master Database'!$A$2:$A$137,0))} -> BOFU | H10: /crowns | I10: Improve service page rankings
A11: Weeks 3–4 | B11: {=INDEX('Keyword Master Database'!$V$2:$V$137,MATCH(E11,'Keyword Master Database'!$A$2:$A$137,0))} -> High | C11: Page Optimization | D11: Bridges page | E11: dental bridges rainsville al | F11: {=INDEX('Keyword Master Database'!$E$2:$E$137,MATCH(E11,'Keyword Master Database'!$A$2:$A$137,0))} -> Transactional | G11: {=INDEX('Keyword Master Database'!$F$2:$F$137,MATCH(E11,'Keyword Master Database'!$A$2:$A$137,0))} -> BOFU | H11: /bridges | I11: Improve service page rankings
A12: Weeks 3–4 | B12: {=INDEX('Keyword Master Database'!$V$2:$V$137,MATCH(E12,'Keyword Master Database'!$A$2:$A$137,0))} -> High | C12: Page Optimization | D12: Veneers page | E12: veneers rainsville al | F12: {=INDEX('Keyword Master Database'!$E$2:$E$137,MATCH(E12,'Keyword Master Database'!$A$2:$A$137,0))} -> Transactional | G12: {=INDEX('Keyword Master Database'!$F$2:$F$137,MATCH(E12,'Keyword Master Database'!$A$2:$A$137,0))} -> BOFU | H12: /veneers | I12: Improve service page rankings
A13: Weeks 3–4 | B13: {=INDEX('Keyword Master Database'!$V$2:$V$137,MATCH(E13,'Keyword Master Database'!$A$2:$A$137,0))} -> High | C13: Page Optimization | D13: Fillings page | E13: dental fillings rainsville al | F13: {=INDEX('Keyword Master Database'!$E$2:$E$137,MATCH(E13,'Keyword Master Database'!$A$2:$A$137,0))} -> Transactional | G13: {=INDEX('Keyword Master Database'!$F$2:$F$137,MATCH(E13,'Keyword Master Database'!$A$2:$A$137,0))} -> BOFU | H13: /fillings | I13: Improve service page rankings
... A49: Month 6 | B49: {=INDEX('Keyword Master Database'!$V$2:$V$137,MATCH(E49,'Keyword Master Database'!$A$2:$A$137,0))} -> Low | C49: Blog Post | D49: How to Prevent Cavities: A Family Guide | E49: how to prevent cavities | F49: {=INDEX('Keyword Master Database'!$E$2:$E$137,MATCH(E49,'Keyword Master Database'!$A$2:$A$137,0))} -> Informational | G49: {=INDEX('Keyword Master Database'!$F$2:$F$137,MATCH(E49,'Keyword Master Database'!$A$2:$A$137,0))} -> TOFU | H49: /blog/how-to-prevent-cavities | I49: Build topical authority and feed service pages

Sheet Quick Wins
A1: Keyword | B1: Intent | C1: Funnel Stage | D1: Opportunity | E1: Reason | F1: Recommended Action | G1: Est. Monthly Volume | H1: Est. KD | I1: Priority Level
A2: emergency dentist rainsville al | B2: {=INDEX('Keyword Master Database'!$E$2:$E$137,MATCH(A2,'Keyword Master Database'!$A$2:$A$137,0))} -> Transactional | C2: {=INDEX('Keyword Master Database'!$F$2:$F$137,MATCH(A2,'Keyword Master Database'!$A$2:$A$137,0))} -> BOFU | D2: {=IF(AND(INDEX('Keyword Master Database'!$I$2:$I$137,MATCH(A2,'Keyword Master Database'!$A$2:$A$137,0))<=20,INDEX('Keyword Master Database'!$U$2:$U$137,MATCH(A2,'Keyword Master Database'!$A$2:$A$137,0))>=75),"High",IF(INDEX('Keyword Master Database'!$I$2:$I$137,MATCH(A2,'Keyword Master Database'!$A$2:$A$137,0))<=30,"Medium","Moderate"))} -> High | E2: Low KD, very high CPC, urgent intent. | F2: Rewrite /emergency-exam with symptoms, hours and a click-to-call CTA; add to GBP services. | G2: {=INDEX('Keyword Master Database'!$H$2:$H$137,MATCH(A2,'Keyword Master Database'!$A$2:$A$137,0))} -> 40 | H2: {=INDEX('Keyword Master Database'!$I$2:$I$137,MATCH(A2,'Keyword Master Database'!$A$2:$A$137,0))} -> 14 | I2: {=INDEX('Keyword Master Database'!$V$2:$V$137,MATCH(A2,'Keyword Master Database'!$A$2:$A$137,0))} -> High
A3: dental implants rainsville al | B3: {=INDEX('Keyword Master Database'!$E$2:$E$137,MATCH(A3,'Keyword Master Database'!$A$2:$A$137,0))} -> Transactional | C3: {=INDEX('Keyword Master Database'!$F$2:$F$137,MATCH(A3,'Keyword Master Database'!$A$2:$A$137,0))} -> BOFU | D3: {=IF(AND(INDEX('Keyword Master Database'!$I$2:$I$137,MATCH(A3,'Keyword Master Database'!$A$2:$A$137,0))<=20,INDEX('Keyword Master Database'!$U$2:$U$137,MATCH(A3,'Keyword Master Database'!$A$2:$A$137,0))>=75),"High",IF(INDEX('Keyword Master Database'!$I$2:$I$137,MATCH(A3,'Keyword Master Database'!$A$2:$A$137,0))<=30,"Medium","Moderate"))} -> High | E3: Highest-value service with low local competition. | F3: Expand /implants copy, add FAQ schema, cost-range section and BCBS mention. | G3: {=INDEX('Keyword Master Database'!$H$2:$H$137,MATCH(A3,'Keyword Master Database'!$A$2:$A$137,0))} -> 40 | H3: {=INDEX('Keyword Master Database'!$I$2:$I$137,MATCH(A3,'Keyword Master Database'!$A$2:$A$137,0))} -> 16 | I3: {=INDEX('Keyword Master Database'!$V$2:$V$137,MATCH(A3,'Keyword Master Database'!$A$2:$A$137,0))} -> High
A4: root canal rainsville al | B4: {=INDEX('Keyword Master Database'!$E$2:$E$137,MATCH(A4,'Keyword Master Database'!$A$2:$A$137,0))} -> Transactional | C4: {=INDEX('Keyword Master Database'!$F$2:$F$137,MATCH(A4,'Keyword Master Database'!$A$2:$A$137,0))} -> BOFU | D4: {=IF(AND(INDEX('Keyword Master Database'!$I$2:$I$137,MATCH(A4,'Keyword Master Database'!$A$2:$A$137,0))<=20,INDEX('Keyword Master Database'!$U$2:$U$137,MATCH(A4,'Keyword Master Database'!$A$2:$A$137,0))>=75),"High",IF(INDEX('Keyword Master Database'!$I$2:$I$137,MATCH(A4,'Keyword Master Database'!$A$2:$A$137,0))<=30,"Medium","Moderate"))} -> High | E4: High CPC and low KD for the local modifier. | F4: Optimize title/H1/body for the local keyword; add recovery FAQ. | G4: {=INDEX('Keyword Master Database'!$H$2:$H$137,MATCH(A4,'Keyword Master Database'!$A$2:$A$137,0))} -> 30 | H4: {=INDEX('Keyword Master Database'!$I$2:$I$137,MATCH(A4,'Keyword Master Database'!$A$2:$A$137,0))} -> 12 | I4: {=INDEX('Keyword Master Database'!$V$2:$V$137,MATCH(A4,'Keyword Master Database'!$A$2:$A$137,0))} -> High
A5: dentist in rainsville al | B5: {=INDEX('Keyword Master Database'!$E$2:$E$137,MATCH(A5,'Keyword Master Database'!$A$2:$A$137,0))} -> Transactional | C5: {=INDEX('Keyword Master Database'!$F$2:$F$137,MATCH(A5,'Keyword Master Database'!$A$2:$A$137,0))} -> BOFU | D5: {=IF(AND(INDEX('Keyword Master Database'!$I$2:$I$137,MATCH(A5,'Keyword Master Database'!$A$2:$A$137,0))<=20,INDEX('Keyword Master Database'!$U$2:$U$137,MATCH(A5,'Keyword Master Database'!$A$2:$A$137,0))>=75),"High",IF(INDEX('Keyword Master Database'!$I$2:$I$137,MATCH(A5,'Keyword Master Database'!$A$2:$A$137,0))<=30,"Medium","Moderate"))} -> High | E5: Core money term; current homepage lacks a keyword H1 and body copy. | F5: Rewrite homepage title (<60 chars), H1 and add location + service copy. | G5: {=INDEX('Keyword Master Database'!$H$2:$H$137,MATCH(A5,'Keyword Master Database'!$A$2:$A$137,0))} -> 110 | H5: {=INDEX('Keyword Master Database'!$I$2:$I$137,MATCH(A5,'Keyword Master Database'!$A$2:$A$137,0))} -> 14 | I5: {=INDEX('Keyword Master Database'!$V$2:$V$137,MATCH(A5,'Keyword Master Database'!$A$2:$A$137,0))} -> Critical
A6: dentures rainsville al | B6: {=INDEX('Keyword Master Database'!$E$2:$E$137,MATCH(A6,'Keyword Master Database'!$A$2:$A$137,0))} -> Transactional | C6: {=INDEX('Keyword Master Database'!$F$2:$F$137,MATCH(A6,'Keyword Master Database'!$A$2:$A$137,0))} -> BOFU | D6: {=IF(AND(INDEX('Keyword Master Database'!$I$2:$I$137,MATCH(A6,'Keyword Master Database'!$A$2:$A$137,0))<=20,INDEX('Keyword Master Database'!$U$2:$U$137,MATCH(A6,'Keyword Master Database'!$A$2:$A$137,0))>=75),"High",IF(INDEX('Keyword Master Database'!$I$2:$I$137,MATCH(A6,'Keyword Master Database'!$A$2:$A$137,0))<=30,"Medium","Moderate"))} -> High | E6: Aging local population; low KD. | F6: Optimize /dentures; link to partial dentures and implants. | G6: {=INDEX('Keyword Master Database'!$H$2:$H$137,MATCH(A6,'Keyword Master Database'!$A$2:$A$137,0))} -> 30 | H6: {=INDEX('Keyword Master Database'!$I$2:$I$137,MATCH(A6,'Keyword Master Database'!$A$2:$A$137,0))} -> 12 | I6: {=INDEX('Keyword Master Database'!$V$2:$V$137,MATCH(A6,'Keyword Master Database'!$A$2:$A$137,0))} -> High
A7: partial dentures rainsville al | B7: {=INDEX('Keyword Master Database'!$E$2:$E$137,MATCH(A7,'Keyword Master Database'!$A$2:$A$137,0))} -> Transactional | C7: {=INDEX('Keyword Master Database'!$F$2:$F$137,MATCH(A7,'Keyword Master Database'!$A$2:$A$137,0))} -> BOFU | D7: {=IF(AND(INDEX('Keyword Master Database'!$I$2:$I$137,MATCH(A7,'Keyword Master Database'!$A$2:$A$137,0))<=20,INDEX('Keyword Master Database'!$U$2:$U$137,MATCH(A7,'Keyword Master Database'!$A$2:$A$137,0))>=75),"High",IF(INDEX('Keyword Master Database'!$I$2:$I$137,MATCH(A7,'Keyword Master Database'!$A$2:$A$137,0))<=30,"Medium","Moderate"))} -> High | E7: Very low competition. | F7: Optimize /partial-dentures with comparison table and FAQ. | G7: {=INDEX('Keyword Master Database'!$H$2:$H$137,MATCH(A7,'Keyword Master Database'!$A$2:$A$137,0))} -> 20 | H7: {=INDEX('Keyword Master Database'!$I$2:$I$137,MATCH(A7,'Keyword Master Database'!$A$2:$A$137,0))} -> 11 | I7: {=INDEX('Keyword Master Database'!$V$2:$V$137,MATCH(A7,'Keyword Master Database'!$A$2:$A$137,0))} -> High
A8: female dentist rainsville al | B8: {=INDEX('Keyword Master Database'!$E$2:$E$137,MATCH(A8,'Keyword Master Database'!$A$2:$A$137,0))} -> Transactional | C8: {=INDEX('Keyword Master Database'!$F$2:$F$137,MATCH(A8,'Keyword Master Database'!$A$2:$A$137,0))} -> BOFU | D8: {=IF(AND(INDEX('Keyword Master Database'!$I$2:$I$137,MATCH(A8,'Keyword Master Database'!$A$2:$A$137,0))<=20,INDEX('Keyword Master Database'!$U$2:$U$137,MATCH(A8,'Keyword Master Database'!$A$2:$A$137,0))>=75),"High",IF(INDEX('Keyword Master Database'!$I$2:$I$137,MATCH(A8,'Keyword Master Database'!$A$2:$A$137,0))<=30,"Medium","Moderate"))} -> Medium | E8: Differentiator already in title tag; almost no competition. | F8: Add a female-dentist section and Person schema on the Dr. Emily Carter page. | G8: {=INDEX('Keyword Master Database'!$H$2:$H$137,MATCH(A8,'Keyword Master Database'!$A$2:$A$137,0))} -> 10 | H8: {=INDEX('Keyword Master Database'!$I$2:$I$137,MATCH(A8,'Keyword Master Database'!$A$2:$A$137,0))} -> 8 | I8: {=INDEX('Keyword Master Database'!$V$2:$V$137,MATCH(A8,'Keyword Master Database'!$A$2:$A$137,0))} -> Medium
A9: silver diamine fluoride rainsville al | B9: {=INDEX('Keyword Master Database'!$E$2:$E$137,MATCH(A9,'Keyword Master Database'!$A$2:$A$137,0))} -> Transactional | C9: {=INDEX('Keyword Master Database'!$F$2:$F$137,MATCH(A9,'Keyword Master Database'!$A$2:$A$137,0))} -> BOFU | D9: {=IF(AND(INDEX('Keyword Master Database'!$I$2:$I$137,MATCH(A9,'Keyword Master Database'!$A$2:$A$137,0))<=20,INDEX('Keyword Master Database'!$U$2:$U$137,MATCH(A9,'Keyword Master Database'!$A$2:$A$137,0))>=75),"High",IF(INDEX('Keyword Master Database'!$I$2:$I$137,MATCH(A9,'Keyword Master Database'!$A$2:$A$137,0))<=30,"Medium","Moderate"))} -> Medium | E9: Niche service few local practices promote. | F9: Strengthen /silver-diamine-fluoride; add Q&A and GBP service. | G9: {=INDEX('Keyword Master Database'!$H$2:$H$137,MATCH(A9,'Keyword Master Database'!$A$2:$A$137,0))} -> 10 | H9: {=INDEX('Keyword Master Database'!$I$2:$I$137,MATCH(A9,'Keyword Master Database'!$A$2:$A$137,0))} -> 6 | I9: {=INDEX('Keyword Master Database'!$V$2:$V$137,MATCH(A9,'Keyword Master Database'!$A$2:$A$137,0))} -> Medium
A10: dentist that accepts blue cross blue shield rainsville al | B10: {=INDEX('Keyword Master Database'!$E$2:$E$137,MATCH(A10,'Keyword Master Database'!$A$2:$A$137,0))} -> Transactional | C10: {=INDEX('Keyword Master Database'!$F$2:$F$137,MATCH(A10,'Keyword Master Database'!$A$2:$A$137,0))} -> BOFU | D10: {=IF(AND(INDEX('Keyword Master Database'!$I$2:$I$137,MATCH(A10,'Keyword Master Database'!$A$2:$A$137,0))<=20,INDEX('Keyword Master Database'!$U$2:$U$137,MATCH(A10,'Keyword Master Database'!$A$2:$A$137,0))>=75),"High",IF(INDEX('Keyword Master Database'!$I$2:$I$137,MATCH(A10,'Keyword Master Database'!$A$2:$A$137,0))<=30,"Medium","Moderate"))} -> High | E10: Practice is in-network with BCBS of Alabama but no page says so. | F10: Create /dental-insurance-payment and link from homepage. | G10: {=INDEX('Keyword Master Database'!$H$2:$H$137,MATCH(A10,'Keyword Master Database'!$A$2:$A$137,0))} -> 20 | H10: {=INDEX('Keyword Master Database'!$I$2:$I$137,MATCH(A10,'Keyword Master Database'!$A$2:$A$137,0))} -> 12 | I10: {=INDEX('Keyword Master Database'!$V$2:$V$137,MATCH(A10,'Keyword Master Database'!$A$2:$A$137,0))} -> High
A11: dentist dekalb county al | B11: {=INDEX('Keyword Master Database'!$E$2:$E$137,MATCH(A11,'Keyword Master Database'!$A$2:$A$137,0))} -> Transactional | C11: {=INDEX('Keyword Master Database'!$F$2:$F$137,MATCH(A11,'Keyword Master Database'!$A$2:$A$137,0))} -> BOFU | D11: {=IF(AND(INDEX('Keyword Master Database'!$I$2:$I$137,MATCH(A11,'Keyword Master Database'!$A$2:$A$137,0))<=20,INDEX('Keyword Master Database'!$U$2:$U$137,MATCH(A11,'Keyword Master Database'!$A$2:$A$137,0))>=75),"High",IF(INDEX('Keyword Master Database'!$I$2:$I$137,MATCH(A11,'Keyword Master Database'!$A$2:$A$137,0))<=30,"Medium","Moderate"))} -> High | E11: Regional modifier with low KD. | F11: Create a service-area hub page listing towns served. | G11: {=INDEX('Keyword Master Database'!$H$2:$H$137,MATCH(A11,'Keyword Master Database'!$A$2:$A$137,0))} -> 30 | H11: {=INDEX('Keyword Master Database'!$I$2:$I$137,MATCH(A11,'Keyword Master Database'!$A$2:$A$137,0))} -> 15 | I11: {=INDEX('Keyword Master Database'!$V$2:$V$137,MATCH(A11,'Keyword Master Database'!$A$2:$A$137,0))} -> High
A12: dentist fort payne al | B12: {=INDEX('Keyword Master Database'!$E$2:$E$137,MATCH(A12,'Keyword Master Database'!$A$2:$A$137,0))} -> Transactional | C12: {=INDEX('Keyword Master Database'!$F$2:$F$137,MATCH(A12,'Keyword Master Database'!$A$2:$A$137,0))} -> BOFU | D12: {=IF(AND(INDEX('Keyword Master Database'!$I$2:$I$137,MATCH(A12,'Keyword Master Database'!$A$2:$A$137,0))<=20,INDEX('Keyword Master Database'!$U$2:$U$137,MATCH(A12,'Keyword Master Database'!$A$2:$A$137,0))>=75),"High",IF(INDEX('Keyword Master Database'!$I$2:$I$137,MATCH(A12,'Keyword Master Database'!$A$2:$A$137,0))<=30,"Medium","Moderate"))} -> Medium | E12: Largest nearby town with real volume at moderate KD. | F12: Build a unique Fort Payne page (drive time, directions, testimonials). | G12: {=INDEX('Keyword Master Database'!$H$2:$H$137,MATCH(A12,'Keyword Master Database'!$A$2:$A$137,0))} -> 210 | H12: {=INDEX('Keyword Master Database'!$I$2:$I$137,MATCH(A12,'Keyword Master Database'!$A$2:$A$137,0))} -> 24 | I12: {=INDEX('Keyword Master Database'!$V$2:$V$137,MATCH(A12,'Keyword Master Database'!$A$2:$A$137,0))} -> High
A13: dentist scottsboro al | B13: {=INDEX('Keyword Master Database'!$E$2:$E$137,MATCH(A13,'Keyword Master Database'!$A$2:$A$137,0))} -> Transactional | C13: {=INDEX('Keyword Master Database'!$F$2:$F$137,MATCH(A13,'Keyword Master Database'!$A$2:$A$137,0))} -> BOFU | D13: {=IF(AND(INDEX('Keyword Master Database'!$I$2:$I$137,MATCH(A13,'Keyword Master Database'!$A$2:$A$137,0))<=20,INDEX('Keyword Master Database'!$U$2:$U$137,MATCH(A13,'Keyword Master Database'!$A$2:$A$137,0))>=75),"High",IF(INDEX('Keyword Master Database'!$I$2:$I$137,MATCH(A13,'Keyword Master Database'!$A$2:$A$137,0))<=30,"Medium","Moderate"))} -> Medium | E13: Large Jackson County town, moderate KD. | F13: Build a unique Scottsboro page. | G13: {=INDEX('Keyword Master Database'!$H$2:$H$137,MATCH(A13,'Keyword Master Database'!$A$2:$A$137,0))} -> 170 | H13: {=INDEX('Keyword Master Database'!$I$2:$I$137,MATCH(A13,'Keyword Master Database'!$A$2:$A$137,0))} -> 24 | I13: {=INDEX('Keyword Master Database'!$V$2:$V$137,MATCH(A13,'Keyword Master Database'!$A$2:$A$137,0))} -> High
... A17: carter family dentistry reviews | B17: {=INDEX('Keyword Master Database'!$E$2:$E$137,MATCH(A17,'Keyword Master Database'!$A$2:$A$137,0))} -> Navigational | C17: {=INDEX('Keyword Master Database'!$F$2:$F$137,MATCH(A17,'Keyword Master Database'!$A$2:$A$137,0))} -> MOFU | D17: {=IF(AND(INDEX('Keyword Master Database'!$I$2:$I$137,MATCH(A17,'Keyword Master Database'!$A$2:$A$137,0))<=20,INDEX('Keyword Master Database'!$U$2:$U$137,MATCH(A17,'Keyword Master Database'!$A$2:$A$137,0))>=75),"High",IF(INDEX('Keyword Master Database'!$I$2:$I$137,MATCH(A17,'Keyword Master Database'!$A$2:$A$137,0))<=30,"Medium","Moderate"))} -> Medium | E17: Branded, easy win and trust signal. | F17: Embed Google reviews and add review schema on /testimonials. | G17: {=INDEX('Keyword Master Database'!$H$2:$H$137,MATCH(A17,'Keyword Master Database'!$A$2:$A$137,0))} -> 40 | H17: {=INDEX('Keyword Master Database'!$I$2:$I$137,MATCH(A17,'Keyword Master Database'!$A$2:$A$137,0))} -> 6 | I17: {=INDEX('Keyword Master Database'!$V$2:$V$137,MATCH(A17,'Keyword Master Database'!$A$2:$A$137,0))} -> Medium

Sheet Methodology
B1: Methodology, Scoring Model & Data Notes
B3: Priority Score weights (SEO Priority Score = weighted 1–5 score × 20 → 0–100 scale)
B4: Factor | C4: Weight | D4: Basis
B5: Business Value | C5: 0.25 | D5: Revenue potential of the service (implants, root canals and emergency visits rank highest).
B6: Search Demand | C6: 0.15 | D6: Looked up from estimated monthly volume (table below).
B7: Ranking Opportunity | C7: 0.2 | D7: Looked up from estimated keyword difficulty (table below).
B8: Intent Strength | C8: 0.15 | D8: Looked up from search intent (table below).
B9: Conversion Potential | C9: 0.15 | D9: Likelihood the searcher books/calls: Transactional 5, Navigational 4, Commercial 3, Informational 1.
B10: Topical Importance | C10: 0.1 | D10: Role of the keyword in building the service-silo authority.
B11: Total (must equal 1.00) | C11: =SUM(C5:C10) -> 1
B13: Search Demand score – minimum monthly volume → score (calibrated for a small rural market)
B14: Min. monthly volume | C14: Score | D14: Remarks
B15: 0 | C15: 1
B16: 20 | C16: 2
B17: 50 | C17: 3
B18: 200 | C18: 4
B19: 1000 | C19: 5
B21: Ranking Opportunity score – minimum KD → score (lower KD = better opportunity)
B22: Min. KD | C22: Score | D22: Remarks
B23: 0 | C23: 5
B24: 16 | C24: 4
B25: 26 | C25: 3
B26: 41 | C26: 2
B27: 56 | C27: 1
B29: Intent Strength score
B30: Search intent | C30: Score | D30: Remarks
B31: Transactional | C31: 5
B32: Commercial | C32: 4
B33: Navigational | C33: 3
B34: Informational | C34: 2
B36: Priority level – minimum score → level
B37: Min. score | C37: Level | D37: Remarks
B38: 0 | C38: Optional
B39: 40 | C39: Low
B40: 60 | C40: Medium
B41: 75 | C41: High
B42: 90 | C42: Critical
B44: Keyword difficulty label – minimum KD → label
B45: Min. KD | C45: Label | D45: Remarks
B46: 0 | C46: Easy
B47: 21 | C47: Moderate
B48: 41 | C48: Competitive
B49: 71 | C49: Very Competitive
