Workbook

Sheet Cover
B2: KEYWORD RESEARCH & STRATEGY WORKBOOK
B3: Drs. Limbaugh & Stephenson Family and Implant Dentistry
B4: Huntsville, Alabama, United States
B5: Prepared By: Md. Abdul Alim | Local SEO & AI Search Optimization Consultant
B9: KEYWORD RESEARCH DASHBOARD
B10: Total Keywords Researched | D10: Keyword Clusters | F10: Est. Monthly Search Volume | H10: Local / National Keywords | J10: Average Keyword Difficulty
B11: =COUNTA('Keyword Master Database'!$A$2:$A$227) -> 226 | D11: =COUNTA('Keyword Clusters'!$A$2:$A$41) -> 40 | F11: =SUM('Keyword Master Database'!$H$2:$H$227) -> 332330 | H11: =SUMPRODUCT(--((ISNUMBER(SEARCH("huntsville",'Keyword Master Database'!$A$2:$A$227))+ISNUMBER(SEARCH("near me",'Keyword Master Database'!$A$2:$A$227))+ISNUMBER(SEARCH("madison al",'Keyword Master Database'!$A$2:$A$227))+ISNUMBER(SEARCH("hampton cove",'Keyword Master Database'!$A$2:$A$227))+ISNUMBER(SEARCH("35802",'Keyword Master Database'!$A$2:$A$227))+ISNUMBER(SEARCH("alabama",'Keyword Master Database'!$A$2:$A$227)))>0))&" / "&(COUNTA('Keyword Master Database'!$A$2:$A$227)-SUMPRODUCT(--((ISNUMBER(SEARCH("huntsville",'Keyword Master Database'!$A$2:$A$227))+ISNUMBER(SEARCH("near me",'Keyword Master Database'!$A$2:$A$227))+ISNUMBER(SEARCH("madison al",'Keyword Master Database'!$A$2:$A$227))+ISNUMBER(SEARCH("hampton cove",'Keyword Master Database'!$A$2:$A$227))+ISNUMBER(SEARCH("35802",'Keyword Master Database'!$A$2:$A$227))+ISNUMBER(SEARCH("alabama",'Keyword Master Database'!$A$2:$A$227)))>0))) -> 127 / 99 | J11: =ROUND(AVERAGE('Keyword Master Database'!$J$2:$J$227),1) -> 30.4
B13: Critical + High Priority Keywords | D13: Pages Mapped | F13: New Pages Recommended | H13: Internal Links Planned | J13: Content Opportunities
B14: =COUNTIF('Keyword Master Database'!$W$2:$W$227,"Critical")+COUNTIF('Keyword Master Database'!$W$2:$W$227,"High") -> 109 | D14: =COUNTA('Keyword Mapping'!$A$2:$A$46) -> 45 | F14: =COUNTIF('Keyword Mapping'!$G$2:$G$46,"New") -> 23 | H14: =COUNTA('Internal Linking Blueprint'!$A$2:$A$123) -> 122 | J14: =COUNTA('Content Roadmap'!$D$2:$D$40) -> 39
B17: KEYWORD DISTRIBUTION ANALYSIS
B18: Search Intent | C18: Keywords | D18: Share | E18: Priority Level | F18: Keywords | G18: Share | H18: Funnel Stage | I18: Keywords | J18: Share | K18: Remark
B19: Informational | C19: =COUNTIF('Keyword Master Database'!$E$2:$E$227,B19) -> 60 | D19: =IFERROR(C19/SUM(C$19:C$22),0) -> 0.26548673 | E19: Critical | F19: =COUNTIF('Keyword Master Database'!$W$2:$W$227,E19) -> 12 | G19: =IFERROR(F19/SUM(F$19:F$22),0) -> 0.053097345 | H19: TOFU | I19: =COUNTIF('Keyword Master Database'!$F$2:$F$227,H19) -> 60 | J19: =IFERROR(I19/SUM(I$19:I$21),0) -> 0.26548673
B20: Navigational | C20: =COUNTIF('Keyword Master Database'!$E$2:$E$227,B20) -> 13 | D20: =IFERROR(C20/SUM(C$19:C$22),0) -> 0.057522124 | E20: High | F20: =COUNTIF('Keyword Master Database'!$W$2:$W$227,E20) -> 97 | G20: =IFERROR(F20/SUM(F$19:F$22),0) -> 0.42920354 | H20: MOFU | I20: =COUNTIF('Keyword Master Database'!$F$2:$F$227,H20) -> 57 | J20: =IFERROR(I20/SUM(I$19:I$21),0) -> 0.25221239
B21: Commercial | C21: =COUNTIF('Keyword Master Database'!$E$2:$E$227,B21) -> 50 | D21: =IFERROR(C21/SUM(C$19:C$22),0) -> 0.22123894 | E21: Medium | F21: =COUNTIF('Keyword Master Database'!$W$2:$W$227,E21) -> 47 | G21: =IFERROR(F21/SUM(F$19:F$22),0) -> 0.2079646 | H21: BOFU | I21: =COUNTIF('Keyword Master Database'!$F$2:$F$227,H21) -> 109 | J21: =IFERROR(I21/SUM(I$19:I$21),0) -> 0.48230089
B22: Transactional | C22: =COUNTIF('Keyword Master Database'!$E$2:$E$227,B22) -> 103 | D22: =IFERROR(C22/SUM(C$19:C$22),0) -> 0.45575221 | E22: Low | F22: =COUNTIF('Keyword Master Database'!$W$2:$W$227,E22) -> 70 | G22: =IFERROR(F22/SUM(F$19:F$22),0) -> 0.30973451
B25: DISTRIBUTION CHART
B42: WORKBOOK CONTENTS
B43: Sheet Name | E43: Purpose
B44: Business Analysis | E44: Business information, website findings, SEO goals and scoring model
B45: Keyword Master Database | E45: Complete keyword research database with metrics and strategy
B46: Keyword Clusters | E46: Keyword grouping and semantic organization
B47: Competitor Analysis | E47: Competitor keyword insights and opportunities
B48: Keyword Mapping | E48: Keyword to page targeting strategy
B49: Topical Authority Map | E49: Content authority planning
B50: SEO Silo Architecture | E50: Website structure planning
B51: Internal Linking Blueprint | E51: Internal authority flow strategy
B52: Content Roadmap | E52: Future content creation strategy
B53: Quick Wins | E53: Immediate SEO opportunities

Sheet Business Analysis
A1: BUSINESS ANALYSIS
A4: BUSINESS PROFILE
A5: Business Name | B5: Drs. Limbaugh & Stephenson Family and Implant Dentistry
A6: Website | B6: https://familyandimplantdentists.com/
A7: Industry | B7: Dental Clinic (family, implant and cosmetic dentistry)
A8: Country | B8: United States
A9: Target Location | B9: 4605 Bellewood Cir SE, Huntsville, AL 35802, United States
A10: Phone | B10: (256) 539-6634
A11: Target Audience
A12: Services | B12: Fillings; Tooth Whitening; Sealants; Dental Crowns; Bridges; Veneers; Dental Implants; Dentures; Root Canals; Extractions; Full Mouth Reconstruction
A13: Products | B13: None - service-based practice (no physical products)
A14: Primary Business Goals | B14: Generate more local leads; increase organic traffic; improve service page rankings; build topical authority; rank in AI search
A15: Primary SEO Focus | B15: Local SEO + AI SEO (Generative Engine Optimization)
A16: Prepared By | B16: Md. Abdul Alim - Local SEO & AI Search Optimization Consultant
A19: WEBSITE ANALYSIS - KEYWORD TARGETING, STRENGTHS & GAPS
A20: Area | B20: Finding (observed on website) | C20: SEO Opportunity | D20: Priority
A21: Homepage title / meta | B21: Title tag is 'Home - Limbaugh & Stephenson' - no service or city keyword. H1 reads 'Comprehensive Dental Care'. | C21: Rewrite title, H1 and meta description around 'Dentist in Huntsville, AL' + family/implant positioning. | D21: High
A22: Homepage content | B22: Includes 'Your Huntsville Dentists' section, FAQ-style answers (implant candidacy, children, payment) and three testimonials. | C22: Turn existing Q&A into FAQPage schema; add services grid with city-modified anchors; add review schema. | D22: High
A23: Service pages | B23: All 11 services have dedicated URLs (e.g. /tooth-implants/, /veneers-for-teeth/, /full-mouth-reconstruction/). Implants page title is 'Dental Implants - Limbaugh & Stephenson' - no location modifier. | C23: Add 'Huntsville, AL' modifiers, FAQs, cost ranges and procedure steps to every service page; target ~800-1,200 words. | D23: High
A24: Dental implants page | B24: Covers single-tooth, implant-supported bridges and implant-supported dentures (lower dentures with as few as two implants). No cost, candidacy, recovery or FAQ sections. Page metadata shows 2019 modification. | C24: Expand pillar page + build supporting cluster (cost, candidacy, recovery, comparisons, implant-supported dentures). | D24: High
A25: Blog / content | B25: Blog contains only two posts: 'Cosmetic Dentistry: Let Your Smile Tell the Story' and 'Professional Teeth Whitening: Say Cheese!' (both 2019-era). | C25: Major topical-authority gap - 23 new pages planned in the Content Roadmap. | D25: High
A26: Missing service pages | B26: Homepage references Cleanings & Exams and pediatric care, but neither has a dedicated page; no cosmetic or family dentistry hub; no emergency page. | C26: Create Family Dentistry, Cleanings & Exams, Pediatric, Emergency (confirm availability), Cosmetic Hub and Restorative Hub. | D26: High
A27: Local signals | B27: NAP shown in footer: 4605 Bellewood Circle, Huntsville, AL 35802; (256) 539-6634. No area/neighborhood landing pages. | C27: Add Southeast Huntsville/35802, Hampton Cove and Madison service-area pages; keep NAP identical to Google Business Profile. | D27: Medium
A28: Financing & insurance | B28: /financial-arrangements/ lists CareCredit, Citi Health Card, major cards and claim submission. | C28: Rewrite to target 'dentist that accepts insurance Huntsville' and financing queries; link from every high-ticket service page. | D28: Medium
A29: Trust / E-E-A-T | B29: Doctor profile pages exist (Dr. Limbaugh, Dr. Stephenson) and an office tour page. | C29: Add credentials, Person schema, memberships, before/after gallery and review feeds. | D29: Medium
A30: Technical notes | B30: WordPress 6.8 on Dentricity; indexable (robots index, follow). Viewport meta disables user zoom (maximum-scale=1.0, user-scalable=0). | C30: Remove zoom restriction (accessibility), add Dentist/LocalBusiness schema, validate Core Web Vitals. | D30: Medium
A31: Competitor set review | B31: Of 5 supplied competitors, only 2 operate in the Huntsville area (smilehsv.com; huntsvilleperio.com in Madison). The other 3 are out-of-market (Conroe TX; Indianapolis IN; North Providence RI). | C31: Added 4 Huntsville organic competitors found via SERP research - see Competitor Analysis. | D31: Info
A34: SCORING MODEL (SEO PRIORITY SCORE)
A35: Score Component (1-5) | B35: How It Is Measured | C35: Calculation in Workbook | D35: Weight
A36: Business Value Score | B36: Revenue / appointment value of the service and funnel stage | C36: Assigned by service value (implants, full mouth, veneers = highest); reduced 1 point at MOFU and 2 at TOFU | D36: 0.25
A37: Search Demand Score | B37: Estimated monthly search volume | C37: Formula: >=2,000 = 5; >=800 = 4; >=300 = 3; >=100 = 2; else 1 | D37: 0.1
A38: Ranking Opportunity Score | B38: Realistic ability to rank given SERP difficulty | C38: Formula from KD (local-market calibration): <=25 = 5; <=35 = 4; <=45 = 3; <=60 = 2; else 1 | D38: 0.2
A39: Intent Strength Score | B39: How close the searcher is to taking action | C39: Transactional 5; Navigational 4; Commercial 3-4 (4 if local); Informational 1-2 | D39: 0.15
A40: Conversion Potential Score | B40: Likelihood of generating a lead or appointment | C40: BOFU transactional 5; local commercial 4; informational 1-2 | D40: 0.2
A41: Topical Importance Score | B41: Importance for building topical authority | C41: Cluster importance; primary keywords +1 | D41: 0.1
A42: Total Weight | D42: =SUM(D36:D41) -> 1
A43: SEO Priority Score = ROUND((Business Value x w1 + Demand x w2 + Opportunity x w3 + Intent x w4 + Conversion x w5 + Topical x w6) / 5 x 100, 0). Weights in blue are editable inputs.
A46: Priority Level | B46: SEO Priority Score | C46: Meaning
A47: Critical | B47: 90 - 100 | C47: Build / optimize first - highest revenue + ranking potential
A48: High | B48: 75 - 89 | C48: Core targets for months 1-3
A49: Medium | B49: 60 - 74 | C49: Support content and secondary pages
A50: Low | B50: 40 - 59 | C50: Long-term / opportunistic
A51: Optional | B51: Below 40 | C51: Monitor only
A54: METHODOLOGY & ASSUMPTIONS
A55: - Search volume, keyword difficulty (KD) and CPC are portfolio ESTIMATES (sources labelled 'SEO Market Estimate', 'SERP Competition Analysis' and 'Commercial Intent Analysis'). They are not exports from Semrush, Ahrefs or Google Keyword Planner and should be validated with a live tool before client forecasting.
A56: - Local volumes are calibrated to a mid-sized U.S. metro (Huntsville, AL); national informational keywords are included for topical authority and AI-search coverage and carry much higher volume and KD.
A57: - Estimated Monthly Search Volume on the Cover is the simple sum of all keywords and overlaps across closely related terms - treat it as a demand index, not a traffic forecast.
A58: - 'Ranking Competitors' lists the typical SERP landscape (local practices for local terms; health publishers for informational terms) and should be confirmed with live SERP checks.
A59: - Services flagged VERIFY (emergency dentistry, wisdom-tooth removal, implant-supported denture page, pediatric positioning) were inferred from the website or market norms and must be confirmed with the practice before publishing.
A60: - Target URLs for new pages are recommended slugs; confirm CMS (Dentricity/WordPress) constraints. Existing URLs were taken from the live site navigation.
A61: - Search intent is assigned once per keyword (Informational, Navigational, Commercial or Transactional); funnel stage: TOFU = awareness, MOFU = comparison, BOFU = ready to book.

Sheet Keyword Master Database
A1: Keyword | B1: Keyword Type | C1: Parent Topic | D1: Cluster | E1: Search Intent | F1: Funnel Stage | G1: Primary/Secondary | H1: Search Volume | I1: Volume Source | J1: Estimated KD | K1: KD Source | L1: Estimated CPC | M1: CPC Source | N1: SERP Competition | O1: Ranking Competitors | P1: Business Value Score (1-5) | Q1: Search Demand Score (1-5) | R1: Ranking Opportunity Score (1-5) | S1: Intent Strength Score (1-5) | T1: Conversion Potential Score (1-5) | U1: Topical Importance Score (1-5) | V1: SEO Priority Score | W1: Priority Level | X1: Target URL | Y1: Recommended Action | Z1: Notes
A2: limbaugh and stephenson dentistry | B2: Brand | C2: Brand | D2: Brand & Practice Name | E2: Navigational | F2: BOFU | G2: Primary | H2: 90 | I2: SEO Market Estimate | J2: 6 | K2: SERP Competition Analysis | L2: 4.2 | M2: Commercial Intent Analysis | N2: =IF(J2<=20,"Low",IF(J2<=40,"Moderate",IF(J2<=70,"Competitive","Very Competitive"))) -> Low | O2: familyandimplantdentists.com (own); Healthgrades; Yelp; Facebook | P2: 5 | Q2: =IF(H2>=2000,5,IF(H2>=800,4,IF(H2>=300,3,IF(H2>=100,2,1)))) -> 1 | R2: =IF(J2<=25,5,IF(J2<=35,4,IF(J2<=45,3,IF(J2<=60,2,1)))) -> 5 | S2: 4 | T2: 5 | U2: 5 | V2: =ROUND((P2*'Business Analysis'!$D$36+Q2*'Business Analysis'!$D$37+R2*'Business Analysis'!$D$38+S2*'Business Analysis'!$D$39+T2*'Business Analysis'!$D$40+U2*'Business Analysis'!$D$41)/5*100,0) -> 89 | W2: =IF(V2>=90,"Critical",IF(V2>=75,"High",IF(V2>=60,"Medium",IF(V2>=40,"Low","Optional")))) -> High | X2: / | Y2: Optimize | Z2: Brand SERP control - own the knowledge panel, reviews and sitelinks.
A3: drs limbaugh and stephenson huntsville al | B3: Brand | C3: Brand | D3: Brand & Practice Name | E3: Navigational | F3: BOFU | G3: Secondary | H3: 50 | I3: SEO Market Estimate | J3: 5 | K3: SERP Competition Analysis | L3: 3.8 | M3: Commercial Intent Analysis | N3: =IF(J3<=20,"Low",IF(J3<=40,"Moderate",IF(J3<=70,"Competitive","Very Competitive"))) -> Low | O3: familyandimplantdentists.com (own); Healthgrades; Yelp; Facebook | P3: 5 | Q3: =IF(H3>=2000,5,IF(H3>=800,4,IF(H3>=300,3,IF(H3>=100,2,1)))) -> 1 | R3: =IF(J3<=25,5,IF(J3<=35,4,IF(J3<=45,3,IF(J3<=60,2,1)))) -> 5 | S3: 4 | T3: 5 | U3: 4 | V3: =ROUND((P3*'Business Analysis'!$D$36+Q3*'Business Analysis'!$D$37+R3*'Business Analysis'!$D$38+S3*'Business Analysis'!$D$39+T3*'Business Analysis'!$D$40+U3*'Business Analysis'!$D$41)/5*100,0) -> 87 | W3: =IF(V3>=90,"Critical",IF(V3>=75,"High",IF(V3>=60,"Medium",IF(V3>=40,"Low","Optional")))) -> High | X3: / | Y3: Optimize | Z3: Support keyword - weave into H2s, FAQs and internal anchor text.
A4: limbaugh stephenson family and implant dentistry | B4: Brand | C4: Brand | D4: Brand & Practice Name | E4: Navigational | F4: BOFU | G4: Secondary | H4: 40 | I4: SEO Market Estimate | J4: 4 | K4: SERP Competition Analysis | L4: 3.5 | M4: Commercial Intent Analysis | N4: =IF(J4<=20,"Low",IF(J4<=40,"Moderate",IF(J4<=70,"Competitive","Very Competitive"))) -> Low | O4: familyandimplantdentists.com (own); Healthgrades; Yelp; Facebook | P4: 5 | Q4: =IF(H4>=2000,5,IF(H4>=800,4,IF(H4>=300,3,IF(H4>=100,2,1)))) -> 1 | R4: =IF(J4<=25,5,IF(J4<=35,4,IF(J4<=45,3,IF(J4<=60,2,1)))) -> 5 | S4: 4 | T4: 5 | U4: 4 | V4: =ROUND((P4*'Business Analysis'!$D$36+Q4*'Business Analysis'!$D$37+R4*'Business Analysis'!$D$38+S4*'Business Analysis'!$D$39+T4*'Business Analysis'!$D$40+U4*'Business Analysis'!$D$41)/5*100,0) -> 87 | W4: =IF(V4>=90,"Critical",IF(V4>=75,"High",IF(V4>=60,"Medium",IF(V4>=40,"Low","Optional")))) -> High | X4: / | Y4: Optimize | Z4: Support keyword - weave into H2s, FAQs and internal anchor text.
A5: family and implant dentists huntsville | B5: Brand | C5: Brand | D5: Brand & Practice Name | E5: Navigational | F5: BOFU | G5: Secondary | H5: 30 | I5: SEO Market Estimate | J5: 7 | K5: SERP Competition Analysis | L5: 4 | M5: Commercial Intent Analysis | N5: =IF(J5<=20,"Low",IF(J5<=40,"Moderate",IF(J5<=70,"Competitive","Very Competitive"))) -> Low | O5: familyandimplantdentists.com (own); Healthgrades; Yelp; Facebook | P5: 5 | Q5: =IF(H5>=2000,5,IF(H5>=800,4,IF(H5>=300,3,IF(H5>=100,2,1)))) -> 1 | R5: =IF(J5<=25,5,IF(J5<=35,4,IF(J5<=45,3,IF(J5<=60,2,1)))) -> 5 | S5: 4 | T5: 5 | U5: 4 | V5: =ROUND((P5*'Business Analysis'!$D$36+Q5*'Business Analysis'!$D$37+R5*'Business Analysis'!$D$38+S5*'Business Analysis'!$D$39+T5*'Business Analysis'!$D$40+U5*'Business Analysis'!$D$41)/5*100,0) -> 87 | W5: =IF(V5>=90,"Critical",IF(V5>=75,"High",IF(V5>=60,"Medium",IF(V5>=40,"Low","Optional")))) -> High | X5: / | Y5: Optimize | Z5: Support keyword - weave into H2s, FAQs and internal anchor text.
A6: limbaugh and stephenson dentistry reviews | B6: Brand | C6: Brand | D6: Brand & Practice Name | E6: Navigational | F6: MOFU | G6: Secondary | H6: 30 | I6: SEO Market Estimate | J6: 5 | K6: SERP Competition Analysis | L6: 2.1 | M6: Commercial Intent Analysis | N6: =IF(J6<=20,"Low",IF(J6<=40,"Moderate",IF(J6<=70,"Competitive","Very Competitive"))) -> Low | O6: familyandimplantdentists.com (own); Healthgrades; Yelp; Facebook | P6: 4 | Q6: =IF(H6>=2000,5,IF(H6>=800,4,IF(H6>=300,3,IF(H6>=100,2,1)))) -> 1 | R6: =IF(J6<=25,5,IF(J6<=35,4,IF(J6<=45,3,IF(J6<=60,2,1)))) -> 5 | S6: 4 | T6: 3 | U6: 4 | V6: =ROUND((P6*'Business Analysis'!$D$36+Q6*'Business Analysis'!$D$37+R6*'Business Analysis'!$D$38+S6*'Business Analysis'!$D$39+T6*'Business Analysis'!$D$40+U6*'Business Analysis'!$D$41)/5*100,0) -> 74 | W6: =IF(V6>=90,"Critical",IF(V6>=75,"High",IF(V6>=60,"Medium",IF(V6>=40,"Low","Optional")))) -> Medium | X6: / | Y6: Optimize | Z6: Support keyword - weave into H2s, FAQs and internal anchor text.
A7: limbaugh and stephenson dentist phone number | B7: Brand | C7: Brand | D7: Brand & Practice Name | E7: Navigational | F7: BOFU | G7: Secondary | H7: 20 | I7: SEO Market Estimate | J7: 3 | K7: SERP Competition Analysis | L7: 1.5 | M7: Commercial Intent Analysis | N7: =IF(J7<=20,"Low",IF(J7<=40,"Moderate",IF(J7<=70,"Competitive","Very Competitive"))) -> Low | O7: familyandimplantdentists.com (own); Healthgrades; Yelp; Facebook | P7: 5 | Q7: =IF(H7>=2000,5,IF(H7>=800,4,IF(H7>=300,3,IF(H7>=100,2,1)))) -> 1 | R7: =IF(J7<=25,5,IF(J7<=35,4,IF(J7<=45,3,IF(J7<=60,2,1)))) -> 5 | S7: 4 | T7: 5 | U7: 4 | V7: =ROUND((P7*'Business Analysis'!$D$36+Q7*'Business Analysis'!$D$37+R7*'Business Analysis'!$D$38+S7*'Business Analysis'!$D$39+T7*'Business Analysis'!$D$40+U7*'Business Analysis'!$D$41)/5*100,0) -> 87 | W7: =IF(V7>=90,"Critical",IF(V7>=75,"High",IF(V7>=60,"Medium",IF(V7>=40,"Low","Optional")))) -> High | X7: / | Y7: Optimize | Z7: Support keyword - weave into H2s, FAQs and internal anchor text.
A8: dentist bellewood circle huntsville al | B8: Brand | C8: Brand | D8: Brand & Practice Name | E8: Navigational | F8: BOFU | G8: Secondary | H8: 20 | I8: SEO Market Estimate | J8: 3 | K8: SERP Competition Analysis | L8: 1.2 | M8: Commercial Intent Analysis | N8: =IF(J8<=20,"Low",IF(J8<=40,"Moderate",IF(J8<=70,"Competitive","Very Competitive"))) -> Low | O8: familyandimplantdentists.com (own); Healthgrades; Yelp; Facebook | P8: 5 | Q8: =IF(H8>=2000,5,IF(H8>=800,4,IF(H8>=300,3,IF(H8>=100,2,1)))) -> 1 | R8: =IF(J8<=25,5,IF(J8<=35,4,IF(J8<=45,3,IF(J8<=60,2,1)))) -> 5 | S8: 4 | T8: 5 | U8: 4 | V8: =ROUND((P8*'Business Analysis'!$D$36+Q8*'Business Analysis'!$D$37+R8*'Business Analysis'!$D$38+S8*'Business Analysis'!$D$39+T8*'Business Analysis'!$D$40+U8*'Business Analysis'!$D$41)/5*100,0) -> 87 | W8: =IF(V8>=90,"Critical",IF(V8>=75,"High",IF(V8>=60,"Medium",IF(V8>=40,"Low","Optional")))) -> High | X8: / | Y8: Optimize | Z8: Support keyword - weave into H2s, FAQs and internal anchor text.
A9: dr matt limbaugh dmd | B9: Brand | C9: Brand | D9: Dr. Matt Limbaugh Profile | E9: Navigational | F9: MOFU | G9: Primary | H9: 40 | I9: SEO Market Estimate | J9: 4 | K9: SERP Competition Analysis | L9: 2 | M9: Commercial Intent Analysis | N9: =IF(J9<=20,"Low",IF(J9<=40,"Moderate",IF(J9<=70,"Competitive","Very Competitive"))) -> Low | O9: Healthline; WebMD; Cleveland Clinic; Colgate | P9: 3 | Q9: =IF(H9>=2000,5,IF(H9>=800,4,IF(H9>=300,3,IF(H9>=100,2,1)))) -> 1 | R9: =IF(J9<=25,5,IF(J9<=35,4,IF(J9<=45,3,IF(J9<=60,2,1)))) -> 5 | S9: 4 | T9: 3 | U9: 4 | V9: =ROUND((P9*'Business Analysis'!$D$36+Q9*'Business Analysis'!$D$37+R9*'Business Analysis'!$D$38+S9*'Business Analysis'!$D$39+T9*'Business Analysis'!$D$40+U9*'Business Analysis'!$D$41)/5*100,0) -> 69 | W9: =IF(V9>=90,"Critical",IF(V9>=75,"High",IF(V9>=60,"Medium",IF(V9>=40,"Low","Optional")))) -> Medium | X9: /matt-limbaugh-dmd/ | Y9: Optimize | Z9: Doctor E-E-A-T page - add credentials, Person schema and review snippets.
A10: dr matthew limbaugh dentist huntsville al | B10: Brand | C10: Brand | D10: Dr. Matt Limbaugh Profile | E10: Navigational | F10: MOFU | G10: Secondary | H10: 30 | I10: SEO Market Estimate | J10: 4 | K10: SERP Competition Analysis | L10: 2 | M10: Commercial Intent Analysis | N10: =IF(J10<=20,"Low",IF(J10<=40,"Moderate",IF(J10<=70,"Competitive","Very Competitive"))) -> Low | O10: Healthgrades; Vitals; familyandimplantdentists.com (own) | P10: 3 | Q10: =IF(H10>=2000,5,IF(H10>=800,4,IF(H10>=300,3,IF(H10>=100,2,1)))) -> 1 | R10: =IF(J10<=25,5,IF(J10<=35,4,IF(J10<=45,3,IF(J10<=60,2,1)))) -> 5 | S10: 4 | T10: 3 | U10: 3 | V10: =ROUND((P10*'Business Analysis'!$D$36+Q10*'Business Analysis'!$D$37+R10*'Business Analysis'!$D$38+S10*'Business Analysis'!$D$39+T10*'Business Analysis'!$D$40+U10*'Business Analysis'!$D$41)/5*100,0) -> 67 | W10: =IF(V10>=90,"Critical",IF(V10>=75,"High",IF(V10>=60,"Medium",IF(V10>=40,"Low","Optional")))) -> Medium | X10: /matt-limbaugh-dmd/ | Y10: Optimize | Z10: Support keyword - weave into H2s, FAQs and internal anchor text.
A11: matt limbaugh dmd huntsville reviews | B11: Brand | C11: Brand | D11: Dr. Matt Limbaugh Profile | E11: Navigational | F11: MOFU | G11: Secondary | H11: 10 | I11: SEO Market Estimate | J11: 3 | K11: SERP Competition Analysis | L11: 1.4 | M11: Commercial Intent Analysis | N11: =IF(J11<=20,"Low",IF(J11<=40,"Moderate",IF(J11<=70,"Competitive","Very Competitive"))) -> Low | O11: Healthgrades; Vitals; familyandimplantdentists.com (own) | P11: 3 | Q11: =IF(H11>=2000,5,IF(H11>=800,4,IF(H11>=300,3,IF(H11>=100,2,1)))) -> 1 | R11: =IF(J11<=25,5,IF(J11<=35,4,IF(J11<=45,3,IF(J11<=60,2,1)))) -> 5 | S11: 4 | T11: 3 | U11: 3 | V11: =ROUND((P11*'Business Analysis'!$D$36+Q11*'Business Analysis'!$D$37+R11*'Business Analysis'!$D$38+S11*'Business Analysis'!$D$39+T11*'Business Analysis'!$D$40+U11*'Business Analysis'!$D$41)/5*100,0) -> 67 | W11: =IF(V11>=90,"Critical",IF(V11>=75,"High",IF(V11>=60,"Medium",IF(V11>=40,"Low","Optional")))) -> Medium | X11: /matt-limbaugh-dmd/ | Y11: Optimize | Z11: Support keyword - weave into H2s, FAQs and internal anchor text.
A12: dr matt stephenson dentist huntsville al | B12: Brand | C12: Brand | D12: Dr. Matt Stephenson Profile | E12: Navigational | F12: MOFU | G12: Primary | H12: 40 | I12: SEO Market Estimate | J12: 5 | K12: SERP Competition Analysis | L12: 2 | M12: Commercial Intent Analysis | N12: =IF(J12<=20,"Low",IF(J12<=40,"Moderate",IF(J12<=70,"Competitive","Very Competitive"))) -> Low | O12: Healthgrades; Vitals; familyandimplantdentists.com (own) | P12: 3 | Q12: =IF(H12>=2000,5,IF(H12>=800,4,IF(H12>=300,3,IF(H12>=100,2,1)))) -> 1 | R12: =IF(J12<=25,5,IF(J12<=35,4,IF(J12<=45,3,IF(J12<=60,2,1)))) -> 5 | S12: 4 | T12: 3 | U12: 4 | V12: =ROUND((P12*'Business Analysis'!$D$36+Q12*'Business Analysis'!$D$37+R12*'Business Analysis'!$D$38+S12*'Business Analysis'!$D$39+T12*'Business Analysis'!$D$40+U12*'Business Analysis'!$D$41)/5*100,0) -> 69 | W12: =IF(V12>=90,"Critical",IF(V12>=75,"High",IF(V12>=60,"Medium",IF(V12>=40,"Low","Optional")))) -> Medium | X12: /matt-stephenson-dmd/ | Y12: Optimize | Z12: Doctor E-E-A-T page - differentiate from other 'Stephenson' dentists nationally.
A13: matt stephenson dmd huntsville | B13: Brand | C13: Brand | D13: Dr. Matt Stephenson Profile | E13: Navigational | F13: MOFU | G13: Secondary | H13: 30 | I13: SEO Market Estimate | J13: 4 | K13: SERP Competition Analysis | L13: 1.9 | M13: Commercial Intent Analysis | N13: =IF(J13<=20,"Low",IF(J13<=40,"Moderate",IF(J13<=70,"Competitive","Very Competitive"))) -> Low | O13: Healthgrades; Vitals; familyandimplantdentists.com (own) | P13: 3 | Q13: =IF(H13>=2000,5,IF(H13>=800,4,IF(H13>=300,3,IF(H13>=100,2,1)))) -> 1 | R13: =IF(J13<=25,5,IF(J13<=35,4,IF(J13<=45,3,IF(J13<=60,2,1)))) -> 5 | S13: 4 | T13: 3 | U13: 3 | V13: =ROUND((P13*'Business Analysis'!$D$36+Q13*'Business Analysis'!$D$37+R13*'Business Analysis'!$D$38+S13*'Business Analysis'!$D$39+T13*'Business Analysis'!$D$40+U13*'Business Analysis'!$D$41)/5*100,0) -> 67 | W13: =IF(V13>=90,"Critical",IF(V13>=75,"High",IF(V13>=60,"Medium",IF(V13>=40,"Low","Optional")))) -> Medium | X13: /matt-stephenson-dmd/ | Y13: Optimize | Z13: Support keyword - weave into H2s, FAQs and internal anchor text.
... A227: do i need a referral for an implant dentist | B227: Informational | C227: Local Trust & Conversion | D227: AI Search & Conversational FAQ | E227: Informational | F227: TOFU | G227: Secondary | H227: 30 | I227: SEO Market Estimate | J227: 8 | K227: SERP Competition Analysis | L227: 2 | M227: Commercial Intent Analysis | N227: =IF(J227<=20,"Low",IF(J227<=40,"Moderate",IF(J227<=70,"Competitive","Very Competitive"))) -> Low | O227: Healthline; WebMD; Cleveland Clinic; Colgate | P227: 3 | Q227: =IF(H227>=2000,5,IF(H227>=800,4,IF(H227>=300,3,IF(H227>=100,2,1)))) -> 1 | R227: =IF(J227<=25,5,IF(J227<=35,4,IF(J227<=45,3,IF(J227<=60,2,1)))) -> 5 | S227: 1 | T227: 2 | U227: 4 | V227: =ROUND((P227*'Business Analysis'!$D$36+Q227*'Business Analysis'!$D$37+R227*'Business Analysis'!$D$38+S227*'Business Analysis'!$D$39+T227*'Business Analysis'!$D$40+U227*'Business Analysis'!$D$41)/5*100,0) -> 56 | W227: =IF(V227>=90,"Critical",IF(V227>=75,"High",IF(V227>=60,"Medium",IF(V227>=40,"Low","Optional")))) -> Low | X227: /huntsville-dental-faq/ | Y227: Create | Z227: Support keyword - weave into H2s, FAQs and internal anchor text.

Sheet Keyword Clusters
A1: Cluster Name | B1: Primary Keyword | C1: Secondary Keywords | D1: Questions | E1: Entities | F1: Intent | G1: Funnel Stage | H1: Recommended Page | I1: Page Type | J1: Keywords in Cluster | K1: Total Est. Cluster Volume
A2: Brand & Practice Name | B2: limbaugh and stephenson dentistry | C2: drs limbaugh and stephenson huntsville al; limbaugh stephenson family and implant dentistry; family and implant dentists huntsville; limbaugh and stephenson dentistry reviews; limbaugh and stephenson dentist phone number; dentist bellewood circle huntsville al | D2: Is Limbaugh & Stephenson accepting new patients? | E2: Limbaugh & Stephenson; SNL Dental PC; 4605 Bellewood Circle; (256) 539-6634; Dr. Limbaugh; Dr. Stephenson | F2: {=INDEX('Keyword Master Database'!$E$2:$E$227,MATCH(B2,'Keyword Master Database'!$A$2:$A$227,0))} -> Navigational | G2: {=INDEX('Keyword Master Database'!$F$2:$F$227,MATCH(B2,'Keyword Master Database'!$A$2:$A$227,0))} -> BOFU | H2: / | I2: Homepage | J2: =COUNTIF('Keyword Master Database'!$D$2:$D$227,A2) -> 7 | K2: =SUMIF('Keyword Master Database'!$D$2:$D$227,A2,'Keyword Master Database'!$H$2:$H$227) -> 280
A3: Dr. Matt Limbaugh Profile | B3: dr matt limbaugh dmd | C3: dr matthew limbaugh dentist huntsville al; matt limbaugh dmd huntsville reviews | D3: N/A (navigational / transactional cluster) | E3: Matt Limbaugh DMD; University of Alabama School of Dentistry; Huntsville | F3: {=INDEX('Keyword Master Database'!$E$2:$E$227,MATCH(B3,'Keyword Master Database'!$A$2:$A$227,0))} -> Navigational | G3: {=INDEX('Keyword Master Database'!$F$2:$F$227,MATCH(B3,'Keyword Master Database'!$A$2:$A$227,0))} -> MOFU | H3: /matt-limbaugh-dmd/ | I3: Doctor Profile | J3: =COUNTIF('Keyword Master Database'!$D$2:$D$227,A3) -> 3 | K3: =SUMIF('Keyword Master Database'!$D$2:$D$227,A3,'Keyword Master Database'!$H$2:$H$227) -> 80
A4: Dr. Matt Stephenson Profile | B4: dr matt stephenson dentist huntsville al | C4: matt stephenson dmd huntsville; dr stephenson dental implants huntsville | D4: N/A (navigational / transactional cluster) | E4: Matt Stephenson DMD; Birmingham-Southern College; Hartselle AL; Huntsville | F4: {=INDEX('Keyword Master Database'!$E$2:$E$227,MATCH(B4,'Keyword Master Database'!$A$2:$A$227,0))} -> Navigational | G4: {=INDEX('Keyword Master Database'!$F$2:$F$227,MATCH(B4,'Keyword Master Database'!$A$2:$A$227,0))} -> MOFU | H4: /matt-stephenson-dmd/ | I4: Doctor Profile | J4: =COUNTIF('Keyword Master Database'!$D$2:$D$227,A4) -> 3 | K4: =SUMIF('Keyword Master Database'!$D$2:$D$227,A4,'Keyword Master Database'!$H$2:$H$227) -> 80
A5: Huntsville Dentist (Local Hub) | B5: dentist huntsville al | C5: dentist in huntsville alabama; huntsville dentist; best dentist in huntsville al; dentist near me huntsville al; dental office huntsville al; general dentist huntsville al; top rated dentist huntsville al; dentist accepting new patients huntsville al | D5: Who is a good family dentist in Huntsville, AL? | E5: Huntsville; Madison County; Southeast Huntsville; family dentist; general dentist; new patients | F5: {=INDEX('Keyword Master Database'!$E$2:$E$227,MATCH(B5,'Keyword Master Database'!$A$2:$A$227,0))} -> Transactional | G5: {=INDEX('Keyword Master Database'!$F$2:$F$227,MATCH(B5,'Keyword Master Database'!$A$2:$A$227,0))} -> BOFU | H5: / | I5: Homepage | J5: =COUNTIF('Keyword Master Database'!$D$2:$D$227,A5) -> 10 | K5: =SUMIF('Keyword Master Database'!$D$2:$D$227,A5,'Keyword Master Database'!$H$2:$H$227) -> 5370
A6: Family Dentistry | B6: family dentist huntsville al | C6: family dentist vs general dentist; family dentistry huntsville; family dentist near me huntsville al; dentist for the whole family huntsville | D6: What does a family dentist do? | E6: family dentist; general dentist; children; adults; seniors; preventive care; cleanings; exams | F6: {=INDEX('Keyword Master Database'!$E$2:$E$227,MATCH(B6,'Keyword Master Database'!$A$2:$A$227,0))} -> Transactional | G6: {=INDEX('Keyword Master Database'!$F$2:$F$227,MATCH(B6,'Keyword Master Database'!$A$2:$A$227,0))} -> BOFU | H6: /family-dentistry-huntsville-al/ (new) | I6: Service Hub Page | J6: =COUNTIF('Keyword Master Database'!$D$2:$D$227,A6) -> 6 | K6: =SUMIF('Keyword Master Database'!$D$2:$D$227,A6,'Keyword Master Database'!$H$2:$H$227) -> 2290
A7: Cleanings & Exams | B7: teeth cleaning huntsville al | C7: dental cleaning cost without insurance; dental cleaning huntsville al; dental checkup huntsville al; dental exam and cleaning huntsville | D7: How often should you get your teeth cleaned? | What happens during a dental cleaning? | E7: dental cleaning; hygienist; X-rays; oral exam; checkup; preventive care | F7: {=INDEX('Keyword Master Database'!$E$2:$E$227,MATCH(B7,'Keyword Master Database'!$A$2:$A$227,0))} -> Transactional | G7: {=INDEX('Keyword Master Database'!$F$2:$F$227,MATCH(B7,'Keyword Master Database'!$A$2:$A$227,0))} -> BOFU | H7: /dental-cleanings-exams-huntsville-al/ (new) | I7: Service Page | J7: =COUNTIF('Keyword Master Database'!$D$2:$D$227,A7) -> 7 | K7: =SUMIF('Keyword Master Database'!$D$2:$D$227,A7,'Keyword Master Database'!$H$2:$H$227) -> 9480
A8: Pediatric & Kids Dentistry | B8: kids dentist huntsville al | C8: children's dentist huntsville al; pediatric dentistry huntsville al | D8: When should a child first see a dentist? | E8: children's teeth; first dental visit; sealants; fluoride; family dentist | F8: {=INDEX('Keyword Master Database'!$E$2:$E$227,MATCH(B8,'Keyword Master Database'!$A$2:$A$227,0))} -> Transactional | G8: {=INDEX('Keyword Master Database'!$F$2:$F$227,MATCH(B8,'Keyword Master Database'!$A$2:$A$227,0))} -> BOFU | H8: /pediatric-dentistry-huntsville-al/ (new) | I8: Service Page | J8: =COUNTIF('Keyword Master Database'!$D$2:$D$227,A8) -> 4 | K8: =SUMIF('Keyword Master Database'!$D$2:$D$227,A8,'Keyword Master Database'!$H$2:$H$227) -> 2270
A9: Emergency Dentistry | B9: emergency dentist huntsville al | C9: cracked tooth symptoms; emergency dentist near me huntsville al; same day dentist appointment huntsville al; toothache dentist huntsville al; broken tooth repair huntsville al; chipped tooth repair huntsville al | D9: What to do for a broken tooth? | E9: toothache; broken tooth; chipped tooth; same-day appointment; dental pain | F9: {=INDEX('Keyword Master Database'!$E$2:$E$227,MATCH(B9,'Keyword Master Database'!$A$2:$A$227,0))} -> Transactional | G9: {=INDEX('Keyword Master Database'!$F$2:$F$227,MATCH(B9,'Keyword Master Database'!$A$2:$A$227,0))} -> BOFU | H9: /emergency-dentist-huntsville-al/ (new) | I9: Service Page | J9: =COUNTIF('Keyword Master Database'!$D$2:$D$227,A9) -> 8 | K9: =SUMIF('Keyword Master Database'!$D$2:$D$227,A9,'Keyword Master Database'!$H$2:$H$227) -> 7370
A10: Dental Implants (Core) | B10: dental implants huntsville al | C10: dental implants huntsville alabama; dental implant dentist huntsville al; dental implants near me huntsville; best dental implants huntsville al; tooth implants huntsville al; implant dentist near me huntsville; single tooth implant huntsville al | D10: N/A (navigational / transactional cluster) | E10: dental implant; titanium post; abutment; implant crown; osseointegration; single tooth implant; implant dentist | F10: {=INDEX('Keyword Master Database'!$E$2:$E$227,MATCH(B10,'Keyword Master Database'!$A$2:$A$227,0))} -> Transactional | G10: {=INDEX('Keyword Master Database'!$F$2:$F$227,MATCH(B10,'Keyword Master Database'!$A$2:$A$227,0))} -> BOFU | H10: /tooth-implants/ | I10: Pillar Service Page | J10: =COUNTIF('Keyword Master Database'!$D$2:$D$227,A10) -> 8 | K10: =SUMIF('Keyword Master Database'!$D$2:$D$227,A10,'Keyword Master Database'!$H$2:$H$227) -> 1330
A11: Implant Cost & Financing | B11: dental implant cost huntsville al | C11: dental implant cost; single tooth implant cost; carecredit dental implants; affordable dental implants huntsville al; dental implants financing huntsville al | D11: How much do dental implants cost in alabama? | Does dental insurance cover implants? | E11: implant cost; CareCredit; Citi Health Card; dental insurance; financing; payment plans | F11: {=INDEX('Keyword Master Database'!$E$2:$E$227,MATCH(B11,'Keyword Master Database'!$A$2:$A$227,0))} -> Transactional | G11: {=INDEX('Keyword Master Database'!$F$2:$F$227,MATCH(B11,'Keyword Master Database'!$A$2:$A$227,0))} -> BOFU | H11: /dental-implant-cost-huntsville-al/ (new) | I11: Cost Guide Page | J11: =COUNTIF('Keyword Master Database'!$D$2:$D$227,A11) -> 8 | K11: =SUMIF('Keyword Master Database'!$D$2:$D$227,A11,'Keyword Master Database'!$H$2:$H$227) -> 25040
A12: Implant Candidacy & Procedure | B12: am i a candidate for dental implants | C12: dental implant procedure step by step; dental implants with diabetes; enough bone for dental implants | D12: Am i a candidate for dental implants? | Are dental implants painful? | How long do dental implants last? | Can smokers get dental implants? | What is a dental implant? | E12: bone density; healthy gums; smokers; diabetes; implant procedure; consultation; 3D imaging | F12: {=INDEX('Keyword Master Database'!$E$2:$E$227,MATCH(B12,'Keyword Master Database'!$A$2:$A$227,0))} -> Informational | G12: {=INDEX('Keyword Master Database'!$F$2:$F$227,MATCH(B12,'Keyword Master Database'!$A$2:$A$227,0))} -> TOFU | H12: /blog/am-i-a-candidate-for-dental-implants/ (new) | I12: Blog Guide | J12: =COUNTIF('Keyword Master Database'!$D$2:$D$227,A12) -> 8 | K12: =SUMIF('Keyword Master Database'!$D$2:$D$227,A12,'Keyword Master Database'!$H$2:$H$227) -> 28150
A13: Implant Recovery & Aftercare | B13: dental implant recovery time | C13: dental implant healing stages; signs of dental implant failure; dental implant aftercare instructions | D13: What to eat after dental implant surgery? | E13: healing stages; aftercare; soft foods; implant failure; osseointegration | F13: {=INDEX('Keyword Master Database'!$E$2:$E$227,MATCH(B13,'Keyword Master Database'!$A$2:$A$227,0))} -> Informational | G13: {=INDEX('Keyword Master Database'!$F$2:$F$227,MATCH(B13,'Keyword Master Database'!$A$2:$A$227,0))} -> TOFU | H13: /blog/dental-implant-recovery-timeline/ (new) | I13: Blog Guide | J13: =COUNTIF('Keyword Master Database'!$D$2:$D$227,A13) -> 5 | K13: =SUMIF('Keyword Master Database'!$D$2:$D$227,A13,'Keyword Master Database'!$H$2:$H$227) -> 7920
... A41: AI Search & Conversational FAQ | B41: who is the best dentist for dental implants in huntsville al | C41: - | D41: Who is the best dentist for dental implants in huntsville al? | Where can i get dental implants in huntsville al? | What dentist does implants and crowns in huntsville? | Is a family dentist or specialist better for dental implants? | How much do dental implants cost in huntsville al? | E41: Huntsville; dental implants; family dentist; cost; insurance; financing; new patients | F41: {=INDEX('Keyword Master Database'!$E$2:$E$227,MATCH(B41,'Keyword Master Database'!$A$2:$A$227,0))} -> Commercial | G41: {=INDEX('Keyword Master Database'!$F$2:$F$227,MATCH(B41,'Keyword Master Database'!$A$2:$A$227,0))} -> MOFU | H41: /huntsville-dental-faq/ (new) | I41: FAQ Hub Page | J41: =COUNTIF('Keyword Master Database'!$D$2:$D$227,A41) -> 8 | K41: =SUMIF('Keyword Master Database'!$D$2:$D$227,A41,'Keyword Master Database'!$H$2:$H$227) -> 330

Sheet Competitor Analysis
A1: Competitor | B1: URL | C1: Ranking Topics | D1: Strong Pages | E1: Weakness | F1: Content Gap | G1: Opportunity
A2: Dr. Mark Stephenson DDS - Conroe, TX | B2: https://www.markstephensondds.com/ | C2: Hospital sedation dentistry; special-needs and medically compromised patient care; pediatric hospital-based dentistry (Conroe, TX). | D2: Homepage (credentials, hospital privileges); Meet Your Dentists. | E2: Out of market (Texas); referral-based practice; small Wix site with limited service content. | F2: No general, cosmetic or implant service pages. | G2: Not a Huntsville competitor - very low keyword overlap. Reference only; do not benchmark rankings against it.
A3: Smile HSV - Jennifer H. Drummond DMD | B3: https://smilehsv.com/ | C3: Huntsville general dentistry and brand terms; new-patient and payments pages. | D3: Homepage; Services page; New Patient page. | E3: Homepage title is only 'Smile HSV'; thin copy; site-builder template; single Services page rather than individual treatment pages. | F3: No visible blog, cost guides, location pages or per-service landing pages in site navigation. | G3: Genuine local competitor. Outrank with dedicated service+Huntsville pages, FAQs and cost content.
A4: Stevenson Dental - Indianapolis, IN | B4: https://stevensondds.com/ | C4: Indianapolis family dentistry with focus on implant restorations. | D4: Homepage with Google-reviews widget (5.0 stars, 231 reviews shown) and click-to-call / click-to-text CTAs. | E4: Out of market (Indiana); single-page style site. | F4: Few dedicated treatment pages visible from the homepage. | G4: Not a local competitor. Borrow conversion patterns: city in title tag, on-page review feed, text-us CTA.
A5: Huntsville Periodontal & Implant Specialists - Madison, AL | B5: https://huntsvilleperio.com/ | C5: Dental implants, immediate implants, full-arch, ridge augmentation, sinus lift, gum grafting, scaling & root planing, crown lengthening, extractions. | D5: /services/ (long page with anchor sections); patient-education and post-operative instruction pages; referral page. | E5: All treatments live on one /services/ page via anchors (no individual URLs); homepage title duplicates the brand name; specialist/referral model, limited restorative and family care. | F5: No visible cost guides, comparison content or family-dentistry content. | G5: Most important implant competitor. Win 'dental implants Huntsville' with dedicated pages, cost + FAQ content and the one-office implant-plus-restoration advantage.
A6: Lawrence P. Stephenson DDS - North Providence, RI | B6: https://lawrencepstephenson.com/ | C6: North Providence dentistry; cosmetic, emergency, sleep-apnea mouth guards, teeth whitening. | D6: Homepage; Sleep Apnea page. | E6: Out of market (Rhode Island). | F6: Not applicable to Huntsville. | G6: Not a local competitor. Name-match only - exclude from rank benchmarking.
A7: W. Timothy Brooks DMD, PC | B7: https://my.officite.com/0074099 (Officite-hosted; confirm primary domain) | C7: Family dentistry Huntsville; implants, mini implants, implant-supported dentures; TMJ, sleep apnea, sedation; Opalescence whitening; Invisalign; serves Huntsville, Madison and Decatur. | D7: Family dentistry page; blog posts such as 'Find a Family Dentist in Huntsville, AL'. | E7: To validate with a live crawl (template-based site; page depth and schema not yet audited). | F7: To validate. | G7: Closest content competitor for 'family dentist Huntsville' and implant queries. Out-build with richer city-modified pages and cost/FAQ content.
A8: King Dental - David King, DMD | B8: https://www.drkingdentistry.com/ | C8: Dental implants positioning; same-day crowns, Invisalign, veneers, dentures, whitening, laser treatment, composite bonding (1108 Gleneagles Dr SW). | D8: /services/dental-implants/ (promoted via an October 2023 press release). | E8: To validate with a live crawl. | F8: To validate. | G8: Implant-focused competitor. Compete on cost transparency, FAQs and comparison content.
A9: JDR, Inc. (drjdreed.com) | B9: https://www.drjdreed.com | C9: Family, cosmetic and implant dentistry; crowns, veneers, dentures, root canals, extractions, Zoom whitening (2338 Pansy St SW; solo practice per directory listing). | D9: Practice site (service pages to be audited). | E9: To validate with a live crawl. | F9: To validate. | G9: Direct service overlap with the client. Monitor for family + implant keyword overlap.
A10: Dentistry Today | B10: Directory profile: practicefinder.newpatientsinc.com/dental/dentistry-today-huntsville-al/ | C10: Cosmetic, general and family dentistry; same-day crowns, veneers, Invisalign, whitening; online booking (2801 Memorial Pkwy SW). | D10: Practice profile lists 4.9/5 on about 200 Google reviews (directory data). | E10: To validate with a live crawl. | F10: To validate. | G10: Review-volume and online-booking benchmark for local pack competition.

Sheet Keyword Mapping
A1: URL | B1: Page Name | C1: Primary Keyword | D1: Secondary Keywords | E1: Intent | F1: Funnel Stage | G1: Existing/New | H1: Action | I1: Cannibalization Risk
A2: / | B2: Homepage | C2: limbaugh and stephenson dentistry | D2: drs limbaugh and stephenson huntsville al; limbaugh stephenson family and implant dentistry; family and implant dentists huntsville; limbaugh and stephenson dentistry reviews; dentist huntsville al; dentist in huntsville alabama | E2: {=INDEX('Keyword Master Database'!$E$2:$E$227,MATCH(C2,'Keyword Master Database'!$A$2:$A$227,0))} -> Navigational | F2: {=INDEX('Keyword Master Database'!$F$2:$F$227,MATCH(C2,'Keyword Master Database'!$A$2:$A$227,0))} -> BOFU | G2: Existing | H2: Optimize | I2: Medium
A3: /matt-limbaugh-dmd/ | B3: Meet Dr. Limbaugh | C3: dr matt limbaugh dmd | D3: dr matthew limbaugh dentist huntsville al; matt limbaugh dmd huntsville reviews | E3: {=INDEX('Keyword Master Database'!$E$2:$E$227,MATCH(C3,'Keyword Master Database'!$A$2:$A$227,0))} -> Navigational | F3: {=INDEX('Keyword Master Database'!$F$2:$F$227,MATCH(C3,'Keyword Master Database'!$A$2:$A$227,0))} -> MOFU | G3: Existing | H3: Optimize | I3: Low
A4: /matt-stephenson-dmd/ | B4: Meet Dr. Stephenson | C4: dr matt stephenson dentist huntsville al | D4: matt stephenson dmd huntsville; dr stephenson dental implants huntsville | E4: {=INDEX('Keyword Master Database'!$E$2:$E$227,MATCH(C4,'Keyword Master Database'!$A$2:$A$227,0))} -> Navigational | F4: {=INDEX('Keyword Master Database'!$F$2:$F$227,MATCH(C4,'Keyword Master Database'!$A$2:$A$227,0))} -> MOFU | G4: Existing | H4: Optimize | I4: Low
A5: /family-dentistry-huntsville-al/ | B5: Family Dentistry Huntsville | C5: family dentist huntsville al | D5: family dentist vs general dentist; family dentistry huntsville; family dentist near me huntsville al; dentist for the whole family huntsville | E5: {=INDEX('Keyword Master Database'!$E$2:$E$227,MATCH(C5,'Keyword Master Database'!$A$2:$A$227,0))} -> Transactional | F5: {=INDEX('Keyword Master Database'!$F$2:$F$227,MATCH(C5,'Keyword Master Database'!$A$2:$A$227,0))} -> BOFU | G5: New | H5: Create | I5: Medium
A6: /dental-cleanings-exams-huntsville-al/ | B6: Cleanings & Exams | C6: teeth cleaning huntsville al | D6: dental cleaning cost without insurance; dental cleaning huntsville al; dental checkup huntsville al; dental exam and cleaning huntsville | E6: {=INDEX('Keyword Master Database'!$E$2:$E$227,MATCH(C6,'Keyword Master Database'!$A$2:$A$227,0))} -> Transactional | F6: {=INDEX('Keyword Master Database'!$F$2:$F$227,MATCH(C6,'Keyword Master Database'!$A$2:$A$227,0))} -> BOFU | G6: New | H6: Create | I6: Low
A7: /pediatric-dentistry-huntsville-al/ | B7: Pediatric Dentistry | C7: kids dentist huntsville al | D7: children's dentist huntsville al; pediatric dentistry huntsville al | E7: {=INDEX('Keyword Master Database'!$E$2:$E$227,MATCH(C7,'Keyword Master Database'!$A$2:$A$227,0))} -> Transactional | F7: {=INDEX('Keyword Master Database'!$F$2:$F$227,MATCH(C7,'Keyword Master Database'!$A$2:$A$227,0))} -> BOFU | G7: New | H7: Create | I7: Low
A8: /emergency-dentist-huntsville-al/ | B8: Emergency Dentist | C8: emergency dentist huntsville al | D8: cracked tooth symptoms; emergency dentist near me huntsville al; same day dentist appointment huntsville al; toothache dentist huntsville al | E8: {=INDEX('Keyword Master Database'!$E$2:$E$227,MATCH(C8,'Keyword Master Database'!$A$2:$A$227,0))} -> Transactional | F8: {=INDEX('Keyword Master Database'!$F$2:$F$227,MATCH(C8,'Keyword Master Database'!$A$2:$A$227,0))} -> BOFU | G8: New | H8: Create | I8: Low
A9: /tooth-implants/ | B9: Dental Implants | C9: dental implants huntsville al | D9: dental implants huntsville alabama; dental implant dentist huntsville al; dental implants near me huntsville; best dental implants huntsville al | E9: {=INDEX('Keyword Master Database'!$E$2:$E$227,MATCH(C9,'Keyword Master Database'!$A$2:$A$227,0))} -> Transactional | F9: {=INDEX('Keyword Master Database'!$F$2:$F$227,MATCH(C9,'Keyword Master Database'!$A$2:$A$227,0))} -> BOFU | G9: Existing | H9: Optimize | I9: Medium
A10: /dental-implant-cost-huntsville-al/ | B10: Dental Implant Cost | C10: dental implant cost huntsville al | D10: dental implant cost; single tooth implant cost; carecredit dental implants; affordable dental implants huntsville al | E10: {=INDEX('Keyword Master Database'!$E$2:$E$227,MATCH(C10,'Keyword Master Database'!$A$2:$A$227,0))} -> Transactional | F10: {=INDEX('Keyword Master Database'!$F$2:$F$227,MATCH(C10,'Keyword Master Database'!$A$2:$A$227,0))} -> BOFU | G10: New | H10: Create | I10: Medium
A11: /blog/am-i-a-candidate-for-dental-implants/ | B11: Am I a Candidate for Dental Implants? | C11: am i a candidate for dental implants | D11: dental implant procedure step by step; dental implants with diabetes; enough bone for dental implants | E11: {=INDEX('Keyword Master Database'!$E$2:$E$227,MATCH(C11,'Keyword Master Database'!$A$2:$A$227,0))} -> Informational | F11: {=INDEX('Keyword Master Database'!$F$2:$F$227,MATCH(C11,'Keyword Master Database'!$A$2:$A$227,0))} -> TOFU | G11: New | H11: Create | I11: Low
A12: /blog/dental-implant-recovery-timeline/ | B12: Dental Implant Recovery Timeline | C12: dental implant recovery time | D12: dental implant healing stages; signs of dental implant failure; dental implant aftercare instructions | E12: {=INDEX('Keyword Master Database'!$E$2:$E$227,MATCH(C12,'Keyword Master Database'!$A$2:$A$227,0))} -> Informational | F12: {=INDEX('Keyword Master Database'!$F$2:$F$227,MATCH(C12,'Keyword Master Database'!$A$2:$A$227,0))} -> TOFU | G12: New | H12: Create | I12: Low
A13: /replacing-missing-teeth-huntsville-al/ | B13: Replacing Missing Teeth | C13: replace missing tooth huntsville al | D13: dental implants vs dentures; dental implants vs bridge; missing tooth replacement options; implant vs bridge cost | E13: {=INDEX('Keyword Master Database'!$E$2:$E$227,MATCH(C13,'Keyword Master Database'!$A$2:$A$227,0))} -> Commercial | F13: {=INDEX('Keyword Master Database'!$F$2:$F$227,MATCH(C13,'Keyword Master Database'!$A$2:$A$227,0))} -> MOFU | G13: New | H13: Create | I13: Medium
... A39: /restorative-dentistry-huntsville-al/ | B39: Restorative Dentistry Huntsville | C39: restorative dentistry huntsville al | D39: restorative dentist huntsville al; tooth restoration huntsville al | E39: {=INDEX('Keyword Master Database'!$E$2:$E$227,MATCH(C39,'Keyword Master Database'!$A$2:$A$227,0))} -> Transactional | F39: {=INDEX('Keyword Master Database'!$F$2:$F$227,MATCH(C39,'Keyword Master Database'!$A$2:$A$227,0))} -> BOFU | G39: New | H39: Create | I39: Low
A40: /huntsville-dental-faq/ | B40: Huntsville Dental FAQ | C40: who is the best dentist for dental implants in huntsville al | E40: {=INDEX('Keyword Master Database'!$E$2:$E$227,MATCH(C40,'Keyword Master Database'!$A$2:$A$227,0))} -> Commercial | F40: {=INDEX('Keyword Master Database'!$F$2:$F$227,MATCH(C40,'Keyword Master Database'!$A$2:$A$227,0))} -> MOFU | G40: New | H40: Create | I40: Medium
A41: /about-our-practice/ | B41: About Our Practice | C41: (trust page - no primary keyword) | D41: limbaugh and stephenson dentistry; family and implant dentists huntsville | E41: Navigational | F41: MOFU | G41: Existing | H41: Keep | I41: Low
A42: /office-tour/ | B42: Office Tour | C42: (trust page - no primary keyword) | D42: - | E42: Navigational | F42: MOFU | G42: Existing | H42: Keep | I42: Low
A43: /contact-us/ | B43: Contact Us | C43: (conversion page - no primary keyword) | D43: limbaugh and stephenson dentist phone number | E43: Navigational | F43: BOFU | G43: Existing | H43: Keep | I43: Low
A44: /request-appointment/ | B44: Request Appointment | C44: (conversion page - no primary keyword) | D44: new patient dentist huntsville al | E44: Transactional | F44: BOFU | G44: Existing | H44: Keep | I44: Low
A45: /blog/ | B45: Blog Index | C45: (index page - no primary keyword) | D45: - | E45: Informational | F45: TOFU | G45: Existing | H45: Optimize | I45: Low
A46: /cosmetic-dentistry-smile-tell-story/ | B46: Cosmetic Dentistry: Let Your Smile Tell the Story (old post) | C46: cosmetic dentist huntsville al | D46: Merge content into /cosmetic-dentistry-huntsville-al/ | E46: Commercial | F46: MOFU | G46: Existing | H46: Merge & Redirect (301) | I46: High

Sheet Topical Authority Map
A1: Main Topic | B1: Sub Topics | C1: Supporting Content | D1: Entities | E1: Commercial Connection
A2: Dental Implants & Tooth Replacement | B2: Single-tooth implants; implant-supported bridges; implant-supported dentures; candidacy; procedure; recovery; cost & financing; implants vs dentures vs bridges | C2: Candidacy guide; recovery timeline; cost page; who places implants; replacing missing teeth hub; implant FAQ | D2: titanium implant; abutment; crown; bone graft; osseointegration; periodontist; oral surgeon | E2: Highest-value service - implant consultations and full-arch cases
A3: Dentures & Bridges | B3: Full and partial dentures; denture cost and care; bridges and types; implant-supported alternatives | C3: How much do dentures cost; denture care; bridge lifespan; bridge vs implant comparison | D3: full denture; partial denture; pontic; abutment; relining | E3: Tooth-replacement consultations; denture-to-implant upgrades
A4: Restorative Dentistry | B4: Crowns; fillings; root canals; extractions; restorative hub | C4: Crown guide; composite vs amalgam; root canal vs extraction; extraction aftercare | D4: porcelain; zirconia; composite resin; endodontics; dry socket | E4: High-frequency treatment appointments and urgent-care leads
A5: Cosmetic Dentistry | B5: Veneers; whitening; smile makeover; cosmetic hub | C5: Veneers pros & cons; veneers vs crowns/bonding; professional vs at-home whitening; whitening safety | D5: porcelain veneer; laminate; peroxide; enamel; shade; smile design | E5: Elective high-margin cosmetic consultations
A6: Family & Preventive Dentistry | B6: Family dentistry; cleanings & exams; pediatric; sealants; emergency | C6: First dental visit guide; cleaning frequency; sealants for kids; emergency dental guide | D6: hygienist; X-ray; fluoride; sealant; recall | E6: New-patient acquisition and recurring hygiene revenue
A7: Full Mouth Reconstruction | B7: Process; candidates; cost; worn teeth; bite; combination treatments | C7: Full mouth reconstruction guide; before & after; cost; timeline | D7: bite; occlusion; implants; crowns; bridges; dentures | E7: Highest-ticket comprehensive cases
A8: Cost, Insurance & Financing | B8: Insurance acceptance; CareCredit; Citi Health Card; payment plans; no-insurance options | C8: Financial arrangements page; implant cost; denture cost; cleaning cost without insurance | D8: CareCredit; Citi Health Card; claims; assignment of benefits | E8: Removes price barriers and supports BOFU conversions
A9: Local Trust & Huntsville Authority | B9: Doctors; office tour; reviews; service areas (Southeast Huntsville, Hampton Cove, Madison); NAP consistency | C9: Doctor profiles; area pages; review snippets; community content | D9: Dr. Limbaugh; Dr. Stephenson; 4605 Bellewood Circle; Huntsville; Madison County | E9: Local pack and branded search conversion
A10: AI Search & Conversational FAQ | B10: Natural-language questions about implants, family dentistry, cost and finding a dentist in Huntsville | C10: Huntsville dental FAQ hub; FAQPage schema on every service page; concise answer blocks | D10: Huntsville; implants; family dentist; cost; insurance; new patients | E10: Citations in AI Overviews, ChatGPT and Perplexity answers

Sheet SEO Silo Architecture
A1: Silo | B1: Parent Page | C1: Child Pages | D1: Purpose | E1: Internal Linking Flow
A2: Silo 1 - Dental Implants | B2: /tooth-implants/ | C2: /dental-implant-cost-huntsville-al/ /blog/am-i-a-candidate-for-dental-implants/ /blog/dental-implant-recovery-timeline/ /blog/who-places-dental-implants-dentist-periodontist-oral-surgeon/ /implant-supported-dentures-huntsville-al/ | D2: Own implant keywords locally and nationally | E2: Hub <-> spokes; every spoke links to the pillar and /request-appointment/; cost page links to /financial-arrangements/
A3: Silo 2 - Tooth Replacement | B3: /replacing-missing-teeth-huntsville-al/ | C3: /dentures/ /dental-bridges/ /implant-supported-dentures-huntsville-al/ /blog/how-much-do-dentures-cost-in-alabama/ | D3: Capture comparison-stage searchers deciding between options | E3: Hub compares options and links to each service page; implant pages cross-link back to the hub
A4: Silo 3 - Restorative Dentistry | B4: /restorative-dentistry-huntsville-al/ | C4: /dental-crowns/ /tooth-fillings/ /root-canals/ /extractions/ /blog/dental-crowns-guide-types-cost-lifespan/ /blog/tooth-colored-fillings-vs-silver-amalgam/ /blog/root-canal-vs-extraction-what-to-expect/ /blog/tooth-extraction-aftercare-guide/ | D4: Build authority for everyday restorative treatments | E4: Hub -> service pages -> education posts -> back to service page; root canal and extraction cross-link
A5: Silo 4 - Cosmetic Dentistry | B5: /cosmetic-dentistry-huntsville-al/ | C5: /veneers-for-teeth/ /teeth-whitening/ /professional-teeth-whitening-say-cheese/ /blog/porcelain-veneers-pros-cons-lifespan/ | D5: Capture elective cosmetic demand | E5: Hub -> veneers and whitening; posts feed service pages; veneers and whitening cross-link
A6: Silo 5 - Family & Preventive | B6: /family-dentistry-huntsville-al/ | C6: /dental-cleanings-exams-huntsville-al/ /pediatric-dentistry-huntsville-al/ /sealants/ /emergency-dentist-huntsville-al/ | D6: New-patient and family recall acquisition | E6: Hub -> preventive pages; pediatric <-> sealants; emergency links to request appointment
A7: Silo 6 - Full Mouth Reconstruction | B7: /full-mouth-reconstruction/ | C7: /blog/full-mouth-reconstruction-guide-process-cost/ | D7: Support the highest-ticket comprehensive treatment | E7: Pillar links to implants, crowns, bridges and dentures; guide links back to pillar
A8: Silo 7 - Local Trust & Conversion | B8: / | C8: /dentist-southeast-huntsville-al/ /dentist-hampton-cove-al/ /dentist-madison-al/ /matt-limbaugh-dmd/ /matt-stephenson-dmd/ /financial-arrangements/ /huntsville-dental-faq/ /request-appointment/ | D8: Local SEO, trust signals and conversion | E8: Homepage <-> area, doctor and finance pages; FAQ hub links to every service pillar

Sheet Internal Linking Blueprint
A1: Source Page | B1: Target Page | C1: Anchor Concept | D1: Purpose
A2: /tooth-implants/ | B2: /dental-implant-cost-huntsville-al/ | C2: dental implant cost huntsville al | D2: Hub-to-spoke: pass authority and help users reach the supporting page
A3: /dental-implant-cost-huntsville-al/ | B3: /tooth-implants/ | C3: dental implants huntsville al | D3: Spoke-to-hub: reinforce topical relevance of the pillar page
A4: /tooth-implants/ | B4: /blog/am-i-a-candidate-for-dental-implants/ | C4: am i a candidate for dental implants | D4: Hub-to-spoke: pass authority and help users reach the supporting page
A5: /blog/am-i-a-candidate-for-dental-implants/ | B5: /tooth-implants/ | C5: dental implants huntsville al | D5: Spoke-to-hub: reinforce topical relevance of the pillar page
A6: /tooth-implants/ | B6: /blog/dental-implant-recovery-timeline/ | C6: dental implant recovery time | D6: Hub-to-spoke: pass authority and help users reach the supporting page
A7: /blog/dental-implant-recovery-timeline/ | B7: /tooth-implants/ | C7: dental implants huntsville al | D7: Spoke-to-hub: reinforce topical relevance of the pillar page
A8: /tooth-implants/ | B8: /blog/who-places-dental-implants-dentist-periodontist-oral-surgeon/ | C8: dentist vs periodontist for dental implants | D8: Hub-to-spoke: pass authority and help users reach the supporting page
A9: /blog/who-places-dental-implants-dentist-periodontist-oral-surgeon/ | B9: /tooth-implants/ | C9: dental implants huntsville al | D9: Spoke-to-hub: reinforce topical relevance of the pillar page
A10: /tooth-implants/ | B10: /implant-supported-dentures-huntsville-al/ | C10: implant supported dentures huntsville al | D10: Hub-to-spoke: pass authority and help users reach the supporting page
A11: /implant-supported-dentures-huntsville-al/ | B11: /tooth-implants/ | C11: dental implants huntsville al | D11: Spoke-to-hub: reinforce topical relevance of the pillar page
A12: /replacing-missing-teeth-huntsville-al/ | B12: /dentures/ | C12: dentures huntsville al | D12: Hub-to-spoke: pass authority and help users reach the supporting page
... A123: /cosmetic-dentistry-smile-tell-story/ | B123: /cosmetic-dentistry-huntsville-al/ | C123: cosmetic dentist huntsville al | D123: 301 consolidation: transfer equity from old post

Sheet Content Roadmap
A1: Timeline | B1: Priority | C1: Content Type | D1: Title | E1: Target Keyword | F1: Search Intent | G1: Funnel Stage | H1: URL | I1: Business Goal
A2: Month 1 | B2: {=INDEX('Keyword Master Database'!$W$2:$W$227,MATCH(E2,'Keyword Master Database'!$A$2:$A$227,0))} -> High | C2: On-page optimization | D2: Homepage: title, H1, meta, Dentist schema and Huntsville service grid | E2: dentist huntsville al | F2: {=INDEX('Keyword Master Database'!$E$2:$E$227,MATCH(E2,'Keyword Master Database'!$A$2:$A$227,0))} -> Transactional | G2: {=INDEX('Keyword Master Database'!$F$2:$F$227,MATCH(E2,'Keyword Master Database'!$A$2:$A$227,0))} -> BOFU | H2: / | I2: Generate more local leads
A3: Month 1 | B3: {=INDEX('Keyword Master Database'!$W$2:$W$227,MATCH(E3,'Keyword Master Database'!$A$2:$A$227,0))} -> High | C3: Service page optimization | D3: Dental Implants pillar rewrite with FAQs, process, candidacy and schema | E3: dental implants huntsville al | F3: {=INDEX('Keyword Master Database'!$E$2:$E$227,MATCH(E3,'Keyword Master Database'!$A$2:$A$227,0))} -> Transactional | G3: {=INDEX('Keyword Master Database'!$F$2:$F$227,MATCH(E3,'Keyword Master Database'!$A$2:$A$227,0))} -> BOFU | H3: /tooth-implants/ | I3: Improve service page rankings
A4: Month 1 | B4: {=INDEX('Keyword Master Database'!$W$2:$W$227,MATCH(E4,'Keyword Master Database'!$A$2:$A$227,0))} -> High | C4: Service page optimization | D4: Full Mouth Reconstruction page expansion | E4: full mouth reconstruction huntsville al | F4: {=INDEX('Keyword Master Database'!$E$2:$E$227,MATCH(E4,'Keyword Master Database'!$A$2:$A$227,0))} -> Transactional | G4: {=INDEX('Keyword Master Database'!$F$2:$F$227,MATCH(E4,'Keyword Master Database'!$A$2:$A$227,0))} -> BOFU | H4: /full-mouth-reconstruction/ | I4: Improve service page rankings
A5: Month 1 | B5: {=INDEX('Keyword Master Database'!$W$2:$W$227,MATCH(E5,'Keyword Master Database'!$A$2:$A$227,0))} -> Critical | C5: Service page optimization | D5: Porcelain Veneers page optimization with gallery | E5: porcelain veneers huntsville al | F5: {=INDEX('Keyword Master Database'!$E$2:$E$227,MATCH(E5,'Keyword Master Database'!$A$2:$A$227,0))} -> Transactional | G5: {=INDEX('Keyword Master Database'!$F$2:$F$227,MATCH(E5,'Keyword Master Database'!$A$2:$A$227,0))} -> BOFU | H5: /veneers-for-teeth/ | I5: Improve service page rankings
A6: Month 1 | B6: {=INDEX('Keyword Master Database'!$W$2:$W$227,MATCH(E6,'Keyword Master Database'!$A$2:$A$227,0))} -> High | C6: Service page optimization | D6: Dentures page optimization | E6: dentures huntsville al | F6: {=INDEX('Keyword Master Database'!$E$2:$E$227,MATCH(E6,'Keyword Master Database'!$A$2:$A$227,0))} -> Transactional | G6: {=INDEX('Keyword Master Database'!$F$2:$F$227,MATCH(E6,'Keyword Master Database'!$A$2:$A$227,0))} -> BOFU | H6: /dentures/ | I6: Improve service page rankings
A7: Month 1 | B7: {=INDEX('Keyword Master Database'!$W$2:$W$227,MATCH(E7,'Keyword Master Database'!$A$2:$A$227,0))} -> High | C7: Service page optimization | D7: Dental Crowns page optimization | E7: dental crowns huntsville al | F7: {=INDEX('Keyword Master Database'!$E$2:$E$227,MATCH(E7,'Keyword Master Database'!$A$2:$A$227,0))} -> Transactional | G7: {=INDEX('Keyword Master Database'!$F$2:$F$227,MATCH(E7,'Keyword Master Database'!$A$2:$A$227,0))} -> BOFU | H7: /dental-crowns/ | I7: Improve service page rankings
A8: Month 1 | B8: {=INDEX('Keyword Master Database'!$W$2:$W$227,MATCH(E8,'Keyword Master Database'!$A$2:$A$227,0))} -> High | C8: Service page optimization | D8: Root Canals page optimization | E8: root canal huntsville al | F8: {=INDEX('Keyword Master Database'!$E$2:$E$227,MATCH(E8,'Keyword Master Database'!$A$2:$A$227,0))} -> Transactional | G8: {=INDEX('Keyword Master Database'!$F$2:$F$227,MATCH(E8,'Keyword Master Database'!$A$2:$A$227,0))} -> BOFU | H8: /root-canals/ | I8: Improve service page rankings
A9: Month 1 | B9: {=INDEX('Keyword Master Database'!$W$2:$W$227,MATCH(E9,'Keyword Master Database'!$A$2:$A$227,0))} -> High | C9: Service page optimization | D9: Teeth Whitening page optimization | E9: teeth whitening huntsville al | F9: {=INDEX('Keyword Master Database'!$E$2:$E$227,MATCH(E9,'Keyword Master Database'!$A$2:$A$227,0))} -> Transactional | G9: {=INDEX('Keyword Master Database'!$F$2:$F$227,MATCH(E9,'Keyword Master Database'!$A$2:$A$227,0))} -> BOFU | H9: /teeth-whitening/ | I9: Improve service page rankings
A10: Month 1 | B10: {=INDEX('Keyword Master Database'!$W$2:$W$227,MATCH(E10,'Keyword Master Database'!$A$2:$A$227,0))} -> High | C10: Trust page optimization | D10: Financial Arrangements: insurance, CareCredit, payment plans | E10: dentist that accepts insurance huntsville al | F10: {=INDEX('Keyword Master Database'!$E$2:$E$227,MATCH(E10,'Keyword Master Database'!$A$2:$A$227,0))} -> Transactional | G10: {=INDEX('Keyword Master Database'!$F$2:$F$227,MATCH(E10,'Keyword Master Database'!$A$2:$A$227,0))} -> BOFU | H10: /financial-arrangements/ | I10: Generate more local leads
A11: Month 1 | B11: {=INDEX('Keyword Master Database'!$W$2:$W$227,MATCH(E11,'Keyword Master Database'!$A$2:$A$227,0))} -> Medium | C11: Brand / E-E-A-T | D11: Doctor profile enhancements (Person schema, credentials) | E11: dr matt limbaugh dmd | F11: {=INDEX('Keyword Master Database'!$E$2:$E$227,MATCH(E11,'Keyword Master Database'!$A$2:$A$227,0))} -> Navigational | G11: {=INDEX('Keyword Master Database'!$F$2:$F$227,MATCH(E11,'Keyword Master Database'!$A$2:$A$227,0))} -> MOFU | H11: /matt-limbaugh-dmd/ | I11: Build topical authority
A12: Month 1 | B12: {=INDEX('Keyword Master Database'!$W$2:$W$227,MATCH(E12,'Keyword Master Database'!$A$2:$A$227,0))} -> Medium | C12: Brand / E-E-A-T | D12: Doctor profile enhancements (Person schema, credentials) | E12: dr matt stephenson dentist huntsville al | F12: {=INDEX('Keyword Master Database'!$E$2:$E$227,MATCH(E12,'Keyword Master Database'!$A$2:$A$227,0))} -> Navigational | G12: {=INDEX('Keyword Master Database'!$F$2:$F$227,MATCH(E12,'Keyword Master Database'!$A$2:$A$227,0))} -> MOFU | H12: /matt-stephenson-dmd/ | I12: Build topical authority
A13: Month 2 | B13: {=INDEX('Keyword Master Database'!$W$2:$W$227,MATCH(E13,'Keyword Master Database'!$A$2:$A$227,0))} -> Critical | C13: New service page | D13: Dental Implant Cost in Huntsville, AL: pricing factors and financing | E13: dental implant cost huntsville al | F13: {=INDEX('Keyword Master Database'!$E$2:$E$227,MATCH(E13,'Keyword Master Database'!$A$2:$A$227,0))} -> Transactional | G13: {=INDEX('Keyword Master Database'!$F$2:$F$227,MATCH(E13,'Keyword Master Database'!$A$2:$A$227,0))} -> BOFU | H13: /dental-implant-cost-huntsville-al/ | I13: Generate more local leads
... A40: Month 6 | B40: {=INDEX('Keyword Master Database'!$W$2:$W$227,MATCH(E40,'Keyword Master Database'!$A$2:$A$227,0))} -> Medium | C40: Location page | D40: Dentist near Madison, AL | E40: dentist madison al | F40: {=INDEX('Keyword Master Database'!$E$2:$E$227,MATCH(E40,'Keyword Master Database'!$A$2:$A$227,0))} -> Transactional | G40: {=INDEX('Keyword Master Database'!$F$2:$F$227,MATCH(E40,'Keyword Master Database'!$A$2:$A$227,0))} -> BOFU | H40: /dentist-madison-al/ | I40: Generate more local leads

Sheet Quick Wins
A1: Keyword | B1: Intent | C1: Funnel Stage | D1: Opportunity | E1: Reason | F1: Recommended Action
A2: limbaugh and stephenson dentistry | B2: {=INDEX('Keyword Master Database'!$E$2:$E$227,MATCH(A2,'Keyword Master Database'!$A$2:$A$227,0))} -> Navigational | C2: {=INDEX('Keyword Master Database'!$F$2:$F$227,MATCH(A2,'Keyword Master Database'!$A$2:$A$227,0))} -> BOFU | D2: Own the brand SERP and knowledge panel | E2: Very low KD; branded searches should convert at the highest rate. | F2: Fix homepage title tag, align NAP with Google Business Profile and add Dentist schema.
A3: carecredit dentist huntsville al | B3: {=INDEX('Keyword Master Database'!$E$2:$E$227,MATCH(A3,'Keyword Master Database'!$A$2:$A$227,0))} -> Transactional | C3: {=INDEX('Keyword Master Database'!$F$2:$F$227,MATCH(A3,'Keyword Master Database'!$A$2:$A$227,0))} -> BOFU | D3: Low-KD financing term that the site already supports | E3: Site already accepts CareCredit and Citi Health Card; almost no local competition. | F3: Add a CareCredit/financing section to /financial-arrangements/ and high-ticket pages.
A4: dental implants financing huntsville al | B4: {=INDEX('Keyword Master Database'!$E$2:$E$227,MATCH(A4,'Keyword Master Database'!$A$2:$A$227,0))} -> Transactional | C4: {=INDEX('Keyword Master Database'!$F$2:$F$227,MATCH(A4,'Keyword Master Database'!$A$2:$A$227,0))} -> BOFU | D4: Low-KD, high-CPC commercial term | E4: Implant buyers search for payment options before booking. | F4: Add a financing FAQ block to /tooth-implants/ and the cost page.
A5: implant supported dentures huntsville al | B5: {=INDEX('Keyword Master Database'!$E$2:$E$227,MATCH(A5,'Keyword Master Database'!$A$2:$A$227,0))} -> Transactional | C5: {=INDEX('Keyword Master Database'!$F$2:$F$227,MATCH(A5,'Keyword Master Database'!$A$2:$A$227,0))} -> BOFU | D5: Existing content with no dedicated page | E5: Implants page already explains lower dentures with as few as two implants. | F5: Spin out a dedicated page (confirm scope with the practice).
A6: take home teeth whitening trays huntsville | B6: {=INDEX('Keyword Master Database'!$E$2:$E$227,MATCH(A6,'Keyword Master Database'!$A$2:$A$227,0))} -> Transactional | C6: {=INDEX('Keyword Master Database'!$F$2:$F$227,MATCH(A6,'Keyword Master Database'!$A$2:$A$227,0))} -> BOFU | D6: Very low KD; site already offers at-home whitening | E6: Whitening page describes an at-home procedure requiring two visits. | F6: Add 'take-home whitening trays in Huntsville' section and FAQ to /teeth-whitening/.
A7: dentist southeast huntsville al | B7: {=INDEX('Keyword Master Database'!$E$2:$E$227,MATCH(A7,'Keyword Master Database'!$A$2:$A$227,0))} -> Transactional | C7: {=INDEX('Keyword Master Database'!$F$2:$F$227,MATCH(A7,'Keyword Master Database'!$A$2:$A$227,0))} -> BOFU | D7: Neighborhood-level local intent | E7: Office sits at 4605 Bellewood Cir SE; no area page exists. | F7: Create a Southeast Huntsville / 35802 page with map, directions and NAP.
A8: dentist hampton cove al | B8: {=INDEX('Keyword Master Database'!$E$2:$E$227,MATCH(A8,'Keyword Master Database'!$A$2:$A$227,0))} -> Transactional | C8: {=INDEX('Keyword Master Database'!$F$2:$F$227,MATCH(A8,'Keyword Master Database'!$A$2:$A$227,0))} -> BOFU | D8: Service-area expansion with low KD | E8: Low competition and a natural drive-in market from the southeast side. | F8: Create a short, unique service-area page with drive-time details.
A9: dentist vs periodontist for dental implants | B9: {=INDEX('Keyword Master Database'!$E$2:$E$227,MATCH(A9,'Keyword Master Database'!$A$2:$A$227,0))} -> Commercial | C9: {=INDEX('Keyword Master Database'!$F$2:$F$227,MATCH(A9,'Keyword Master Database'!$A$2:$A$227,0))} -> MOFU | D9: Comparison term with KD 20 | E9: Directly addresses the specialist competitor (huntsvilleperio.com) model. | F9: Publish a comparison guide stressing one-office implant + restoration.
A10: where can i get dental implants in huntsville al | B10: {=INDEX('Keyword Master Database'!$E$2:$E$227,MATCH(A10,'Keyword Master Database'!$A$2:$A$227,0))} -> Transactional | C10: {=INDEX('Keyword Master Database'!$F$2:$F$227,MATCH(A10,'Keyword Master Database'!$A$2:$A$227,0))} -> BOFU | D10: AI-search conversational query | E10: Natural-language prompts are answered by AI assistants; local competition is minimal. | F10: Add concise answer blocks plus FAQPage schema on a Huntsville FAQ hub.
A11: who is the best dentist for dental implants in huntsville al | B11: {=INDEX('Keyword Master Database'!$E$2:$E$227,MATCH(A11,'Keyword Master Database'!$A$2:$A$227,0))} -> Commercial | C11: {=INDEX('Keyword Master Database'!$F$2:$F$227,MATCH(A11,'Keyword Master Database'!$A$2:$A$227,0))} -> MOFU | D11: AI-search recommendation query | E11: Entity strength (reviews, doctors, credentials) determines AI citations. | F11: Strengthen reviews, doctor profiles and consistent NAP; add comparison-style FAQ.
A12: tooth colored fillings huntsville al | B12: {=INDEX('Keyword Master Database'!$E$2:$E$227,MATCH(A12,'Keyword Master Database'!$A$2:$A$227,0))} -> Transactional | C12: {=INDEX('Keyword Master Database'!$F$2:$F$227,MATCH(A12,'Keyword Master Database'!$A$2:$A$227,0))} -> BOFU | D12: Low KD restorative term | E12: Few local competitors target this phrasing. | F12: Add 'tooth-colored fillings' H2 and FAQ to /tooth-fillings/.
A13: dental sealants huntsville al | B13: {=INDEX('Keyword Master Database'!$E$2:$E$227,MATCH(A13,'Keyword Master Database'!$A$2:$A$227,0))} -> Transactional | C13: {=INDEX('Keyword Master Database'!$F$2:$F$227,MATCH(A13,'Keyword Master Database'!$A$2:$A$227,0))} -> BOFU | D13: Low KD preventive term | E13: Sealants page exists; keyword modifiers are missing. | F13: Add Huntsville modifier, kids and adult FAQs to /sealants/.
... A17: smile makeover huntsville al | B17: {=INDEX('Keyword Master Database'!$E$2:$E$227,MATCH(A17,'Keyword Master Database'!$A$2:$A$227,0))} -> Transactional | C17: {=INDEX('Keyword Master Database'!$F$2:$F$227,MATCH(A17,'Keyword Master Database'!$A$2:$A$227,0))} -> BOFU | D17: Low KD cosmetic term | E17: Consolidates veneers, whitening and crowns into one offer. | F17: Include in the new cosmetic hub with a consultation CTA.
